Workbook
Name GlobalCompany: Input!$C$6
Name GlobalMethod: Input!$C$8
Name DefaultResidual: Input!$C$9
Name FirstFYEnd: Input!$C$10
Name ReportingFYEnd: Input!$C$11
Name ScheduleIITable: Input!$C$15:$H$32
Name AssetCategories: Input!$C$15:$C$32
Name ITBlockTable: Input!$B$36:$F$47
Name ITBlockList: Input!$B$36:$B$47
Name ITFYEnd: 'Income-Tax Dep Chart'!$E$5
Name TaxRate: 'Book vs Tax (Def. Tax)'!$F$5

Sheet Input
B2: FIXED ASSET REGISTER | CONTROL PANEL
B3: Companies Act, 2013 – Schedule II • Single switch drives the whole register
B5: A. GLOBAL PARAMETERS (edit the yellow cells)
B6: Company Name | C6: ABC Manufacturing Pvt. Ltd. | E6: ↳ free text
B7: Reporting Currency | C7: INR (Rs.) | E7: display only
B8: Depreciation Method (Global) | C8: WDV | E8: ↳ pick SLM or WDV — recalculates everything
B9: Default Residual Value % | C9: 0.05 | E9: ↳ 5% per Schedule II guidance
B10: First Financial Year End | C10: 44286 | E10: ↳ anchor for the year columns
B11: Reporting Financial Year End | C11: 45747 | E11: ↳ must equal one of the FY columns
B12: No. of Year Columns in FAR | C12: 16 | E12: ↳ informational
B13: B. ASSET MASTER – SCHEDULE II USEFUL LIVES + INCOME-TAX BLOCK MAPPING
B14: Sr. | C14: Asset Category | D14: Description / Notes | E14: Useful Life (Years) | F14: Indicative WDV Rate* | G14: Income-Tax Block | H14: IT Dep Rate
B15: 1 | C15: Buildings - RCC Frame | D15: Buildings other than factory (RCC frame) | E15: 60 | F15: =IF(E15=0,0,1-(DefaultResidual)^(1/E15)) | G15: Building (General/Non-residential) | H15: 0.1
B16: 2 | C16: Buildings - Other than RCC | D16: Buildings other than factory (non-RCC) | E16: 30 | F16: =IF(E16=0,0,1-(DefaultResidual)^(1/E16)) | G16: Building (General/Non-residential) | H16: 0.1
B17: 3 | C17: Factory Building | D17: Factory buildings | E17: 30 | F17: =IF(E17=0,0,1-(DefaultResidual)^(1/E17)) | G17: Building (General/Non-residential) | H17: 0.1
B18: 4 | C18: Plant & Machinery - General | D18: General rate plant & machinery | E18: 15 | F18: =IF(E18=0,0,1-(DefaultResidual)^(1/E18)) | G18: Plant & Machinery (General) | H18: 0.15
B19: 5 | C19: Plant & Machinery - Continuous Process | D19: Continuous process plant | E19: 25 | F19: =IF(E19=0,0,1-(DefaultResidual)^(1/E19)) | G19: Plant & Machinery (General) | H19: 0.15
B20: 6 | C20: Furniture & Fittings | D20: General furniture and fittings | E20: 10 | F20: =IF(E20=0,0,1-(DefaultResidual)^(1/E20)) | G20: Furniture & Fittings | H20: 0.1
B21: 7 | C21: Office Equipment | D21: General office equipment | E21: 5 | F21: =IF(E21=0,0,1-(DefaultResidual)^(1/E21)) | G21: Plant & Machinery (General) | H21: 0.15
B22: 8 | C22: Computers - End User Devices | D22: Laptops, desktops, printers | E22: 3 | F22: =IF(E22=0,0,1-(DefaultResidual)^(1/E22)) | G22: Computers & Software | H22: 0.4
B23: 9 | C23: Computers - Servers & Networks | D23: Servers and network equipment | E23: 6 | F23: =IF(E23=0,0,1-(DefaultResidual)^(1/E23)) | G23: Computers & Software | H23: 0.4
B24: 10 | C24: Electrical Installations | D24: Electrical installations & equipment | E24: 10 | F24: =IF(E24=0,0,1-(DefaultResidual)^(1/E24)) | G24: Plant & Machinery (General) | H24: 0.15
B25: 11 | C25: Motor Vehicles - Motor Cars | D25: Cars (other than used in hire business) | E25: 8 | F25: =IF(E25=0,0,1-(DefaultResidual)^(1/E25)) | G25: Motor Vehicles (Non-hire) | H25: 0.15
B26: 12 | C26: Motor Vehicles - Commercial | D26: Buses/lorries used in business of hire | E26: 6 | F26: =IF(E26=0,0,1-(DefaultResidual)^(1/E26)) | G26: Motor Vehicles (Hire/Commercial) | H26: 0.3
... B32: 18 | C32: Leasehold Improvements | D32: Over primary lease period (illustrative) | E32: 10 | F32: =IF(E32=0,0,1-(DefaultResidual)^(1/E32)) | G32: Building (General/Non-residential) | H32: 0.1
B33: *Companies Act indicative WDV rate = 1 − (Residual)^(1/Useful Life). The Income-Tax block & rate (Sec. 32 / Appendix I, WDV) drive the Income-Tax Depreciation Chart. Edit rows freely – FAR & charts follow.
B34: C. INCOME-TAX BLOCK OF ASSETS – WDV RATES (Sec. 32, Appendix I)
B35: Block of Assets | F35: WDV Rate
B36: Building (Residential) | F36: 0.05
B37: Building (General/Non-residential) | F37: 0.1
B38: Building (Temporary Structures) | F38: 0.4
B39: Furniture & Fittings | F39: 0.1
B40: Plant & Machinery (General) | F40: 0.15
B41: Plant & Machinery (Energy-saving/Pollution) | F41: 0.4
B42: Motor Vehicles (Non-hire) | F42: 0.15
B43: Motor Vehicles (Hire/Commercial) | F43: 0.3
B44: Computers & Software | F44: 0.4
B45: Intangible Assets | F45: 0.25
B46: Ships | F46: 0.2
B47: Books (annual publications / lending library) | F47: 0.4

Sheet FAR
A1: REGISTER OF FIXED ASSETS (FAR)
A2: =Input!C6&" | Depreciation Method: "&GlobalMethod&" | Reporting FY ending: "&TEXT(ReportingFYEnd,"dd-mmm-yyyy")&" | Default Residual: "&TEXT(DefaultResidual,"0%")&" | Companies Act, 2013 – Schedule II (see Income-Tax Chart sheet for Sec. 32)"
A3: ASSET MASTER DETAILS | J3: DISPOSAL | K3: COST & DEPRECIATION BASIS | R3: POSITION AS ON REPORTING FY | V3: EXTRA-SHIFT (SCH. II) & CARO 2020 COMPLIANCE | AA3: =EDATE(FirstFYEnd,12*0) | AC3: =EDATE(FirstFYEnd,12*1) | AE3: =EDATE(FirstFYEnd,12*2) | AG3: =EDATE(FirstFYEnd,12*3) | AI3: =EDATE(FirstFYEnd,12*4) | AK3: =EDATE(FirstFYEnd,12*5) | AM3: =EDATE(FirstFYEnd,12*6) | AO3: =EDATE(FirstFYEnd,12*7) | AQ3: =EDATE(FirstFYEnd,12*8) | AS3: =EDATE(FirstFYEnd,12*9) | AU3: =EDATE(FirstFYEnd,12*10) | AW3: =EDATE(FirstFYEnd,12*11) | AY3: =EDATE(FirstFYEnd,12*12) | BA3: =EDATE(FirstFYEnd,12*13) | BC3: =EDATE(FirstFYEnd,12*14) | BE3: =EDATE(FirstFYEnd,12*15)
A4: Asset ID | B4: Asset Description | C4: Asset Category | D4: Location / Cost Centre | E4: Supplier / Vendor | F4: Invoice No. | G4: Date of Purchase | H4: Date Put to Use | I4: Date of Sale / Disposal | J4: Sale Proceeds (Rs.) | K4: Gross Cost (Rs.) | L4: Residual % | M4: Residual Value (Rs.) | N4: Useful Life (Yrs) | O4: Method | P4: WDV Rate | Q4: Depreciable Amt (Rs.) | R4: Dep – Reporting FY (Rs.) | S4: Acc. Dep – Rep. FY (Rs.) | T4: WDV – Reporting FY (Rs.) | U4: Status | V4: Shift Basis | W4: Shift Factor | X4: Date of Physical Verif. | Y4: Title Deed in Co. Name? | Z4: Remarks / Components | AA4: ="Dep "&TEXT(EDATE(FirstFYEnd,12*0),"yyyy") | AB4: ="WDV "&TEXT(EDATE(FirstFYEnd,12*0),"yyyy") | AC4: ="Dep "&TEXT(EDATE(FirstFYEnd,12*1),"yyyy") | AD4: ="WDV "&TEXT(EDATE(FirstFYEnd,12*1),"yyyy") | AE4: ="Dep "&TEXT(EDATE(FirstFYEnd,12*2),"yyyy") | AF4: ="WDV "&TEXT(EDATE(FirstFYEnd,12*2),"yyyy") | AG4: ="Dep "&TEXT(EDATE(FirstFYEnd,12*3),"yyyy") | AH4: ="WDV "&TEXT(EDATE(FirstFYEnd,12*3),"yyyy") | AI4: ="Dep "&TEXT(EDATE(FirstFYEnd,12*4),"yyyy") | AJ4: ="WDV "&TEXT(EDATE(FirstFYEnd,12*4),"yyyy") | AK4: ="Dep "&TEXT(EDATE(FirstFYEnd,12*5),"yyyy") | AL4: ="WDV "&TEXT(EDATE(FirstFYEnd,12*5),"yyyy") | AM4: ="Dep "&TEXT(EDATE(FirstFYEnd,12*6),"yyyy") | AN4: ="WDV "&TEXT(EDATE(FirstFYEnd,12*6),"yyyy") | AO4: ="Dep "&TEXT(EDATE(FirstFYEnd,12*7),"yyyy") | AP4: ="WDV "&TEXT(EDATE(FirstFYEnd,12*7),"yyyy") | AQ4: ="Dep "&TEXT(EDATE(FirstFYEnd,12*8),"yyyy") | AR4: ="WDV "&TEXT(EDATE(FirstFYEnd,12*8),"yyyy") | AS4: ="Dep "&TEXT(EDATE(FirstFYEnd,12*9),"yyyy") | AT4: ="WDV "&TEXT(EDATE(FirstFYEnd,12*9),"yyyy") | AU4: ="Dep "&TEXT(EDATE(FirstFYEnd,12*10),"yyyy") | AV4: ="WDV "&TEXT(EDATE(FirstFYEnd,12*10),"yyyy") | AW4: ="Dep "&TEXT(EDATE(FirstFYEnd,12*11),"yyyy") | AX4: ="WDV "&TEXT(EDATE(FirstFYEnd,12*11),"yyyy") | AY4: ="Dep "&TEXT(EDATE(FirstFYEnd,12*12),"yyyy") | AZ4: ="WDV "&TEXT(EDATE(FirstFYEnd,12*12),"yyyy") | BA4: ="Dep "&TEXT(EDATE(FirstFYEnd,12*13),"yyyy") | BB4: ="WDV "&TEXT(EDATE(FirstFYEnd,12*13),"yyyy") | BC4: ="Dep "&TEXT(EDATE(FirstFYEnd,12*14),"yyyy") | BD4: ="WDV "&TEXT(EDATE(FirstFYEnd,12*14),"yyyy") | BE4: ="Dep "&TEXT(EDATE(FirstFYEnd,12*15),"yyyy") | BF4: ="WDV "&TEXT(EDATE(FirstFYEnd,12*15),"yyyy")
A5: FA-001 | B5: Head Office Building | C5: Buildings - RCC Frame | D5: Mumbai HO | E5: Skyline Constructions | F5: INV-HO-001 | G5: 43922 | H5: 43922 | K5: 50000000 | L5: =DefaultResidual | M5: =IF($K5="","",$K5*$L5) | N5: =IF($C5="","",IFERROR(VLOOKUP($C5,ScheduleIITable,3,FALSE),"#N/A")) | O5: =IF($K5="","",GlobalMethod) | P5: =IF(OR($K5="",$N5="",$N5=0,$M5=0),0,1-($M5/$K5)^(1/$N5)) | Q5: =IF($K5="","",$K5-$M5) | R5: =IF($K5="","",INDEX($AA5:$BF5,1,MATCH(ReportingFYEnd,$AA$3:$BF$3,0))) | S5: =IF($K5="","",IF($U5="Disposed",0,$K5-$T5)) | T5: =IF($K5="","",INDEX($AA5:$BF5,1,MATCH(ReportingFYEnd,$AA$3:$BF$3,0)+1)) | U5: =IF($K5="","",IF(AND($I5<>"",$I5<=ReportingFYEnd),"Disposed",IF(OR($H5="",$H5>ReportingFYEnd),"Not Yet in Use","Active"))) | V5: Single | W5: =IF($V5="Double",1.5,IF($V5="Triple",2,1)) | Y5: =IF($K5="","",IF(OR(ISNUMBER(SEARCH("Build",$C5)),ISNUMBER(SEARCH("Lease",$C5))),"Yes","NA")) | AA5: =IF(OR($K5="",$H5=""),"",MIN(MAX(0,IF($O5="WDV",$K5*$P5*MAX(0,(IF($I5="",AA$3,MIN($I5,AA$3)))-(MAX($H5,(EDATE(AA$3,-12)+1)))+1)/(AA$3-(EDATE(AA$3,-12)+1)+1),IF($N5=0,0,$Q5/$N5*MAX(0,(IF($I5="",AA$3,MIN($I5,AA$3)))-(MAX($H5,(EDATE(AA$3,-12)+1)))+1)/(AA$3-(EDATE(AA$3,-12)+1)+1)))*$W5),MAX(0,$K5-$M5))) | AB5: =IF($K5="","",IF(AND($I5<>"",$I5<=AA$3),0,$K5-AA5)) | AC5: =IF(OR($K5="",$H5=""),"",MIN(MAX(0,IF($O5="WDV",AB5*$P5*MAX(0,(IF($I5="",AC$3,MIN($I5,AC$3)))-(MAX($H5,(EDATE(AC$3,-12)+1)))+1)/(AC$3-(EDATE(AC$3,-12)+1)+1),IF($N5=0,0,$Q5/$N5*MAX(0,(IF($I5="",AC$3,MIN($I5,AC$3)))-(MAX($H5,(EDATE(AC$3,-12)+1)))+1)/(AC$3-(EDATE(AC$3,-12)+1)+1)))*$W5),MAX(0,AB5-$M5))) | AD5: =IF($K5="","",IF(AND($I5<>"",$I5<=AC$3),0,AB5-AC5)) | AE5: =IF(OR($K5="",$H5=""),"",MIN(MAX(0,IF($O5="WDV",AD5*$P5*MAX(0,(IF($I5="",AE$3,MIN($I5,AE$3)))-(MAX($H5,(EDATE(AE$3,-12)+1)))+1)/(AE$3-(EDATE(AE$3,-12)+1)+1),IF($N5=0,0,$Q5/$N5*MAX(0,(IF($I5="",AE$3,MIN($I5,AE$3)))-(MAX($H5,(EDATE(AE$3,-12)+1)))+1)/(AE$3-(EDATE(AE$3,-12)+1)+1)))*$W5),MAX(0,AD5-$M5))) | AF5: =IF($K5="","",IF(AND($I5<>"",$I5<=AE$3),0,AD5-AE5)) | AG5: =IF(OR($K5="",$H5=""),"",MIN(MAX(0,IF($O5="WDV",AF5*$P5*MAX(0,(IF($I5="",AG$3,MIN($I5,AG$3)))-(MAX($H5,(EDATE(AG$3,-12)+1)))+1)/(AG$3-(EDATE(AG$3,-12)+1)+1),IF($N5=0,0,$Q5/$N5*MAX(0,(IF($I5="",AG$3,MIN($I5,AG$3)))-(MAX($H5,(EDATE(AG$3,-12)+1)))+1)/(AG$3-(EDATE(AG$3,-12)+1)+1)))*$W5),MAX(0,AF5-$M5))) | AH5: =IF($K5="","",IF(AND($I5<>"",$I5<=AG$3),0,AF5-AG5)) | AI5: =IF(OR($K5="",$H5=""),"",MIN(MAX(0,IF($O5="WDV",AH5*$P5*MAX(0,(IF($I5="",AI$3,MIN($I5,AI$3)))-(MAX($H5,(EDATE(AI$3,-12)+1)))+1)/(AI$3-(EDATE(AI$3,-12)+1)+1),IF($N5=0,0,$Q5/$N5*MAX(0,(IF($I5="",AI$3,MIN($I5,AI$3)))-(MAX($H5,(EDATE(AI$3,-12)+1)))+1)/(AI$3-(EDATE(AI$3,-12)+1)+1)))*$W5),MAX(0,AH5-$M5))) | AJ5: =IF($K5="","",IF(AND($I5<>"",$I5<=AI$3),0,AH5-AI5)) | AK5: =IF(OR($K5="",$H5=""),"",MIN(MAX(0,IF($O5="WDV",AJ5*$P5*MAX(0,(IF($I5="",AK$3,MIN($I5,AK$3)))-(MAX($H5,(EDATE(AK$3,-12)+1)))+1)/(AK$3-(EDATE(AK$3,-12)+1)+1),IF($N5=0,0,$Q5/$N5*MAX(0,(IF($I5="",AK$3,MIN($I5,AK$3)))-(MAX($H5,(EDATE(AK$3,-12)+1)))+1)/(AK$3-(EDATE(AK$3,-12)+1)+1)))*$W5),MAX(0,AJ5-$M5))) | AL5: =IF($K5="","",IF(AND($I5<>"",$I5<=AK$3),0,AJ5-AK5)) | AM5: =IF(OR($K5="",$H5=""),"",MIN(MAX(0,IF($O5="WDV",AL5*$P5*MAX(0,(IF($I5="",AM$3,MIN($I5,AM$3)))-(MAX($H5,(EDATE(AM$3,-12)+1)))+1)/(AM$3-(EDATE(AM$3,-12)+1)+1),IF($N5=0,0,$Q5/$N5*MAX(0,(IF($I5="",AM$3,MIN($I5,AM$3)))-(MAX($H5,(EDATE(AM$3,-12)+1)))+1)/(AM$3-(EDATE(AM$3,-12)+1)+1)))*$W5),MAX(0,AL5-$M5))) | AN5: =IF($K5="","",IF(AND($I5<>"",$I5<=AM$3),0,AL5-AM5)) | AO5: =IF(OR($K5="",$H5=""),"",MIN(MAX(0,IF($O5="WDV",AN5*$P5*MAX(0,(IF($I5="",AO$3,MIN($I5,AO$3)))-(MAX($H5,(EDATE(AO$3,-12)+1)))+1)/(AO$3-(EDATE(AO$3,-12)+1)+1),IF($N5=0,0,$Q5/$N5*MAX(0,(IF($I5="",AO$3,MIN($I5,AO$3)))-(MAX($H5,(EDATE(AO$3,-12)+1)))+1)/(AO$3-(EDATE(AO$3,-12)+1)+1)))*$W5),MAX(0,AN5-$M5))) | AP5: =IF($K5="","",IF(AND($I5<>"",$I5<=AO$3),0,AN5-AO5)) | AQ5: =IF(OR($K5="",$H5=""),"",MIN(MAX(0,IF($O5="WDV",AP5*$P5*MAX(0,(IF($I5="",AQ$3,MIN($I5,AQ$3)))-(MAX($H5,(EDATE(AQ$3,-12)+1)))+1)/(AQ$3-(EDATE(AQ$3,-12)+1)+1),IF($N5=0,0,$Q5/$N5*MAX(0,(IF($I5="",AQ$3,MIN($I5,AQ$3)))-(MAX($H5,(EDATE(AQ$3,-12)+1)))+1)/(AQ$3-(EDATE(AQ$3,-12)+1)+1)))*$W5),MAX(0,AP5-$M5))) | AR5: =IF($K5="","",IF(AND($I5<>"",$I5<=AQ$3),0,AP5-AQ5)) | AS5: =IF(OR($K5="",$H5=""),"",MIN(MAX(0,IF($O5="WDV",AR5*$P5*MAX(0,(IF($I5="",AS$3,MIN($I5,AS$3)))-(MAX($H5,(EDATE(AS$3,-12)+1)))+1)/(AS$3-(EDATE(AS$3,-12)+1)+1),IF($N5=0,0,$Q5/$N5*MAX(0,(IF($I5="",AS$3,MIN($I5,AS$3)))-(MAX($H5,(EDATE(AS$3,-12)+1)))+1)/(AS$3-(EDATE(AS$3,-12)+1)+1)))*$W5),MAX(0,AR5-$M5))) | AT5: =IF($K5="","",IF(AND($I5<>"",$I5<=AS$3),0,AR5-AS5)) | AU5: =IF(OR($K5="",$H5=""),"",MIN(MAX(0,IF($O5="WDV",AT5*$P5*MAX(0,(IF($I5="",AU$3,MIN($I5,AU$3)))-(MAX($H5,(EDATE(AU$3,-12)+1)))+1)/(AU$3-(EDATE(AU$3,-12)+1)+1),IF($N5=0,0,$Q5/$N5*MAX(0,(IF($I5="",AU$3,MIN($I5,AU$3)))-(MAX($H5,(EDATE(AU$3,-12)+1)))+1)/(AU$3-(EDATE(AU$3,-12)+1)+1)))*$W5),MAX(0,AT5-$M5))) | AV5: =IF($K5="","",IF(AND($I5<>"",$I5<=AU$3),0,AT5-AU5)) | AW5: =IF(OR($K5="",$H5=""),"",MIN(MAX(0,IF($O5="WDV",AV5*$P5*MAX(0,(IF($I5="",AW$3,MIN($I5,AW$3)))-(MAX($H5,(EDATE(AW$3,-12)+1)))+1)/(AW$3-(EDATE(AW$3,-12)+1)+1),IF($N5=0,0,$Q5/$N5*MAX(0,(IF($I5="",AW$3,MIN($I5,AW$3)))-(MAX($H5,(EDATE(AW$3,-12)+1)))+1)/(AW$3-(EDATE(AW$3,-12)+1)+1)))*$W5),MAX(0,AV5-$M5))) | AX5: =IF($K5="","",IF(AND($I5<>"",$I5<=AW$3),0,AV5-AW5)) | AY5: =IF(OR($K5="",$H5=""),"",MIN(MAX(0,IF($O5="WDV",AX5*$P5*MAX(0,(IF($I5="",AY$3,MIN($I5,AY$3)))-(MAX($H5,(EDATE(AY$3,-12)+1)))+1)/(AY$3-(EDATE(AY$3,-12)+1)+1),IF($N5=0,0,$Q5/$N5*MAX(0,(IF($I5="",AY$3,MIN($I5,AY$3)))-(MAX($H5,(EDATE(AY$3,-12)+1)))+1)/(AY$3-(EDATE(AY$3,-12)+1)+1)))*$W5),MAX(0,AX5-$M5))) | AZ5: =IF($K5="","",IF(AND($I5<>"",$I5<=AY$3),0,AX5-AY5)) | BA5: =IF(OR($K5="",$H5=""),"",MIN(MAX(0,IF($O5="WDV",AZ5*$P5*MAX(0,(IF($I5="",BA$3,MIN($I5,BA$3)))-(MAX($H5,(EDATE(BA$3,-12)+1)))+1)/(BA$3-(EDATE(BA$3,-12)+1)+1),IF($N5=0,0,$Q5/$N5*MAX(0,(IF($I5="",BA$3,MIN($I5,BA$3)))-(MAX($H5,(EDATE(BA$3,-12)+1)))+1)/(BA$3-(EDATE(BA$3,-12)+1)+1)))*$W5),MAX(0,AZ5-$M5))) | BB5: =IF($K5="","",IF(AND($I5<>"",$I5<=BA$3),0,AZ5-BA5)) | BC5: =IF(OR($K5="",$H5=""),"",MIN(MAX(0,IF($O5="WDV",BB5*$P5*MAX(0,(IF($I5="",BC$3,MIN($I5,BC$3)))-(MAX($H5,(EDATE(BC$3,-12)+1)))+1)/(BC$3-(EDATE(BC$3,-12)+1)+1),IF($N5=0,0,$Q5/$N5*MAX(0,(IF($I5="",BC$3,MIN($I5,BC$3)))-(MAX($H5,(EDATE(BC$3,-12)+1)))+1)/(BC$3-(EDATE(BC$3,-12)+1)+1)))*$W5),MAX(0,BB5-$M5))) | BD5: =IF($K5="","",IF(AND($I5<>"",$I5<=BC$3),0,BB5-BC5)) | BE5: =IF(OR($K5="",$H5=""),"",MIN(MAX(0,IF($O5="WDV",BD5*$P5*MAX(0,(IF($I5="",BE$3,MIN($I5,BE$3)))-(MAX($H5,(EDATE(BE$3,-12)+1)))+1)/(BE$3-(EDATE(BE$3,-12)+1)+1),IF($N5=0,0,$Q5/$N5*MAX(0,(IF($I5="",BE$3,MIN($I5,BE$3)))-(MAX($H5,(EDATE(BE$3,-12)+1)))+1)/(BE$3-(EDATE(BE$3,-12)+1)+1)))*$W5),MAX(0,BD5-$M5))) | BF5: =IF($K5="","",IF(AND($I5<>"",$I5<=BE$3),0,BD5-BE5))
A6: FA-002 | B6: Factory Shed - Unit 1 | C6: Factory Building | D6: Pune Plant | E6: BuildWell Ltd | F6: INV-FB-014 | G6: 44027 | H6: 44044 | K6: 18000000 | L6: =DefaultResidual | M6: =IF($K6="","",$K6*$L6) | N6: =IF($C6="","",IFERROR(VLOOKUP($C6,ScheduleIITable,3,FALSE),"#N/A")) | O6: =IF($K6="","",GlobalMethod) | P6: =IF(OR($K6="",$N6="",$N6=0,$M6=0),0,1-($M6/$K6)^(1/$N6)) | Q6: =IF($K6="","",$K6-$M6) | R6: =IF($K6="","",INDEX($AA6:$BF6,1,MATCH(ReportingFYEnd,$AA$3:$BF$3,0))) | S6: =IF($K6="","",IF($U6="Disposed",0,$K6-$T6)) | T6: =IF($K6="","",INDEX($AA6:$BF6,1,MATCH(ReportingFYEnd,$AA$3:$BF$3,0)+1)) | U6: =IF($K6="","",IF(AND($I6<>"",$I6<=ReportingFYEnd),"Disposed",IF(OR($H6="",$H6>ReportingFYEnd),"Not Yet in Use","Active"))) | V6: Single | W6: =IF($V6="Double",1.5,IF($V6="Triple",2,1)) | Y6: =IF($K6="","",IF(OR(ISNUMBER(SEARCH("Build",$C6)),ISNUMBER(SEARCH("Lease",$C6))),"Yes","NA")) | AA6: =IF(OR($K6="",$H6=""),"",MIN(MAX(0,IF($O6="WDV",$K6*$P6*MAX(0,(IF($I6="",AA$3,MIN($I6,AA$3)))-(MAX($H6,(EDATE(AA$3,-12)+1)))+1)/(AA$3-(EDATE(AA$3,-12)+1)+1),IF($N6=0,0,$Q6/$N6*MAX(0,(IF($I6="",AA$3,MIN($I6,AA$3)))-(MAX($H6,(EDATE(AA$3,-12)+1)))+1)/(AA$3-(EDATE(AA$3,-12)+1)+1)))*$W6),MAX(0,$K6-$M6))) | AB6: =IF($K6="","",IF(AND($I6<>"",$I6<=AA$3),0,$K6-AA6)) | AC6: =IF(OR($K6="",$H6=""),"",MIN(MAX(0,IF($O6="WDV",AB6*$P6*MAX(0,(IF($I6="",AC$3,MIN($I6,AC$3)))-(MAX($H6,(EDATE(AC$3,-12)+1)))+1)/(AC$3-(EDATE(AC$3,-12)+1)+1),IF($N6=0,0,$Q6/$N6*MAX(0,(IF($I6="",AC$3,MIN($I6,AC$3)))-(MAX($H6,(EDATE(AC$3,-12)+1)))+1)/(AC$3-(EDATE(AC$3,-12)+1)+1)))*$W6),MAX(0,AB6-$M6))) | AD6: =IF($K6="","",IF(AND($I6<>"",$I6<=AC$3),0,AB6-AC6)) | AE6: =IF(OR($K6="",$H6=""),"",MIN(MAX(0,IF($O6="WDV",AD6*$P6*MAX(0,(IF($I6="",AE$3,MIN($I6,AE$3)))-(MAX($H6,(EDATE(AE$3,-12)+1)))+1)/(AE$3-(EDATE(AE$3,-12)+1)+1),IF($N6=0,0,$Q6/$N6*MAX(0,(IF($I6="",AE$3,MIN($I6,AE$3)))-(MAX($H6,(EDATE(AE$3,-12)+1)))+1)/(AE$3-(EDATE(AE$3,-12)+1)+1)))*$W6),MAX(0,AD6-$M6))) | AF6: =IF($K6="","",IF(AND($I6<>"",$I6<=AE$3),0,AD6-AE6)) | AG6: =IF(OR($K6="",$H6=""),"",MIN(MAX(0,IF($O6="WDV",AF6*$P6*MAX(0,(IF($I6="",AG$3,MIN($I6,AG$3)))-(MAX($H6,(EDATE(AG$3,-12)+1)))+1)/(AG$3-(EDATE(AG$3,-12)+1)+1),IF($N6=0,0,$Q6/$N6*MAX(0,(IF($I6="",AG$3,MIN($I6,AG$3)))-(MAX($H6,(EDATE(AG$3,-12)+1)))+1)/(AG$3-(EDATE(AG$3,-12)+1)+1)))*$W6),MAX(0,AF6-$M6))) | AH6: =IF($K6="","",IF(AND($I6<>"",$I6<=AG$3),0,AF6-AG6)) | AI6: =IF(OR($K6="",$H6=""),"",MIN(MAX(0,IF($O6="WDV",AH6*$P6*MAX(0,(IF($I6="",AI$3,MIN($I6,AI$3)))-(MAX($H6,(EDATE(AI$3,-12)+1)))+1)/(AI$3-(EDATE(AI$3,-12)+1)+1),IF($N6=0,0,$Q6/$N6*MAX(0,(IF($I6="",AI$3,MIN($I6,AI$3)))-(MAX($H6,(EDATE(AI$3,-12)+1)))+1)/(AI$3-(EDATE(AI$3,-12)+1)+1)))*$W6),MAX(0,AH6-$M6))) | AJ6: =IF($K6="","",IF(AND($I6<>"",$I6<=AI$3),0,AH6-AI6)) | AK6: =IF(OR($K6="",$H6=""),"",MIN(MAX(0,IF($O6="WDV",AJ6*$P6*MAX(0,(IF($I6="",AK$3,MIN($I6,AK$3)))-(MAX($H6,(EDATE(AK$3,-12)+1)))+1)/(AK$3-(EDATE(AK$3,-12)+1)+1),IF($N6=0,0,$Q6/$N6*MAX(0,(IF($I6="",AK$3,MIN($I6,AK$3)))-(MAX($H6,(EDATE(AK$3,-12)+1)))+1)/(AK$3-(EDATE(AK$3,-12)+1)+1)))*$W6),MAX(0,AJ6-$M6))) | AL6: =IF($K6="","",IF(AND($I6<>"",$I6<=AK$3),0,AJ6-AK6)) | AM6: =IF(OR($K6="",$H6=""),"",MIN(MAX(0,IF($O6="WDV",AL6*$P6*MAX(0,(IF($I6="",AM$3,MIN($I6,AM$3)))-(MAX($H6,(EDATE(AM$3,-12)+1)))+1)/(AM$3-(EDATE(AM$3,-12)+1)+1),IF($N6=0,0,$Q6/$N6*MAX(0,(IF($I6="",AM$3,MIN($I6,AM$3)))-(MAX($H6,(EDATE(AM$3,-12)+1)))+1)/(AM$3-(EDATE(AM$3,-12)+1)+1)))*$W6),MAX(0,AL6-$M6))) | AN6: =IF($K6="","",IF(AND($I6<>"",$I6<=AM$3),0,AL6-AM6)) | AO6: =IF(OR($K6="",$H6=""),"",MIN(MAX(0,IF($O6="WDV",AN6*$P6*MAX(0,(IF($I6="",AO$3,MIN($I6,AO$3)))-(MAX($H6,(EDATE(AO$3,-12)+1)))+1)/(AO$3-(EDATE(AO$3,-12)+1)+1),IF($N6=0,0,$Q6/$N6*MAX(0,(IF($I6="",AO$3,MIN($I6,AO$3)))-(MAX($H6,(EDATE(AO$3,-12)+1)))+1)/(AO$3-(EDATE(AO$3,-12)+1)+1)))*$W6),MAX(0,AN6-$M6))) | AP6: =IF($K6="","",IF(AND($I6<>"",$I6<=AO$3),0,AN6-AO6)) | AQ6: =IF(OR($K6="",$H6=""),"",MIN(MAX(0,IF($O6="WDV",AP6*$P6*MAX(0,(IF($I6="",AQ$3,MIN($I6,AQ$3)))-(MAX($H6,(EDATE(AQ$3,-12)+1)))+1)/(AQ$3-(EDATE(AQ$3,-12)+1)+1),IF($N6=0,0,$Q6/$N6*MAX(0,(IF($I6="",AQ$3,MIN($I6,AQ$3)))-(MAX($H6,(EDATE(AQ$3,-12)+1)))+1)/(AQ$3-(EDATE(AQ$3,-12)+1)+1)))*$W6),MAX(0,AP6-$M6))) | AR6: =IF($K6="","",IF(AND($I6<>"",$I6<=AQ$3),0,AP6-AQ6)) | AS6: =IF(OR($K6="",$H6=""),"",MIN(MAX(0,IF($O6="WDV",AR6*$P6*MAX(0,(IF($I6="",AS$3,MIN($I6,AS$3)))-(MAX($H6,(EDATE(AS$3,-12)+1)))+1)/(AS$3-(EDATE(AS$3,-12)+1)+1),IF($N6=0,0,$Q6/$N6*MAX(0,(IF($I6="",AS$3,MIN($I6,AS$3)))-(MAX($H6,(EDATE(AS$3,-12)+1)))+1)/(AS$3-(EDATE(AS$3,-12)+1)+1)))*$W6),MAX(0,AR6-$M6))) | AT6: =IF($K6="","",IF(AND($I6<>"",$I6<=AS$3),0,AR6-AS6)) | AU6: =IF(OR($K6="",$H6=""),"",MIN(MAX(0,IF($O6="WDV",AT6*$P6*MAX(0,(IF($I6="",AU$3,MIN($I6,AU$3)))-(MAX($H6,(EDATE(AU$3,-12)+1)))+1)/(AU$3-(EDATE(AU$3,-12)+1)+1),IF($N6=0,0,$Q6/$N6*MAX(0,(IF($I6="",AU$3,MIN($I6,AU$3)))-(MAX($H6,(EDATE(AU$3,-12)+1)))+1)/(AU$3-(EDATE(AU$3,-12)+1)+1)))*$W6),MAX(0,AT6-$M6))) | AV6: =IF($K6="","",IF(AND($I6<>"",$I6<=AU$3),0,AT6-AU6)) | AW6: =IF(OR($K6="",$H6=""),"",MIN(MAX(0,IF($O6="WDV",AV6*$P6*MAX(0,(IF($I6="",AW$3,MIN($I6,AW$3)))-(MAX($H6,(EDATE(AW$3,-12)+1)))+1)/(AW$3-(EDATE(AW$3,-12)+1)+1),IF($N6=0,0,$Q6/$N6*MAX(0,(IF($I6="",AW$3,MIN($I6,AW$3)))-(MAX($H6,(EDATE(AW$3,-12)+1)))+1)/(AW$3-(EDATE(AW$3,-12)+1)+1)))*$W6),MAX(0,AV6-$M6))) | AX6: =IF($K6="","",IF(AND($I6<>"",$I6<=AW$3),0,AV6-AW6)) | AY6: =IF(OR($K6="",$H6=""),"",MIN(MAX(0,IF($O6="WDV",AX6*$P6*MAX(0,(IF($I6="",AY$3,MIN($I6,AY$3)))-(MAX($H6,(EDATE(AY$3,-12)+1)))+1)/(AY$3-(EDATE(AY$3,-12)+1)+1),IF($N6=0,0,$Q6/$N6*MAX(0,(IF($I6="",AY$3,MIN($I6,AY$3)))-(MAX($H6,(EDATE(AY$3,-12)+1)))+1)/(AY$3-(EDATE(AY$3,-12)+1)+1)))*$W6),MAX(0,AX6-$M6))) | AZ6: =IF($K6="","",IF(AND($I6<>"",$I6<=AY$3),0,AX6-AY6)) | BA6: =IF(OR($K6="",$H6=""),"",MIN(MAX(0,IF($O6="WDV",AZ6*$P6*MAX(0,(IF($I6="",BA$3,MIN($I6,BA$3)))-(MAX($H6,(EDATE(BA$3,-12)+1)))+1)/(BA$3-(EDATE(BA$3,-12)+1)+1),IF($N6=0,0,$Q6/$N6*MAX(0,(IF($I6="",BA$3,MIN($I6,BA$3)))-(MAX($H6,(EDATE(BA$3,-12)+1)))+1)/(BA$3-(EDATE(BA$3,-12)+1)+1)))*$W6),MAX(0,AZ6-$M6))) | BB6: =IF($K6="","",IF(AND($I6<>"",$I6<=BA$3),0,AZ6-BA6)) | BC6: =IF(OR($K6="",$H6=""),"",MIN(MAX(0,IF($O6="WDV",BB6*$P6*MAX(0,(IF($I6="",BC$3,MIN($I6,BC$3)))-(MAX($H6,(EDATE(BC$3,-12)+1)))+1)/(BC$3-(EDATE(BC$3,-12)+1)+1),IF($N6=0,0,$Q6/$N6*MAX(0,(IF($I6="",BC$3,MIN($I6,BC$3)))-(MAX($H6,(EDATE(BC$3,-12)+1)))+1)/(BC$3-(EDATE(BC$3,-12)+1)+1)))*$W6),MAX(0,BB6-$M6))) | BD6: =IF($K6="","",IF(AND($I6<>"",$I6<=BC$3),0,BB6-BC6)) | BE6: =IF(OR($K6="",$H6=""),"",MIN(MAX(0,IF($O6="WDV",BD6*$P6*MAX(0,(IF($I6="",BE$3,MIN($I6,BE$3)))-(MAX($H6,(EDATE(BE$3,-12)+1)))+1)/(BE$3-(EDATE(BE$3,-12)+1)+1),IF($N6=0,0,$Q6/$N6*MAX(0,(IF($I6="",BE$3,MIN($I6,BE$3)))-(MAX($H6,(EDATE(BE$3,-12)+1)))+1)/(BE$3-(EDATE(BE$3,-12)+1)+1)))*$W6),MAX(0,BD6-$M6))) | BF6: =IF($K6="","",IF(AND($I6<>"",$I6<=BE$3),0,BD6-BE6))
A7: FA-003 | B7: CNC Machine | C7: Plant & Machinery - General | D7: Pune Plant | E7: TechMach India | F7: INV-PM-203 | G7: 44326 | H7: 44348 | K7: 6500000 | L7: =DefaultResidual | M7: =IF($K7="","",$K7*$L7) | N7: =IF($C7="","",IFERROR(VLOOKUP($C7,ScheduleIITable,3,FALSE),"#N/A")) | O7: =IF($K7="","",GlobalMethod) | P7: =IF(OR($K7="",$N7="",$N7=0,$M7=0),0,1-($M7/$K7)^(1/$N7)) | Q7: =IF($K7="","",$K7-$M7) | R7: =IF($K7="","",INDEX($AA7:$BF7,1,MATCH(ReportingFYEnd,$AA$3:$BF$3,0))) | S7: =IF($K7="","",IF($U7="Disposed",0,$K7-$T7)) | T7: =IF($K7="","",INDEX($AA7:$BF7,1,MATCH(ReportingFYEnd,$AA$3:$BF$3,0)+1)) | U7: =IF($K7="","",IF(AND($I7<>"",$I7<=ReportingFYEnd),"Disposed",IF(OR($H7="",$H7>ReportingFYEnd),"Not Yet in Use","Active"))) | V7: Single | W7: =IF($V7="Double",1.5,IF($V7="Triple",2,1)) | Y7: =IF($K7="","",IF(OR(ISNUMBER(SEARCH("Build",$C7)),ISNUMBER(SEARCH("Lease",$C7))),"Yes","NA")) | AA7: =IF(OR($K7="",$H7=""),"",MIN(MAX(0,IF($O7="WDV",$K7*$P7*MAX(0,(IF($I7="",AA$3,MIN($I7,AA$3)))-(MAX($H7,(EDATE(AA$3,-12)+1)))+1)/(AA$3-(EDATE(AA$3,-12)+1)+1),IF($N7=0,0,$Q7/$N7*MAX(0,(IF($I7="",AA$3,MIN($I7,AA$3)))-(MAX($H7,(EDATE(AA$3,-12)+1)))+1)/(AA$3-(EDATE(AA$3,-12)+1)+1)))*$W7),MAX(0,$K7-$M7))) | AB7: =IF($K7="","",IF(AND($I7<>"",$I7<=AA$3),0,$K7-AA7)) | AC7: =IF(OR($K7="",$H7=""),"",MIN(MAX(0,IF($O7="WDV",AB7*$P7*MAX(0,(IF($I7="",AC$3,MIN($I7,AC$3)))-(MAX($H7,(EDATE(AC$3,-12)+1)))+1)/(AC$3-(EDATE(AC$3,-12)+1)+1),IF($N7=0,0,$Q7/$N7*MAX(0,(IF($I7="",AC$3,MIN($I7,AC$3)))-(MAX($H7,(EDATE(AC$3,-12)+1)))+1)/(AC$3-(EDATE(AC$3,-12)+1)+1)))*$W7),MAX(0,AB7-$M7))) | AD7: =IF($K7="","",IF(AND($I7<>"",$I7<=AC$3),0,AB7-AC7)) | AE7: =IF(OR($K7="",$H7=""),"",MIN(MAX(0,IF($O7="WDV",AD7*$P7*MAX(0,(IF($I7="",AE$3,MIN($I7,AE$3)))-(MAX($H7,(EDATE(AE$3,-12)+1)))+1)/(AE$3-(EDATE(AE$3,-12)+1)+1),IF($N7=0,0,$Q7/$N7*MAX(0,(IF($I7="",AE$3,MIN($I7,AE$3)))-(MAX($H7,(EDATE(AE$3,-12)+1)))+1)/(AE$3-(EDATE(AE$3,-12)+1)+1)))*$W7),MAX(0,AD7-$M7))) | AF7: =IF($K7="","",IF(AND($I7<>"",$I7<=AE$3),0,AD7-AE7)) | AG7: =IF(OR($K7="",$H7=""),"",MIN(MAX(0,IF($O7="WDV",AF7*$P7*MAX(0,(IF($I7="",AG$3,MIN($I7,AG$3)))-(MAX($H7,(EDATE(AG$3,-12)+1)))+1)/(AG$3-(EDATE(AG$3,-12)+1)+1),IF($N7=0,0,$Q7/$N7*MAX(0,(IF($I7="",AG$3,MIN($I7,AG$3)))-(MAX($H7,(EDATE(AG$3,-12)+1)))+1)/(AG$3-(EDATE(AG$3,-12)+1)+1)))*$W7),MAX(0,AF7-$M7))) | AH7: =IF($K7="","",IF(AND($I7<>"",$I7<=AG$3),0,AF7-AG7)) | AI7: =IF(OR($K7="",$H7=""),"",MIN(MAX(0,IF($O7="WDV",AH7*$P7*MAX(0,(IF($I7="",AI$3,MIN($I7,AI$3)))-(MAX($H7,(EDATE(AI$3,-12)+1)))+1)/(AI$3-(EDATE(AI$3,-12)+1)+1),IF($N7=0,0,$Q7/$N7*MAX(0,(IF($I7="",AI$3,MIN($I7,AI$3)))-(MAX($H7,(EDATE(AI$3,-12)+1)))+1)/(AI$3-(EDATE(AI$3,-12)+1)+1)))*$W7),MAX(0,AH7-$M7))) | AJ7: =IF($K7="","",IF(AND($I7<>"",$I7<=AI$3),0,AH7-AI7)) | AK7: =IF(OR($K7="",$H7=""),"",MIN(MAX(0,IF($O7="WDV",AJ7*$P7*MAX(0,(IF($I7="",AK$3,MIN($I7,AK$3)))-(MAX($H7,(EDATE(AK$3,-12)+1)))+1)/(AK$3-(EDATE(AK$3,-12)+1)+1),IF($N7=0,0,$Q7/$N7*MAX(0,(IF($I7="",AK$3,MIN($I7,AK$3)))-(MAX($H7,(EDATE(AK$3,-12)+1)))+1)/(AK$3-(EDATE(AK$3,-12)+1)+1)))*$W7),MAX(0,AJ7-$M7))) | AL7: =IF($K7="","",IF(AND($I7<>"",$I7<=AK$3),0,AJ7-AK7)) | AM7: =IF(OR($K7="",$H7=""),"",MIN(MAX(0,IF($O7="WDV",AL7*$P7*MAX(0,(IF($I7="",AM$3,MIN($I7,AM$3)))-(MAX($H7,(EDATE(AM$3,-12)+1)))+1)/(AM$3-(EDATE(AM$3,-12)+1)+1),IF($N7=0,0,$Q7/$N7*MAX(0,(IF($I7="",AM$3,MIN($I7,AM$3)))-(MAX($H7,(EDATE(AM$3,-12)+1)))+1)/(AM$3-(EDATE(AM$3,-12)+1)+1)))*$W7),MAX(0,AL7-$M7))) | AN7: =IF($K7="","",IF(AND($I7<>"",$I7<=AM$3),0,AL7-AM7)) | AO7: =IF(OR($K7="",$H7=""),"",MIN(MAX(0,IF($O7="WDV",AN7*$P7*MAX(0,(IF($I7="",AO$3,MIN($I7,AO$3)))-(MAX($H7,(EDATE(AO$3,-12)+1)))+1)/(AO$3-(EDATE(AO$3,-12)+1)+1),IF($N7=0,0,$Q7/$N7*MAX(0,(IF($I7="",AO$3,MIN($I7,AO$3)))-(MAX($H7,(EDATE(AO$3,-12)+1)))+1)/(AO$3-(EDATE(AO$3,-12)+1)+1)))*$W7),MAX(0,AN7-$M7))) | AP7: =IF($K7="","",IF(AND($I7<>"",$I7<=AO$3),0,AN7-AO7)) | AQ7: =IF(OR($K7="",$H7=""),"",MIN(MAX(0,IF($O7="WDV",AP7*$P7*MAX(0,(IF($I7="",AQ$3,MIN($I7,AQ$3)))-(MAX($H7,(EDATE(AQ$3,-12)+1)))+1)/(AQ$3-(EDATE(AQ$3,-12)+1)+1),IF($N7=0,0,$Q7/$N7*MAX(0,(IF($I7="",AQ$3,MIN($I7,AQ$3)))-(MAX($H7,(EDATE(AQ$3,-12)+1)))+1)/(AQ$3-(EDATE(AQ$3,-12)+1)+1)))*$W7),MAX(0,AP7-$M7))) | AR7: =IF($K7="","",IF(AND($I7<>"",$I7<=AQ$3),0,AP7-AQ7)) | AS7: =IF(OR($K7="",$H7=""),"",MIN(MAX(0,IF($O7="WDV",AR7*$P7*MAX(0,(IF($I7="",AS$3,MIN($I7,AS$3)))-(MAX($H7,(EDATE(AS$3,-12)+1)))+1)/(AS$3-(EDATE(AS$3,-12)+1)+1),IF($N7=0,0,$Q7/$N7*MAX(0,(IF($I7="",AS$3,MIN($I7,AS$3)))-(MAX($H7,(EDATE(AS$3,-12)+1)))+1)/(AS$3-(EDATE(AS$3,-12)+1)+1)))*$W7),MAX(0,AR7-$M7))) | AT7: =IF($K7="","",IF(AND($I7<>"",$I7<=AS$3),0,AR7-AS7)) | AU7: =IF(OR($K7="",$H7=""),"",MIN(MAX(0,IF($O7="WDV",AT7*$P7*MAX(0,(IF($I7="",AU$3,MIN($I7,AU$3)))-(MAX($H7,(EDATE(AU$3,-12)+1)))+1)/(AU$3-(EDATE(AU$3,-12)+1)+1),IF($N7=0,0,$Q7/$N7*MAX(0,(IF($I7="",AU$3,MIN($I7,AU$3)))-(MAX($H7,(EDATE(AU$3,-12)+1)))+1)/(AU$3-(EDATE(AU$3,-12)+1)+1)))*$W7),MAX(0,AT7-$M7))) | AV7: =IF($K7="","",IF(AND($I7<>"",$I7<=AU$3),0,AT7-AU7)) | AW7: =IF(OR($K7="",$H7=""),"",MIN(MAX(0,IF($O7="WDV",AV7*$P7*MAX(0,(IF($I7="",AW$3,MIN($I7,AW$3)))-(MAX($H7,(EDATE(AW$3,-12)+1)))+1)/(AW$3-(EDATE(AW$3,-12)+1)+1),IF($N7=0,0,$Q7/$N7*MAX(0,(IF($I7="",AW$3,MIN($I7,AW$3)))-(MAX($H7,(EDATE(AW$3,-12)+1)))+1)/(AW$3-(EDATE(AW$3,-12)+1)+1)))*$W7),MAX(0,AV7-$M7))) | AX7: =IF($K7="","",IF(AND($I7<>"",$I7<=AW$3),0,AV7-AW7)) | AY7: =IF(OR($K7="",$H7=""),"",MIN(MAX(0,IF($O7="WDV",AX7*$P7*MAX(0,(IF($I7="",AY$3,MIN($I7,AY$3)))-(MAX($H7,(EDATE(AY$3,-12)+1)))+1)/(AY$3-(EDATE(AY$3,-12)+1)+1),IF($N7=0,0,$Q7/$N7*MAX(0,(IF($I7="",AY$3,MIN($I7,AY$3)))-(MAX($H7,(EDATE(AY$3,-12)+1)))+1)/(AY$3-(EDATE(AY$3,-12)+1)+1)))*$W7),MAX(0,AX7-$M7))) | AZ7: =IF($K7="","",IF(AND($I7<>"",$I7<=AY$3),0,AX7-AY7)) | BA7: =IF(OR($K7="",$H7=""),"",MIN(MAX(0,IF($O7="WDV",AZ7*$P7*MAX(0,(IF($I7="",BA$3,MIN($I7,BA$3)))-(MAX($H7,(EDATE(BA$3,-12)+1)))+1)/(BA$3-(EDATE(BA$3,-12)+1)+1),IF($N7=0,0,$Q7/$N7*MAX(0,(IF($I7="",BA$3,MIN($I7,BA$3)))-(MAX($H7,(EDATE(BA$3,-12)+1)))+1)/(BA$3-(EDATE(BA$3,-12)+1)+1)))*$W7),MAX(0,AZ7-$M7))) | BB7: =IF($K7="","",IF(AND($I7<>"",$I7<=BA$3),0,AZ7-BA7)) | BC7: =IF(OR($K7="",$H7=""),"",MIN(MAX(0,IF($O7="WDV",BB7*$P7*MAX(0,(IF($I7="",BC$3,MIN($I7,BC$3)))-(MAX($H7,(EDATE(BC$3,-12)+1)))+1)/(BC$3-(EDATE(BC$3,-12)+1)+1),IF($N7=0,0,$Q7/$N7*MAX(0,(IF($I7="",BC$3,MIN($I7,BC$3)))-(MAX($H7,(EDATE(BC$3,-12)+1)))+1)/(BC$3-(EDATE(BC$3,-12)+1)+1)))*$W7),MAX(0,BB7-$M7))) | BD7: =IF($K7="","",IF(AND($I7<>"",$I7<=BC$3),0,BB7-BC7)) | BE7: =IF(OR($K7="",$H7=""),"",MIN(MAX(0,IF($O7="WDV",BD7*$P7*MAX(0,(IF($I7="",BE$3,MIN($I7,BE$3)))-(MAX($H7,(EDATE(BE$3,-12)+1)))+1)/(BE$3-(EDATE(BE$3,-12)+1)+1),IF($N7=0,0,$Q7/$N7*MAX(0,(IF($I7="",BE$3,MIN($I7,BE$3)))-(MAX($H7,(EDATE(BE$3,-12)+1)))+1)/(BE$3-(EDATE(BE$3,-12)+1)+1)))*$W7),MAX(0,BD7-$M7))) | BF7: =IF($K7="","",IF(AND($I7<>"",$I7<=BE$3),0,BD7-BE7))
A8: FA-004 | B8: Office Furniture (lot) | C8: Furniture & Fittings | D8: Mumbai HO | E8: Featherlite | F8: INV-FF-099 | G8: 44306 | H8: 44306 | K8: 850000 | L8: =DefaultResidual | M8: =IF($K8="","",$K8*$L8) | N8: =IF($C8="","",IFERROR(VLOOKUP($C8,ScheduleIITable,3,FALSE),"#N/A")) | O8: =IF($K8="","",GlobalMethod) | P8: =IF(OR($K8="",$N8="",$N8=0,$M8=0),0,1-($M8/$K8)^(1/$N8)) | Q8: =IF($K8="","",$K8-$M8) | R8: =IF($K8="","",INDEX($AA8:$BF8,1,MATCH(ReportingFYEnd,$AA$3:$BF$3,0))) | S8: =IF($K8="","",IF($U8="Disposed",0,$K8-$T8)) | T8: =IF($K8="","",INDEX($AA8:$BF8,1,MATCH(ReportingFYEnd,$AA$3:$BF$3,0)+1)) | U8: =IF($K8="","",IF(AND($I8<>"",$I8<=ReportingFYEnd),"Disposed",IF(OR($H8="",$H8>ReportingFYEnd),"Not Yet in Use","Active"))) | V8: Single | W8: =IF($V8="Double",1.5,IF($V8="Triple",2,1)) | Y8: =IF($K8="","",IF(OR(ISNUMBER(SEARCH("Build",$C8)),ISNUMBER(SEARCH("Lease",$C8))),"Yes","NA")) | AA8: =IF(OR($K8="",$H8=""),"",MIN(MAX(0,IF($O8="WDV",$K8*$P8*MAX(0,(IF($I8="",AA$3,MIN($I8,AA$3)))-(MAX($H8,(EDATE(AA$3,-12)+1)))+1)/(AA$3-(EDATE(AA$3,-12)+1)+1),IF($N8=0,0,$Q8/$N8*MAX(0,(IF($I8="",AA$3,MIN($I8,AA$3)))-(MAX($H8,(EDATE(AA$3,-12)+1)))+1)/(AA$3-(EDATE(AA$3,-12)+1)+1)))*$W8),MAX(0,$K8-$M8))) | AB8: =IF($K8="","",IF(AND($I8<>"",$I8<=AA$3),0,$K8-AA8)) | AC8: =IF(OR($K8="",$H8=""),"",MIN(MAX(0,IF($O8="WDV",AB8*$P8*MAX(0,(IF($I8="",AC$3,MIN($I8,AC$3)))-(MAX($H8,(EDATE(AC$3,-12)+1)))+1)/(AC$3-(EDATE(AC$3,-12)+1)+1),IF($N8=0,0,$Q8/$N8*MAX(0,(IF($I8="",AC$3,MIN($I8,AC$3)))-(MAX($H8,(EDATE(AC$3,-12)+1)))+1)/(AC$3-(EDATE(AC$3,-12)+1)+1)))*$W8),MAX(0,AB8-$M8))) | AD8: =IF($K8="","",IF(AND($I8<>"",$I8<=AC$3),0,AB8-AC8)) | AE8: =IF(OR($K8="",$H8=""),"",MIN(MAX(0,IF($O8="WDV",AD8*$P8*MAX(0,(IF($I8="",AE$3,MIN($I8,AE$3)))-(MAX($H8,(EDATE(AE$3,-12)+1)))+1)/(AE$3-(EDATE(AE$3,-12)+1)+1),IF($N8=0,0,$Q8/$N8*MAX(0,(IF($I8="",AE$3,MIN($I8,AE$3)))-(MAX($H8,(EDATE(AE$3,-12)+1)))+1)/(AE$3-(EDATE(AE$3,-12)+1)+1)))*$W8),MAX(0,AD8-$M8))) | AF8: =IF($K8="","",IF(AND($I8<>"",$I8<=AE$3),0,AD8-AE8)) | AG8: =IF(OR($K8="",$H8=""),"",MIN(MAX(0,IF($O8="WDV",AF8*$P8*MAX(0,(IF($I8="",AG$3,MIN($I8,AG$3)))-(MAX($H8,(EDATE(AG$3,-12)+1)))+1)/(AG$3-(EDATE(AG$3,-12)+1)+1),IF($N8=0,0,$Q8/$N8*MAX(0,(IF($I8="",AG$3,MIN($I8,AG$3)))-(MAX($H8,(EDATE(AG$3,-12)+1)))+1)/(AG$3-(EDATE(AG$3,-12)+1)+1)))*$W8),MAX(0,AF8-$M8))) | AH8: =IF($K8="","",IF(AND($I8<>"",$I8<=AG$3),0,AF8-AG8)) | AI8: =IF(OR($K8="",$H8=""),"",MIN(MAX(0,IF($O8="WDV",AH8*$P8*MAX(0,(IF($I8="",AI$3,MIN($I8,AI$3)))-(MAX($H8,(EDATE(AI$3,-12)+1)))+1)/(AI$3-(EDATE(AI$3,-12)+1)+1),IF($N8=0,0,$Q8/$N8*MAX(0,(IF($I8="",AI$3,MIN($I8,AI$3)))-(MAX($H8,(EDATE(AI$3,-12)+1)))+1)/(AI$3-(EDATE(AI$3,-12)+1)+1)))*$W8),MAX(0,AH8-$M8))) | AJ8: =IF($K8="","",IF(AND($I8<>"",$I8<=AI$3),0,AH8-AI8)) | AK8: =IF(OR($K8="",$H8=""),"",MIN(MAX(0,IF($O8="WDV",AJ8*$P8*MAX(0,(IF($I8="",AK$3,MIN($I8,AK$3)))-(MAX($H8,(EDATE(AK$3,-12)+1)))+1)/(AK$3-(EDATE(AK$3,-12)+1)+1),IF($N8=0,0,$Q8/$N8*MAX(0,(IF($I8="",AK$3,MIN($I8,AK$3)))-(MAX($H8,(EDATE(AK$3,-12)+1)))+1)/(AK$3-(EDATE(AK$3,-12)+1)+1)))*$W8),MAX(0,AJ8-$M8))) | AL8: =IF($K8="","",IF(AND($I8<>"",$I8<=AK$3),0,AJ8-AK8)) | AM8: =IF(OR($K8="",$H8=""),"",MIN(MAX(0,IF($O8="WDV",AL8*$P8*MAX(0,(IF($I8="",AM$3,MIN($I8,AM$3)))-(MAX($H8,(EDATE(AM$3,-12)+1)))+1)/(AM$3-(EDATE(AM$3,-12)+1)+1),IF($N8=0,0,$Q8/$N8*MAX(0,(IF($I8="",AM$3,MIN($I8,AM$3)))-(MAX($H8,(EDATE(AM$3,-12)+1)))+1)/(AM$3-(EDATE(AM$3,-12)+1)+1)))*$W8),MAX(0,AL8-$M8))) | AN8: =IF($K8="","",IF(AND($I8<>"",$I8<=AM$3),0,AL8-AM8)) | AO8: =IF(OR($K8="",$H8=""),"",MIN(MAX(0,IF($O8="WDV",AN8*$P8*MAX(0,(IF($I8="",AO$3,MIN($I8,AO$3)))-(MAX($H8,(EDATE(AO$3,-12)+1)))+1)/(AO$3-(EDATE(AO$3,-12)+1)+1),IF($N8=0,0,$Q8/$N8*MAX(0,(IF($I8="",AO$3,MIN($I8,AO$3)))-(MAX($H8,(EDATE(AO$3,-12)+1)))+1)/(AO$3-(EDATE(AO$3,-12)+1)+1)))*$W8),MAX(0,AN8-$M8))) | AP8: =IF($K8="","",IF(AND($I8<>"",$I8<=AO$3),0,AN8-AO8)) | AQ8: =IF(OR($K8="",$H8=""),"",MIN(MAX(0,IF($O8="WDV",AP8*$P8*MAX(0,(IF($I8="",AQ$3,MIN($I8,AQ$3)))-(MAX($H8,(EDATE(AQ$3,-12)+1)))+1)/(AQ$3-(EDATE(AQ$3,-12)+1)+1),IF($N8=0,0,$Q8/$N8*MAX(0,(IF($I8="",AQ$3,MIN($I8,AQ$3)))-(MAX($H8,(EDATE(AQ$3,-12)+1)))+1)/(AQ$3-(EDATE(AQ$3,-12)+1)+1)))*$W8),MAX(0,AP8-$M8))) | AR8: =IF($K8="","",IF(AND($I8<>"",$I8<=AQ$3),0,AP8-AQ8)) | AS8: =IF(OR($K8="",$H8=""),"",MIN(MAX(0,IF($O8="WDV",AR8*$P8*MAX(0,(IF($I8="",AS$3,MIN($I8,AS$3)))-(MAX($H8,(EDATE(AS$3,-12)+1)))+1)/(AS$3-(EDATE(AS$3,-12)+1)+1),IF($N8=0,0,$Q8/$N8*MAX(0,(IF($I8="",AS$3,MIN($I8,AS$3)))-(MAX($H8,(EDATE(AS$3,-12)+1)))+1)/(AS$3-(EDATE(AS$3,-12)+1)+1)))*$W8),MAX(0,AR8-$M8))) | AT8: =IF($K8="","",IF(AND($I8<>"",$I8<=AS$3),0,AR8-AS8)) | AU8: =IF(OR($K8="",$H8=""),"",MIN(MAX(0,IF($O8="WDV",AT8*$P8*MAX(0,(IF($I8="",AU$3,MIN($I8,AU$3)))-(MAX($H8,(EDATE(AU$3,-12)+1)))+1)/(AU$3-(EDATE(AU$3,-12)+1)+1),IF($N8=0,0,$Q8/$N8*MAX(0,(IF($I8="",AU$3,MIN($I8,AU$3)))-(MAX($H8,(EDATE(AU$3,-12)+1)))+1)/(AU$3-(EDATE(AU$3,-12)+1)+1)))*$W8),MAX(0,AT8-$M8))) | AV8: =IF($K8="","",IF(AND($I8<>"",$I8<=AU$3),0,AT8-AU8)) | AW8: =IF(OR($K8="",$H8=""),"",MIN(MAX(0,IF($O8="WDV",AV8*$P8*MAX(0,(IF($I8="",AW$3,MIN($I8,AW$3)))-(MAX($H8,(EDATE(AW$3,-12)+1)))+1)/(AW$3-(EDATE(AW$3,-12)+1)+1),IF($N8=0,0,$Q8/$N8*MAX(0,(IF($I8="",AW$3,MIN($I8,AW$3)))-(MAX($H8,(EDATE(AW$3,-12)+1)))+1)/(AW$3-(EDATE(AW$3,-12)+1)+1)))*$W8),MAX(0,AV8-$M8))) | AX8: =IF($K8="","",IF(AND($I8<>"",$I8<=AW$3),0,AV8-AW8)) | AY8: =IF(OR($K8="",$H8=""),"",MIN(MAX(0,IF($O8="WDV",AX8*$P8*MAX(0,(IF($I8="",AY$3,MIN($I8,AY$3)))-(MAX($H8,(EDATE(AY$3,-12)+1)))+1)/(AY$3-(EDATE(AY$3,-12)+1)+1),IF($N8=0,0,$Q8/$N8*MAX(0,(IF($I8="",AY$3,MIN($I8,AY$3)))-(MAX($H8,(EDATE(AY$3,-12)+1)))+1)/(AY$3-(EDATE(AY$3,-12)+1)+1)))*$W8),MAX(0,AX8-$M8))) | AZ8: =IF($K8="","",IF(AND($I8<>"",$I8<=AY$3),0,AX8-AY8)) | BA8: =IF(OR($K8="",$H8=""),"",MIN(MAX(0,IF($O8="WDV",AZ8*$P8*MAX(0,(IF($I8="",BA$3,MIN($I8,BA$3)))-(MAX($H8,(EDATE(BA$3,-12)+1)))+1)/(BA$3-(EDATE(BA$3,-12)+1)+1),IF($N8=0,0,$Q8/$N8*MAX(0,(IF($I8="",BA$3,MIN($I8,BA$3)))-(MAX($H8,(EDATE(BA$3,-12)+1)))+1)/(BA$3-(EDATE(BA$3,-12)+1)+1)))*$W8),MAX(0,AZ8-$M8))) | BB8: =IF($K8="","",IF(AND($I8<>"",$I8<=BA$3),0,AZ8-BA8)) | BC8: =IF(OR($K8="",$H8=""),"",MIN(MAX(0,IF($O8="WDV",BB8*$P8*MAX(0,(IF($I8="",BC$3,MIN($I8,BC$3)))-(MAX($H8,(EDATE(BC$3,-12)+1)))+1)/(BC$3-(EDATE(BC$3,-12)+1)+1),IF($N8=0,0,$Q8/$N8*MAX(0,(IF($I8="",BC$3,MIN($I8,BC$3)))-(MAX($H8,(EDATE(BC$3,-12)+1)))+1)/(BC$3-(EDATE(BC$3,-12)+1)+1)))*$W8),MAX(0,BB8-$M8))) | BD8: =IF($K8="","",IF(AND($I8<>"",$I8<=BC$3),0,BB8-BC8)) | BE8: =IF(OR($K8="",$H8=""),"",MIN(MAX(0,IF($O8="WDV",BD8*$P8*MAX(0,(IF($I8="",BE$3,MIN($I8,BE$3)))-(MAX($H8,(EDATE(BE$3,-12)+1)))+1)/(BE$3-(EDATE(BE$3,-12)+1)+1),IF($N8=0,0,$Q8/$N8*MAX(0,(IF($I8="",BE$3,MIN($I8,BE$3)))-(MAX($H8,(EDATE(BE$3,-12)+1)))+1)/(BE$3-(EDATE(BE$3,-12)+1)+1)))*$W8),MAX(0,BD8-$M8))) | BF8: =IF($K8="","",IF(AND($I8<>"",$I8<=BE$3),0,BD8-BE8))
A9: FA-005 | B9: Laptops (25 nos.) | C9: Computers - End User Devices | D9: Mumbai HO | E9: Dell India | F9: INV-IT-451 | G9: 44713 | H9: 44717 | K9: 1750000 | L9: =DefaultResidual | M9: =IF($K9="","",$K9*$L9) | N9: =IF($C9="","",IFERROR(VLOOKUP($C9,ScheduleIITable,3,FALSE),"#N/A")) | O9: =IF($K9="","",GlobalMethod) | P9: =IF(OR($K9="",$N9="",$N9=0,$M9=0),0,1-($M9/$K9)^(1/$N9)) | Q9: =IF($K9="","",$K9-$M9) | R9: =IF($K9="","",INDEX($AA9:$BF9,1,MATCH(ReportingFYEnd,$AA$3:$BF$3,0))) | S9: =IF($K9="","",IF($U9="Disposed",0,$K9-$T9)) | T9: =IF($K9="","",INDEX($AA9:$BF9,1,MATCH(ReportingFYEnd,$AA$3:$BF$3,0)+1)) | U9: =IF($K9="","",IF(AND($I9<>"",$I9<=ReportingFYEnd),"Disposed",IF(OR($H9="",$H9>ReportingFYEnd),"Not Yet in Use","Active"))) | V9: Single | W9: =IF($V9="Double",1.5,IF($V9="Triple",2,1)) | Y9: =IF($K9="","",IF(OR(ISNUMBER(SEARCH("Build",$C9)),ISNUMBER(SEARCH("Lease",$C9))),"Yes","NA")) | AA9: =IF(OR($K9="",$H9=""),"",MIN(MAX(0,IF($O9="WDV",$K9*$P9*MAX(0,(IF($I9="",AA$3,MIN($I9,AA$3)))-(MAX($H9,(EDATE(AA$3,-12)+1)))+1)/(AA$3-(EDATE(AA$3,-12)+1)+1),IF($N9=0,0,$Q9/$N9*MAX(0,(IF($I9="",AA$3,MIN($I9,AA$3)))-(MAX($H9,(EDATE(AA$3,-12)+1)))+1)/(AA$3-(EDATE(AA$3,-12)+1)+1)))*$W9),MAX(0,$K9-$M9))) | AB9: =IF($K9="","",IF(AND($I9<>"",$I9<=AA$3),0,$K9-AA9)) | AC9: =IF(OR($K9="",$H9=""),"",MIN(MAX(0,IF($O9="WDV",AB9*$P9*MAX(0,(IF($I9="",AC$3,MIN($I9,AC$3)))-(MAX($H9,(EDATE(AC$3,-12)+1)))+1)/(AC$3-(EDATE(AC$3,-12)+1)+1),IF($N9=0,0,$Q9/$N9*MAX(0,(IF($I9="",AC$3,MIN($I9,AC$3)))-(MAX($H9,(EDATE(AC$3,-12)+1)))+1)/(AC$3-(EDATE(AC$3,-12)+1)+1)))*$W9),MAX(0,AB9-$M9))) | AD9: =IF($K9="","",IF(AND($I9<>"",$I9<=AC$3),0,AB9-AC9)) | AE9: =IF(OR($K9="",$H9=""),"",MIN(MAX(0,IF($O9="WDV",AD9*$P9*MAX(0,(IF($I9="",AE$3,MIN($I9,AE$3)))-(MAX($H9,(EDATE(AE$3,-12)+1)))+1)/(AE$3-(EDATE(AE$3,-12)+1)+1),IF($N9=0,0,$Q9/$N9*MAX(0,(IF($I9="",AE$3,MIN($I9,AE$3)))-(MAX($H9,(EDATE(AE$3,-12)+1)))+1)/(AE$3-(EDATE(AE$3,-12)+1)+1)))*$W9),MAX(0,AD9-$M9))) | AF9: =IF($K9="","",IF(AND($I9<>"",$I9<=AE$3),0,AD9-AE9)) | AG9: =IF(OR($K9="",$H9=""),"",MIN(MAX(0,IF($O9="WDV",AF9*$P9*MAX(0,(IF($I9="",AG$3,MIN($I9,AG$3)))-(MAX($H9,(EDATE(AG$3,-12)+1)))+1)/(AG$3-(EDATE(AG$3,-12)+1)+1),IF($N9=0,0,$Q9/$N9*MAX(0,(IF($I9="",AG$3,MIN($I9,AG$3)))-(MAX($H9,(EDATE(AG$3,-12)+1)))+1)/(AG$3-(EDATE(AG$3,-12)+1)+1)))*$W9),MAX(0,AF9-$M9))) | AH9: =IF($K9="","",IF(AND($I9<>"",$I9<=AG$3),0,AF9-AG9)) | AI9: =IF(OR($K9="",$H9=""),"",MIN(MAX(0,IF($O9="WDV",AH9*$P9*MAX(0,(IF($I9="",AI$3,MIN($I9,AI$3)))-(MAX($H9,(EDATE(AI$3,-12)+1)))+1)/(AI$3-(EDATE(AI$3,-12)+1)+1),IF($N9=0,0,$Q9/$N9*MAX(0,(IF($I9="",AI$3,MIN($I9,AI$3)))-(MAX($H9,(EDATE(AI$3,-12)+1)))+1)/(AI$3-(EDATE(AI$3,-12)+1)+1)))*$W9),MAX(0,AH9-$M9))) | AJ9: =IF($K9="","",IF(AND($I9<>"",$I9<=AI$3),0,AH9-AI9)) | AK9: =IF(OR($K9="",$H9=""),"",MIN(MAX(0,IF($O9="WDV",AJ9*$P9*MAX(0,(IF($I9="",AK$3,MIN($I9,AK$3)))-(MAX($H9,(EDATE(AK$3,-12)+1)))+1)/(AK$3-(EDATE(AK$3,-12)+1)+1),IF($N9=0,0,$Q9/$N9*MAX(0,(IF($I9="",AK$3,MIN($I9,AK$3)))-(MAX($H9,(EDATE(AK$3,-12)+1)))+1)/(AK$3-(EDATE(AK$3,-12)+1)+1)))*$W9),MAX(0,AJ9-$M9))) | AL9: =IF($K9="","",IF(AND($I9<>"",$I9<=AK$3),0,AJ9-AK9)) | AM9: =IF(OR($K9="",$H9=""),"",MIN(MAX(0,IF($O9="WDV",AL9*$P9*MAX(0,(IF($I9="",AM$3,MIN($I9,AM$3)))-(MAX($H9,(EDATE(AM$3,-12)+1)))+1)/(AM$3-(EDATE(AM$3,-12)+1)+1),IF($N9=0,0,$Q9/$N9*MAX(0,(IF($I9="",AM$3,MIN($I9,AM$3)))-(MAX($H9,(EDATE(AM$3,-12)+1)))+1)/(AM$3-(EDATE(AM$3,-12)+1)+1)))*$W9),MAX(0,AL9-$M9))) | AN9: =IF($K9="","",IF(AND($I9<>"",$I9<=AM$3),0,AL9-AM9)) | AO9: =IF(OR($K9="",$H9=""),"",MIN(MAX(0,IF($O9="WDV",AN9*$P9*MAX(0,(IF($I9="",AO$3,MIN($I9,AO$3)))-(MAX($H9,(EDATE(AO$3,-12)+1)))+1)/(AO$3-(EDATE(AO$3,-12)+1)+1),IF($N9=0,0,$Q9/$N9*MAX(0,(IF($I9="",AO$3,MIN($I9,AO$3)))-(MAX($H9,(EDATE(AO$3,-12)+1)))+1)/(AO$3-(EDATE(AO$3,-12)+1)+1)))*$W9),MAX(0,AN9-$M9))) | AP9: =IF($K9="","",IF(AND($I9<>"",$I9<=AO$3),0,AN9-AO9)) | AQ9: =IF(OR($K9="",$H9=""),"",MIN(MAX(0,IF($O9="WDV",AP9*$P9*MAX(0,(IF($I9="",AQ$3,MIN($I9,AQ$3)))-(MAX($H9,(EDATE(AQ$3,-12)+1)))+1)/(AQ$3-(EDATE(AQ$3,-12)+1)+1),IF($N9=0,0,$Q9/$N9*MAX(0,(IF($I9="",AQ$3,MIN($I9,AQ$3)))-(MAX($H9,(EDATE(AQ$3,-12)+1)))+1)/(AQ$3-(EDATE(AQ$3,-12)+1)+1)))*$W9),MAX(0,AP9-$M9))) | AR9: =IF($K9="","",IF(AND($I9<>"",$I9<=AQ$3),0,AP9-AQ9)) | AS9: =IF(OR($K9="",$H9=""),"",MIN(MAX(0,IF($O9="WDV",AR9*$P9*MAX(0,(IF($I9="",AS$3,MIN($I9,AS$3)))-(MAX($H9,(EDATE(AS$3,-12)+1)))+1)/(AS$3-(EDATE(AS$3,-12)+1)+1),IF($N9=0,0,$Q9/$N9*MAX(0,(IF($I9="",AS$3,MIN($I9,AS$3)))-(MAX($H9,(EDATE(AS$3,-12)+1)))+1)/(AS$3-(EDATE(AS$3,-12)+1)+1)))*$W9),MAX(0,AR9-$M9))) | AT9: =IF($K9="","",IF(AND($I9<>"",$I9<=AS$3),0,AR9-AS9)) | AU9: =IF(OR($K9="",$H9=""),"",MIN(MAX(0,IF($O9="WDV",AT9*$P9*MAX(0,(IF($I9="",AU$3,MIN($I9,AU$3)))-(MAX($H9,(EDATE(AU$3,-12)+1)))+1)/(AU$3-(EDATE(AU$3,-12)+1)+1),IF($N9=0,0,$Q9/$N9*MAX(0,(IF($I9="",AU$3,MIN($I9,AU$3)))-(MAX($H9,(EDATE(AU$3,-12)+1)))+1)/(AU$3-(EDATE(AU$3,-12)+1)+1)))*$W9),MAX(0,AT9-$M9))) | AV9: =IF($K9="","",IF(AND($I9<>"",$I9<=AU$3),0,AT9-AU9)) | AW9: =IF(OR($K9="",$H9=""),"",MIN(MAX(0,IF($O9="WDV",AV9*$P9*MAX(0,(IF($I9="",AW$3,MIN($I9,AW$3)))-(MAX($H9,(EDATE(AW$3,-12)+1)))+1)/(AW$3-(EDATE(AW$3,-12)+1)+1),IF($N9=0,0,$Q9/$N9*MAX(0,(IF($I9="",AW$3,MIN($I9,AW$3)))-(MAX($H9,(EDATE(AW$3,-12)+1)))+1)/(AW$3-(EDATE(AW$3,-12)+1)+1)))*$W9),MAX(0,AV9-$M9))) | AX9: =IF($K9="","",IF(AND($I9<>"",$I9<=AW$3),0,AV9-AW9)) | AY9: =IF(OR($K9="",$H9=""),"",MIN(MAX(0,IF($O9="WDV",AX9*$P9*MAX(0,(IF($I9="",AY$3,MIN($I9,AY$3)))-(MAX($H9,(EDATE(AY$3,-12)+1)))+1)/(AY$3-(EDATE(AY$3,-12)+1)+1),IF($N9=0,0,$Q9/$N9*MAX(0,(IF($I9="",AY$3,MIN($I9,AY$3)))-(MAX($H9,(EDATE(AY$3,-12)+1)))+1)/(AY$3-(EDATE(AY$3,-12)+1)+1)))*$W9),MAX(0,AX9-$M9))) | AZ9: =IF($K9="","",IF(AND($I9<>"",$I9<=AY$3),0,AX9-AY9)) | BA9: =IF(OR($K9="",$H9=""),"",MIN(MAX(0,IF($O9="WDV",AZ9*$P9*MAX(0,(IF($I9="",BA$3,MIN($I9,BA$3)))-(MAX($H9,(EDATE(BA$3,-12)+1)))+1)/(BA$3-(EDATE(BA$3,-12)+1)+1),IF($N9=0,0,$Q9/$N9*MAX(0,(IF($I9="",BA$3,MIN($I9,BA$3)))-(MAX($H9,(EDATE(BA$3,-12)+1)))+1)/(BA$3-(EDATE(BA$3,-12)+1)+1)))*$W9),MAX(0,AZ9-$M9))) | BB9: =IF($K9="","",IF(AND($I9<>"",$I9<=BA$3),0,AZ9-BA9)) | BC9: =IF(OR($K9="",$H9=""),"",MIN(MAX(0,IF($O9="WDV",BB9*$P9*MAX(0,(IF($I9="",BC$3,MIN($I9,BC$3)))-(MAX($H9,(EDATE(BC$3,-12)+1)))+1)/(BC$3-(EDATE(BC$3,-12)+1)+1),IF($N9=0,0,$Q9/$N9*MAX(0,(IF($I9="",BC$3,MIN($I9,BC$3)))-(MAX($H9,(EDATE(BC$3,-12)+1)))+1)/(BC$3-(EDATE(BC$3,-12)+1)+1)))*$W9),MAX(0,BB9-$M9))) | BD9: =IF($K9="","",IF(AND($I9<>"",$I9<=BC$3),0,BB9-BC9)) | BE9: =IF(OR($K9="",$H9=""),"",MIN(MAX(0,IF($O9="WDV",BD9*$P9*MAX(0,(IF($I9="",BE$3,MIN($I9,BE$3)))-(MAX($H9,(EDATE(BE$3,-12)+1)))+1)/(BE$3-(EDATE(BE$3,-12)+1)+1),IF($N9=0,0,$Q9/$N9*MAX(0,(IF($I9="",BE$3,MIN($I9,BE$3)))-(MAX($H9,(EDATE(BE$3,-12)+1)))+1)/(BE$3-(EDATE(BE$3,-12)+1)+1)))*$W9),MAX(0,BD9-$M9))) | BF9: =IF($K9="","",IF(AND($I9<>"",$I9<=BE$3),0,BD9-BE9))
A10: FA-006 | B10: Application Server | C10: Computers - Servers & Networks | D10: Mumbai HO | E10: HPE | F10: INV-IT-460 | G10: 44816 | H10: 44824 | K10: 1200000 | L10: =DefaultResidual | M10: =IF($K10="","",$K10*$L10) | N10: =IF($C10="","",IFERROR(VLOOKUP($C10,ScheduleIITable,3,FALSE),"#N/A")) | O10: =IF($K10="","",GlobalMethod) | P10: =IF(OR($K10="",$N10="",$N10=0,$M10=0),0,1-($M10/$K10)^(1/$N10)) | Q10: =IF($K10="","",$K10-$M10) | R10: =IF($K10="","",INDEX($AA10:$BF10,1,MATCH(ReportingFYEnd,$AA$3:$BF$3,0))) | S10: =IF($K10="","",IF($U10="Disposed",0,$K10-$T10)) | T10: =IF($K10="","",INDEX($AA10:$BF10,1,MATCH(ReportingFYEnd,$AA$3:$BF$3,0)+1)) | U10: =IF($K10="","",IF(AND($I10<>"",$I10<=ReportingFYEnd),"Disposed",IF(OR($H10="",$H10>ReportingFYEnd),"Not Yet in Use","Active"))) | V10: Single | W10: =IF($V10="Double",1.5,IF($V10="Triple",2,1)) | Y10: =IF($K10="","",IF(OR(ISNUMBER(SEARCH("Build",$C10)),ISNUMBER(SEARCH("Lease",$C10))),"Yes","NA")) | AA10: =IF(OR($K10="",$H10=""),"",MIN(MAX(0,IF($O10="WDV",$K10*$P10*MAX(0,(IF($I10="",AA$3,MIN($I10,AA$3)))-(MAX($H10,(EDATE(AA$3,-12)+1)))+1)/(AA$3-(EDATE(AA$3,-12)+1)+1),IF($N10=0,0,$Q10/$N10*MAX(0,(IF($I10="",AA$3,MIN($I10,AA$3)))-(MAX($H10,(EDATE(AA$3,-12)+1)))+1)/(AA$3-(EDATE(AA$3,-12)+1)+1)))*$W10),MAX(0,$K10-$M10))) | AB10: =IF($K10="","",IF(AND($I10<>"",$I10<=AA$3),0,$K10-AA10)) | AC10: =IF(OR($K10="",$H10=""),"",MIN(MAX(0,IF($O10="WDV",AB10*$P10*MAX(0,(IF($I10="",AC$3,MIN($I10,AC$3)))-(MAX($H10,(EDATE(AC$3,-12)+1)))+1)/(AC$3-(EDATE(AC$3,-12)+1)+1),IF($N10=0,0,$Q10/$N10*MAX(0,(IF($I10="",AC$3,MIN($I10,AC$3)))-(MAX($H10,(EDATE(AC$3,-12)+1)))+1)/(AC$3-(EDATE(AC$3,-12)+1)+1)))*$W10),MAX(0,AB10-$M10))) | AD10: =IF($K10="","",IF(AND($I10<>"",$I10<=AC$3),0,AB10-AC10)) | AE10: =IF(OR($K10="",$H10=""),"",MIN(MAX(0,IF($O10="WDV",AD10*$P10*MAX(0,(IF($I10="",AE$3,MIN($I10,AE$3)))-(MAX($H10,(EDATE(AE$3,-12)+1)))+1)/(AE$3-(EDATE(AE$3,-12)+1)+1),IF($N10=0,0,$Q10/$N10*MAX(0,(IF($I10="",AE$3,MIN($I10,AE$3)))-(MAX($H10,(EDATE(AE$3,-12)+1)))+1)/(AE$3-(EDATE(AE$3,-12)+1)+1)))*$W10),MAX(0,AD10-$M10))) | AF10: =IF($K10="","",IF(AND($I10<>"",$I10<=AE$3),0,AD10-AE10)) | AG10: =IF(OR($K10="",$H10=""),"",MIN(MAX(0,IF($O10="WDV",AF10*$P10*MAX(0,(IF($I10="",AG$3,MIN($I10,AG$3)))-(MAX($H10,(EDATE(AG$3,-12)+1)))+1)/(AG$3-(EDATE(AG$3,-12)+1)+1),IF($N10=0,0,$Q10/$N10*MAX(0,(IF($I10="",AG$3,MIN($I10,AG$3)))-(MAX($H10,(EDATE(AG$3,-12)+1)))+1)/(AG$3-(EDATE(AG$3,-12)+1)+1)))*$W10),MAX(0,AF10-$M10))) | AH10: =IF($K10="","",IF(AND($I10<>"",$I10<=AG$3),0,AF10-AG10)) | AI10: =IF(OR($K10="",$H10=""),"",MIN(MAX(0,IF($O10="WDV",AH10*$P10*MAX(0,(IF($I10="",AI$3,MIN($I10,AI$3)))-(MAX($H10,(EDATE(AI$3,-12)+1)))+1)/(AI$3-(EDATE(AI$3,-12)+1)+1),IF($N10=0,0,$Q10/$N10*MAX(0,(IF($I10="",AI$3,MIN($I10,AI$3)))-(MAX($H10,(EDATE(AI$3,-12)+1)))+1)/(AI$3-(EDATE(AI$3,-12)+1)+1)))*$W10),MAX(0,AH10-$M10))) | AJ10: =IF($K10="","",IF(AND($I10<>"",$I10<=AI$3),0,AH10-AI10)) | AK10: =IF(OR($K10="",$H10=""),"",MIN(MAX(0,IF($O10="WDV",AJ10*$P10*MAX(0,(IF($I10="",AK$3,MIN($I10,AK$3)))-(MAX($H10,(EDATE(AK$3,-12)+1)))+1)/(AK$3-(EDATE(AK$3,-12)+1)+1),IF($N10=0,0,$Q10/$N10*MAX(0,(IF($I10="",AK$3,MIN($I10,AK$3)))-(MAX($H10,(EDATE(AK$3,-12)+1)))+1)/(AK$3-(EDATE(AK$3,-12)+1)+1)))*$W10),MAX(0,AJ10-$M10))) | AL10: =IF($K10="","",IF(AND($I10<>"",$I10<=AK$3),0,AJ10-AK10)) | AM10: =IF(OR($K10="",$H10=""),"",MIN(MAX(0,IF($O10="WDV",AL10*$P10*MAX(0,(IF($I10="",AM$3,MIN($I10,AM$3)))-(MAX($H10,(EDATE(AM$3,-12)+1)))+1)/(AM$3-(EDATE(AM$3,-12)+1)+1),IF($N10=0,0,$Q10/$N10*MAX(0,(IF($I10="",AM$3,MIN($I10,AM$3)))-(MAX($H10,(EDATE(AM$3,-12)+1)))+1)/(AM$3-(EDATE(AM$3,-12)+1)+1)))*$W10),MAX(0,AL10-$M10))) | AN10: =IF($K10="","",IF(AND($I10<>"",$I10<=AM$3),0,AL10-AM10)) | AO10: =IF(OR($K10="",$H10=""),"",MIN(MAX(0,IF($O10="WDV",AN10*$P10*MAX(0,(IF($I10="",AO$3,MIN($I10,AO$3)))-(MAX($H10,(EDATE(AO$3,-12)+1)))+1)/(AO$3-(EDATE(AO$3,-12)+1)+1),IF($N10=0,0,$Q10/$N10*MAX(0,(IF($I10="",AO$3,MIN($I10,AO$3)))-(MAX($H10,(EDATE(AO$3,-12)+1)))+1)/(AO$3-(EDATE(AO$3,-12)+1)+1)))*$W10),MAX(0,AN10-$M10))) | AP10: =IF($K10="","",IF(AND($I10<>"",$I10<=AO$3),0,AN10-AO10)) | AQ10: =IF(OR($K10="",$H10=""),"",MIN(MAX(0,IF($O10="WDV",AP10*$P10*MAX(0,(IF($I10="",AQ$3,MIN($I10,AQ$3)))-(MAX($H10,(EDATE(AQ$3,-12)+1)))+1)/(AQ$3-(EDATE(AQ$3,-12)+1)+1),IF($N10=0,0,$Q10/$N10*MAX(0,(IF($I10="",AQ$3,MIN($I10,AQ$3)))-(MAX($H10,(EDATE(AQ$3,-12)+1)))+1)/(AQ$3-(EDATE(AQ$3,-12)+1)+1)))*$W10),MAX(0,AP10-$M10))) | AR10: =IF($K10="","",IF(AND($I10<>"",$I10<=AQ$3),0,AP10-AQ10)) | AS10: =IF(OR($K10="",$H10=""),"",MIN(MAX(0,IF($O10="WDV",AR10*$P10*MAX(0,(IF($I10="",AS$3,MIN($I10,AS$3)))-(MAX($H10,(EDATE(AS$3,-12)+1)))+1)/(AS$3-(EDATE(AS$3,-12)+1)+1),IF($N10=0,0,$Q10/$N10*MAX(0,(IF($I10="",AS$3,MIN($I10,AS$3)))-(MAX($H10,(EDATE(AS$3,-12)+1)))+1)/(AS$3-(EDATE(AS$3,-12)+1)+1)))*$W10),MAX(0,AR10-$M10))) | AT10: =IF($K10="","",IF(AND($I10<>"",$I10<=AS$3),0,AR10-AS10)) | AU10: =IF(OR($K10="",$H10=""),"",MIN(MAX(0,IF($O10="WDV",AT10*$P10*MAX(0,(IF($I10="",AU$3,MIN($I10,AU$3)))-(MAX($H10,(EDATE(AU$3,-12)+1)))+1)/(AU$3-(EDATE(AU$3,-12)+1)+1),IF($N10=0,0,$Q10/$N10*MAX(0,(IF($I10="",AU$3,MIN($I10,AU$3)))-(MAX($H10,(EDATE(AU$3,-12)+1)))+1)/(AU$3-(EDATE(AU$3,-12)+1)+1)))*$W10),MAX(0,AT10-$M10))) | AV10: =IF($K10="","",IF(AND($I10<>"",$I10<=AU$3),0,AT10-AU10)) | AW10: =IF(OR($K10="",$H10=""),"",MIN(MAX(0,IF($O10="WDV",AV10*$P10*MAX(0,(IF($I10="",AW$3,MIN($I10,AW$3)))-(MAX($H10,(EDATE(AW$3,-12)+1)))+1)/(AW$3-(EDATE(AW$3,-12)+1)+1),IF($N10=0,0,$Q10/$N10*MAX(0,(IF($I10="",AW$3,MIN($I10,AW$3)))-(MAX($H10,(EDATE(AW$3,-12)+1)))+1)/(AW$3-(EDATE(AW$3,-12)+1)+1)))*$W10),MAX(0,AV10-$M10))) | AX10: =IF($K10="","",IF(AND($I10<>"",$I10<=AW$3),0,AV10-AW10)) | AY10: =IF(OR($K10="",$H10=""),"",MIN(MAX(0,IF($O10="WDV",AX10*$P10*MAX(0,(IF($I10="",AY$3,MIN($I10,AY$3)))-(MAX($H10,(EDATE(AY$3,-12)+1)))+1)/(AY$3-(EDATE(AY$3,-12)+1)+1),IF($N10=0,0,$Q10/$N10*MAX(0,(IF($I10="",AY$3,MIN($I10,AY$3)))-(MAX($H10,(EDATE(AY$3,-12)+1)))+1)/(AY$3-(EDATE(AY$3,-12)+1)+1)))*$W10),MAX(0,AX10-$M10))) | AZ10: =IF($K10="","",IF(AND($I10<>"",$I10<=AY$3),0,AX10-AY10)) | BA10: =IF(OR($K10="",$H10=""),"",MIN(MAX(0,IF($O10="WDV",AZ10*$P10*MAX(0,(IF($I10="",BA$3,MIN($I10,BA$3)))-(MAX($H10,(EDATE(BA$3,-12)+1)))+1)/(BA$3-(EDATE(BA$3,-12)+1)+1),IF($N10=0,0,$Q10/$N10*MAX(0,(IF($I10="",BA$3,MIN($I10,BA$3)))-(MAX($H10,(EDATE(BA$3,-12)+1)))+1)/(BA$3-(EDATE(BA$3,-12)+1)+1)))*$W10),MAX(0,AZ10-$M10))) | BB10: =IF($K10="","",IF(AND($I10<>"",$I10<=BA$3),0,AZ10-BA10)) | BC10: =IF(OR($K10="",$H10=""),"",MIN(MAX(0,IF($O10="WDV",BB10*$P10*MAX(0,(IF($I10="",BC$3,MIN($I10,BC$3)))-(MAX($H10,(EDATE(BC$3,-12)+1)))+1)/(BC$3-(EDATE(BC$3,-12)+1)+1),IF($N10=0,0,$Q10/$N10*MAX(0,(IF($I10="",BC$3,MIN($I10,BC$3)))-(MAX($H10,(EDATE(BC$3,-12)+1)))+1)/(BC$3-(EDATE(BC$3,-12)+1)+1)))*$W10),MAX(0,BB10-$M10))) | BD10: =IF($K10="","",IF(AND($I10<>"",$I10<=BC$3),0,BB10-BC10)) | BE10: =IF(OR($K10="",$H10=""),"",MIN(MAX(0,IF($O10="WDV",BD10*$P10*MAX(0,(IF($I10="",BE$3,MIN($I10,BE$3)))-(MAX($H10,(EDATE(BE$3,-12)+1)))+1)/(BE$3-(EDATE(BE$3,-12)+1)+1),IF($N10=0,0,$Q10/$N10*MAX(0,(IF($I10="",BE$3,MIN($I10,BE$3)))-(MAX($H10,(EDATE(BE$3,-12)+1)))+1)/(BE$3-(EDATE(BE$3,-12)+1)+1)))*$W10),MAX(0,BD10-$M10))) | BF10: =IF($K10="","",IF(AND($I10<>"",$I10<=BE$3),0,BD10-BE10))
A11: FA-007 | B11: Director's Car | C11: Motor Vehicles - Motor Cars | D11: Mumbai HO | E11: Toyota | F11: INV-MV-011 | G11: 44941 | H11: 44941 | K11: 2800000 | L11: =DefaultResidual | M11: =IF($K11="","",$K11*$L11) | N11: =IF($C11="","",IFERROR(VLOOKUP($C11,ScheduleIITable,3,FALSE),"#N/A")) | O11: =IF($K11="","",GlobalMethod) | P11: =IF(OR($K11="",$N11="",$N11=0,$M11=0),0,1-($M11/$K11)^(1/$N11)) | Q11: =IF($K11="","",$K11-$M11) | R11: =IF($K11="","",INDEX($AA11:$BF11,1,MATCH(ReportingFYEnd,$AA$3:$BF$3,0))) | S11: =IF($K11="","",IF($U11="Disposed",0,$K11-$T11)) | T11: =IF($K11="","",INDEX($AA11:$BF11,1,MATCH(ReportingFYEnd,$AA$3:$BF$3,0)+1)) | U11: =IF($K11="","",IF(AND($I11<>"",$I11<=ReportingFYEnd),"Disposed",IF(OR($H11="",$H11>ReportingFYEnd),"Not Yet in Use","Active"))) | V11: Single | W11: =IF($V11="Double",1.5,IF($V11="Triple",2,1)) | Y11: =IF($K11="","",IF(OR(ISNUMBER(SEARCH("Build",$C11)),ISNUMBER(SEARCH("Lease",$C11))),"Yes","NA")) | AA11: =IF(OR($K11="",$H11=""),"",MIN(MAX(0,IF($O11="WDV",$K11*$P11*MAX(0,(IF($I11="",AA$3,MIN($I11,AA$3)))-(MAX($H11,(EDATE(AA$3,-12)+1)))+1)/(AA$3-(EDATE(AA$3,-12)+1)+1),IF($N11=0,0,$Q11/$N11*MAX(0,(IF($I11="",AA$3,MIN($I11,AA$3)))-(MAX($H11,(EDATE(AA$3,-12)+1)))+1)/(AA$3-(EDATE(AA$3,-12)+1)+1)))*$W11),MAX(0,$K11-$M11))) | AB11: =IF($K11="","",IF(AND($I11<>"",$I11<=AA$3),0,$K11-AA11)) | AC11: =IF(OR($K11="",$H11=""),"",MIN(MAX(0,IF($O11="WDV",AB11*$P11*MAX(0,(IF($I11="",AC$3,MIN($I11,AC$3)))-(MAX($H11,(EDATE(AC$3,-12)+1)))+1)/(AC$3-(EDATE(AC$3,-12)+1)+1),IF($N11=0,0,$Q11/$N11*MAX(0,(IF($I11="",AC$3,MIN($I11,AC$3)))-(MAX($H11,(EDATE(AC$3,-12)+1)))+1)/(AC$3-(EDATE(AC$3,-12)+1)+1)))*$W11),MAX(0,AB11-$M11))) | AD11: =IF($K11="","",IF(AND($I11<>"",$I11<=AC$3),0,AB11-AC11)) | AE11: =IF(OR($K11="",$H11=""),"",MIN(MAX(0,IF($O11="WDV",AD11*$P11*MAX(0,(IF($I11="",AE$3,MIN($I11,AE$3)))-(MAX($H11,(EDATE(AE$3,-12)+1)))+1)/(AE$3-(EDATE(AE$3,-12)+1)+1),IF($N11=0,0,$Q11/$N11*MAX(0,(IF($I11="",AE$3,MIN($I11,AE$3)))-(MAX($H11,(EDATE(AE$3,-12)+1)))+1)/(AE$3-(EDATE(AE$3,-12)+1)+1)))*$W11),MAX(0,AD11-$M11))) | AF11: =IF($K11="","",IF(AND($I11<>"",$I11<=AE$3),0,AD11-AE11)) | AG11: =IF(OR($K11="",$H11=""),"",MIN(MAX(0,IF($O11="WDV",AF11*$P11*MAX(0,(IF($I11="",AG$3,MIN($I11,AG$3)))-(MAX($H11,(EDATE(AG$3,-12)+1)))+1)/(AG$3-(EDATE(AG$3,-12)+1)+1),IF($N11=0,0,$Q11/$N11*MAX(0,(IF($I11="",AG$3,MIN($I11,AG$3)))-(MAX($H11,(EDATE(AG$3,-12)+1)))+1)/(AG$3-(EDATE(AG$3,-12)+1)+1)))*$W11),MAX(0,AF11-$M11))) | AH11: =IF($K11="","",IF(AND($I11<>"",$I11<=AG$3),0,AF11-AG11)) | AI11: =IF(OR($K11="",$H11=""),"",MIN(MAX(0,IF($O11="WDV",AH11*$P11*MAX(0,(IF($I11="",AI$3,MIN($I11,AI$3)))-(MAX($H11,(EDATE(AI$3,-12)+1)))+1)/(AI$3-(EDATE(AI$3,-12)+1)+1),IF($N11=0,0,$Q11/$N11*MAX(0,(IF($I11="",AI$3,MIN($I11,AI$3)))-(MAX($H11,(EDATE(AI$3,-12)+1)))+1)/(AI$3-(EDATE(AI$3,-12)+1)+1)))*$W11),MAX(0,AH11-$M11))) | AJ11: =IF($K11="","",IF(AND($I11<>"",$I11<=AI$3),0,AH11-AI11)) | AK11: =IF(OR($K11="",$H11=""),"",MIN(MAX(0,IF($O11="WDV",AJ11*$P11*MAX(0,(IF($I11="",AK$3,MIN($I11,AK$3)))-(MAX($H11,(EDATE(AK$3,-12)+1)))+1)/(AK$3-(EDATE(AK$3,-12)+1)+1),IF($N11=0,0,$Q11/$N11*MAX(0,(IF($I11="",AK$3,MIN($I11,AK$3)))-(MAX($H11,(EDATE(AK$3,-12)+1)))+1)/(AK$3-(EDATE(AK$3,-12)+1)+1)))*$W11),MAX(0,AJ11-$M11))) | AL11: =IF($K11="","",IF(AND($I11<>"",$I11<=AK$3),0,AJ11-AK11)) | AM11: =IF(OR($K11="",$H11=""),"",MIN(MAX(0,IF($O11="WDV",AL11*$P11*MAX(0,(IF($I11="",AM$3,MIN($I11,AM$3)))-(MAX($H11,(EDATE(AM$3,-12)+1)))+1)/(AM$3-(EDATE(AM$3,-12)+1)+1),IF($N11=0,0,$Q11/$N11*MAX(0,(IF($I11="",AM$3,MIN($I11,AM$3)))-(MAX($H11,(EDATE(AM$3,-12)+1)))+1)/(AM$3-(EDATE(AM$3,-12)+1)+1)))*$W11),MAX(0,AL11-$M11))) | AN11: =IF($K11="","",IF(AND($I11<>"",$I11<=AM$3),0,AL11-AM11)) | AO11: =IF(OR($K11="",$H11=""),"",MIN(MAX(0,IF($O11="WDV",AN11*$P11*MAX(0,(IF($I11="",AO$3,MIN($I11,AO$3)))-(MAX($H11,(EDATE(AO$3,-12)+1)))+1)/(AO$3-(EDATE(AO$3,-12)+1)+1),IF($N11=0,0,$Q11/$N11*MAX(0,(IF($I11="",AO$3,MIN($I11,AO$3)))-(MAX($H11,(EDATE(AO$3,-12)+1)))+1)/(AO$3-(EDATE(AO$3,-12)+1)+1)))*$W11),MAX(0,AN11-$M11))) | AP11: =IF($K11="","",IF(AND($I11<>"",$I11<=AO$3),0,AN11-AO11)) | AQ11: =IF(OR($K11="",$H11=""),"",MIN(MAX(0,IF($O11="WDV",AP11*$P11*MAX(0,(IF($I11="",AQ$3,MIN($I11,AQ$3)))-(MAX($H11,(EDATE(AQ$3,-12)+1)))+1)/(AQ$3-(EDATE(AQ$3,-12)+1)+1),IF($N11=0,0,$Q11/$N11*MAX(0,(IF($I11="",AQ$3,MIN($I11,AQ$3)))-(MAX($H11,(EDATE(AQ$3,-12)+1)))+1)/(AQ$3-(EDATE(AQ$3,-12)+1)+1)))*$W11),MAX(0,AP11-$M11))) | AR11: =IF($K11="","",IF(AND($I11<>"",$I11<=AQ$3),0,AP11-AQ11)) | AS11: =IF(OR($K11="",$H11=""),"",MIN(MAX(0,IF($O11="WDV",AR11*$P11*MAX(0,(IF($I11="",AS$3,MIN($I11,AS$3)))-(MAX($H11,(EDATE(AS$3,-12)+1)))+1)/(AS$3-(EDATE(AS$3,-12)+1)+1),IF($N11=0,0,$Q11/$N11*MAX(0,(IF($I11="",AS$3,MIN($I11,AS$3)))-(MAX($H11,(EDATE(AS$3,-12)+1)))+1)/(AS$3-(EDATE(AS$3,-12)+1)+1)))*$W11),MAX(0,AR11-$M11))) | AT11: =IF($K11="","",IF(AND($I11<>"",$I11<=AS$3),0,AR11-AS11)) | AU11: =IF(OR($K11="",$H11=""),"",MIN(MAX(0,IF($O11="WDV",AT11*$P11*MAX(0,(IF($I11="",AU$3,MIN($I11,AU$3)))-(MAX($H11,(EDATE(AU$3,-12)+1)))+1)/(AU$3-(EDATE(AU$3,-12)+1)+1),IF($N11=0,0,$Q11/$N11*MAX(0,(IF($I11="",AU$3,MIN($I11,AU$3)))-(MAX($H11,(EDATE(AU$3,-12)+1)))+1)/(AU$3-(EDATE(AU$3,-12)+1)+1)))*$W11),MAX(0,AT11-$M11))) | AV11: =IF($K11="","",IF(AND($I11<>"",$I11<=AU$3),0,AT11-AU11)) | AW11: =IF(OR($K11="",$H11=""),"",MIN(MAX(0,IF($O11="WDV",AV11*$P11*MAX(0,(IF($I11="",AW$3,MIN($I11,AW$3)))-(MAX($H11,(EDATE(AW$3,-12)+1)))+1)/(AW$3-(EDATE(AW$3,-12)+1)+1),IF($N11=0,0,$Q11/$N11*MAX(0,(IF($I11="",AW$3,MIN($I11,AW$3)))-(MAX($H11,(EDATE(AW$3,-12)+1)))+1)/(AW$3-(EDATE(AW$3,-12)+1)+1)))*$W11),MAX(0,AV11-$M11))) | AX11: =IF($K11="","",IF(AND($I11<>"",$I11<=AW$3),0,AV11-AW11)) | AY11: =IF(OR($K11="",$H11=""),"",MIN(MAX(0,IF($O11="WDV",AX11*$P11*MAX(0,(IF($I11="",AY$3,MIN($I11,AY$3)))-(MAX($H11,(EDATE(AY$3,-12)+1)))+1)/(AY$3-(EDATE(AY$3,-12)+1)+1),IF($N11=0,0,$Q11/$N11*MAX(0,(IF($I11="",AY$3,MIN($I11,AY$3)))-(MAX($H11,(EDATE(AY$3,-12)+1)))+1)/(AY$3-(EDATE(AY$3,-12)+1)+1)))*$W11),MAX(0,AX11-$M11))) | AZ11: =IF($K11="","",IF(AND($I11<>"",$I11<=AY$3),0,AX11-AY11)) | BA11: =IF(OR($K11="",$H11=""),"",MIN(MAX(0,IF($O11="WDV",AZ11*$P11*MAX(0,(IF($I11="",BA$3,MIN($I11,BA$3)))-(MAX($H11,(EDATE(BA$3,-12)+1)))+1)/(BA$3-(EDATE(BA$3,-12)+1)+1),IF($N11=0,0,$Q11/$N11*MAX(0,(IF($I11="",BA$3,MIN($I11,BA$3)))-(MAX($H11,(EDATE(BA$3,-12)+1)))+1)/(BA$3-(EDATE(BA$3,-12)+1)+1)))*$W11),MAX(0,AZ11-$M11))) | BB11: =IF($K11="","",IF(AND($I11<>"",$I11<=BA$3),0,AZ11-BA11)) | BC11: =IF(OR($K11="",$H11=""),"",MIN(MAX(0,IF($O11="WDV",BB11*$P11*MAX(0,(IF($I11="",BC$3,MIN($I11,BC$3)))-(MAX($H11,(EDATE(BC$3,-12)+1)))+1)/(BC$3-(EDATE(BC$3,-12)+1)+1),IF($N11=0,0,$Q11/$N11*MAX(0,(IF($I11="",BC$3,MIN($I11,BC$3)))-(MAX($H11,(EDATE(BC$3,-12)+1)))+1)/(BC$3-(EDATE(BC$3,-12)+1)+1)))*$W11),MAX(0,BB11-$M11))) | BD11: =IF($K11="","",IF(AND($I11<>"",$I11<=BC$3),0,BB11-BC11)) | BE11: =IF(OR($K11="",$H11=""),"",MIN(MAX(0,IF($O11="WDV",BD11*$P11*MAX(0,(IF($I11="",BE$3,MIN($I11,BE$3)))-(MAX($H11,(EDATE(BE$3,-12)+1)))+1)/(BE$3-(EDATE(BE$3,-12)+1)+1),IF($N11=0,0,$Q11/$N11*MAX(0,(IF($I11="",BE$3,MIN($I11,BE$3)))-(MAX($H11,(EDATE(BE$3,-12)+1)))+1)/(BE$3-(EDATE(BE$3,-12)+1)+1)))*$W11),MAX(0,BD11-$M11))) | BF11: =IF($K11="","",IF(AND($I11<>"",$I11<=BE$3),0,BD11-BE11))
A12: FA-008 | B12: Central AC Plant | C12: Air Conditioning Plant | D12: Mumbai HO | E12: Blue Star | F12: INV-AC-007 | G12: 44256 | H12: 44265 | K12: 1500000 | L12: =DefaultResidual | M12: =IF($K12="","",$K12*$L12) | N12: =IF($C12="","",IFERROR(VLOOKUP($C12,ScheduleIITable,3,FALSE),"#N/A")) | O12: =IF($K12="","",GlobalMethod) | P12: =IF(OR($K12="",$N12="",$N12=0,$M12=0),0,1-($M12/$K12)^(1/$N12)) | Q12: =IF($K12="","",$K12-$M12) | R12: =IF($K12="","",INDEX($AA12:$BF12,1,MATCH(ReportingFYEnd,$AA$3:$BF$3,0))) | S12: =IF($K12="","",IF($U12="Disposed",0,$K12-$T12)) | T12: =IF($K12="","",INDEX($AA12:$BF12,1,MATCH(ReportingFYEnd,$AA$3:$BF$3,0)+1)) | U12: =IF($K12="","",IF(AND($I12<>"",$I12<=ReportingFYEnd),"Disposed",IF(OR($H12="",$H12>ReportingFYEnd),"Not Yet in Use","Active"))) | V12: Single | W12: =IF($V12="Double",1.5,IF($V12="Triple",2,1)) | Y12: =IF($K12="","",IF(OR(ISNUMBER(SEARCH("Build",$C12)),ISNUMBER(SEARCH("Lease",$C12))),"Yes","NA")) | AA12: =IF(OR($K12="",$H12=""),"",MIN(MAX(0,IF($O12="WDV",$K12*$P12*MAX(0,(IF($I12="",AA$3,MIN($I12,AA$3)))-(MAX($H12,(EDATE(AA$3,-12)+1)))+1)/(AA$3-(EDATE(AA$3,-12)+1)+1),IF($N12=0,0,$Q12/$N12*MAX(0,(IF($I12="",AA$3,MIN($I12,AA$3)))-(MAX($H12,(EDATE(AA$3,-12)+1)))+1)/(AA$3-(EDATE(AA$3,-12)+1)+1)))*$W12),MAX(0,$K12-$M12))) | AB12: =IF($K12="","",IF(AND($I12<>"",$I12<=AA$3),0,$K12-AA12)) | AC12: =IF(OR($K12="",$H12=""),"",MIN(MAX(0,IF($O12="WDV",AB12*$P12*MAX(0,(IF($I12="",AC$3,MIN($I12,AC$3)))-(MAX($H12,(EDATE(AC$3,-12)+1)))+1)/(AC$3-(EDATE(AC$3,-12)+1)+1),IF($N12=0,0,$Q12/$N12*MAX(0,(IF($I12="",AC$3,MIN($I12,AC$3)))-(MAX($H12,(EDATE(AC$3,-12)+1)))+1)/(AC$3-(EDATE(AC$3,-12)+1)+1)))*$W12),MAX(0,AB12-$M12))) | AD12: =IF($K12="","",IF(AND($I12<>"",$I12<=AC$3),0,AB12-AC12)) | AE12: =IF(OR($K12="",$H12=""),"",MIN(MAX(0,IF($O12="WDV",AD12*$P12*MAX(0,(IF($I12="",AE$3,MIN($I12,AE$3)))-(MAX($H12,(EDATE(AE$3,-12)+1)))+1)/(AE$3-(EDATE(AE$3,-12)+1)+1),IF($N12=0,0,$Q12/$N12*MAX(0,(IF($I12="",AE$3,MIN($I12,AE$3)))-(MAX($H12,(EDATE(AE$3,-12)+1)))+1)/(AE$3-(EDATE(AE$3,-12)+1)+1)))*$W12),MAX(0,AD12-$M12))) | AF12: =IF($K12="","",IF(AND($I12<>"",$I12<=AE$3),0,AD12-AE12)) | AG12: =IF(OR($K12="",$H12=""),"",MIN(MAX(0,IF($O12="WDV",AF12*$P12*MAX(0,(IF($I12="",AG$3,MIN($I12,AG$3)))-(MAX($H12,(EDATE(AG$3,-12)+1)))+1)/(AG$3-(EDATE(AG$3,-12)+1)+1),IF($N12=0,0,$Q12/$N12*MAX(0,(IF($I12="",AG$3,MIN($I12,AG$3)))-(MAX($H12,(EDATE(AG$3,-12)+1)))+1)/(AG$3-(EDATE(AG$3,-12)+1)+1)))*$W12),MAX(0,AF12-$M12))) | AH12: =IF($K12="","",IF(AND($I12<>"",$I12<=AG$3),0,AF12-AG12)) | AI12: =IF(OR($K12="",$H12=""),"",MIN(MAX(0,IF($O12="WDV",AH12*$P12*MAX(0,(IF($I12="",AI$3,MIN($I12,AI$3)))-(MAX($H12,(EDATE(AI$3,-12)+1)))+1)/(AI$3-(EDATE(AI$3,-12)+1)+1),IF($N12=0,0,$Q12/$N12*MAX(0,(IF($I12="",AI$3,MIN($I12,AI$3)))-(MAX($H12,(EDATE(AI$3,-12)+1)))+1)/(AI$3-(EDATE(AI$3,-12)+1)+1)))*$W12),MAX(0,AH12-$M12))) | AJ12: =IF($K12="","",IF(AND($I12<>"",$I12<=AI$3),0,AH12-AI12)) | AK12: =IF(OR($K12="",$H12=""),"",MIN(MAX(0,IF($O12="WDV",AJ12*$P12*MAX(0,(IF($I12="",AK$3,MIN($I12,AK$3)))-(MAX($H12,(EDATE(AK$3,-12)+1)))+1)/(AK$3-(EDATE(AK$3,-12)+1)+1),IF($N12=0,0,$Q12/$N12*MAX(0,(IF($I12="",AK$3,MIN($I12,AK$3)))-(MAX($H12,(EDATE(AK$3,-12)+1)))+1)/(AK$3-(EDATE(AK$3,-12)+1)+1)))*$W12),MAX(0,AJ12-$M12))) | AL12: =IF($K12="","",IF(AND($I12<>"",$I12<=AK$3),0,AJ12-AK12)) | AM12: =IF(OR($K12="",$H12=""),"",MIN(MAX(0,IF($O12="WDV",AL12*$P12*MAX(0,(IF($I12="",AM$3,MIN($I12,AM$3)))-(MAX($H12,(EDATE(AM$3,-12)+1)))+1)/(AM$3-(EDATE(AM$3,-12)+1)+1),IF($N12=0,0,$Q12/$N12*MAX(0,(IF($I12="",AM$3,MIN($I12,AM$3)))-(MAX($H12,(EDATE(AM$3,-12)+1)))+1)/(AM$3-(EDATE(AM$3,-12)+1)+1)))*$W12),MAX(0,AL12-$M12))) | AN12: =IF($K12="","",IF(AND($I12<>"",$I12<=AM$3),0,AL12-AM12)) | AO12: =IF(OR($K12="",$H12=""),"",MIN(MAX(0,IF($O12="WDV",AN12*$P12*MAX(0,(IF($I12="",AO$3,MIN($I12,AO$3)))-(MAX($H12,(EDATE(AO$3,-12)+1)))+1)/(AO$3-(EDATE(AO$3,-12)+1)+1),IF($N12=0,0,$Q12/$N12*MAX(0,(IF($I12="",AO$3,MIN($I12,AO$3)))-(MAX($H12,(EDATE(AO$3,-12)+1)))+1)/(AO$3-(EDATE(AO$3,-12)+1)+1)))*$W12),MAX(0,AN12-$M12))) | AP12: =IF($K12="","",IF(AND($I12<>"",$I12<=AO$3),0,AN12-AO12)) | AQ12: =IF(OR($K12="",$H12=""),"",MIN(MAX(0,IF($O12="WDV",AP12*$P12*MAX(0,(IF($I12="",AQ$3,MIN($I12,AQ$3)))-(MAX($H12,(EDATE(AQ$3,-12)+1)))+1)/(AQ$3-(EDATE(AQ$3,-12)+1)+1),IF($N12=0,0,$Q12/$N12*MAX(0,(IF($I12="",AQ$3,MIN($I12,AQ$3)))-(MAX($H12,(EDATE(AQ$3,-12)+1)))+1)/(AQ$3-(EDATE(AQ$3,-12)+1)+1)))*$W12),MAX(0,AP12-$M12))) | AR12: =IF($K12="","",IF(AND($I12<>"",$I12<=AQ$3),0,AP12-AQ12)) | AS12: =IF(OR($K12="",$H12=""),"",MIN(MAX(0,IF($O12="WDV",AR12*$P12*MAX(0,(IF($I12="",AS$3,MIN($I12,AS$3)))-(MAX($H12,(EDATE(AS$3,-12)+1)))+1)/(AS$3-(EDATE(AS$3,-12)+1)+1),IF($N12=0,0,$Q12/$N12*MAX(0,(IF($I12="",AS$3,MIN($I12,AS$3)))-(MAX($H12,(EDATE(AS$3,-12)+1)))+1)/(AS$3-(EDATE(AS$3,-12)+1)+1)))*$W12),MAX(0,AR12-$M12))) | AT12: =IF($K12="","",IF(AND($I12<>"",$I12<=AS$3),0,AR12-AS12)) | AU12: =IF(OR($K12="",$H12=""),"",MIN(MAX(0,IF($O12="WDV",AT12*$P12*MAX(0,(IF($I12="",AU$3,MIN($I12,AU$3)))-(MAX($H12,(EDATE(AU$3,-12)+1)))+1)/(AU$3-(EDATE(AU$3,-12)+1)+1),IF($N12=0,0,$Q12/$N12*MAX(0,(IF($I12="",AU$3,MIN($I12,AU$3)))-(MAX($H12,(EDATE(AU$3,-12)+1)))+1)/(AU$3-(EDATE(AU$3,-12)+1)+1)))*$W12),MAX(0,AT12-$M12))) | AV12: =IF($K12="","",IF(AND($I12<>"",$I12<=AU$3),0,AT12-AU12)) | AW12: =IF(OR($K12="",$H12=""),"",MIN(MAX(0,IF($O12="WDV",AV12*$P12*MAX(0,(IF($I12="",AW$3,MIN($I12,AW$3)))-(MAX($H12,(EDATE(AW$3,-12)+1)))+1)/(AW$3-(EDATE(AW$3,-12)+1)+1),IF($N12=0,0,$Q12/$N12*MAX(0,(IF($I12="",AW$3,MIN($I12,AW$3)))-(MAX($H12,(EDATE(AW$3,-12)+1)))+1)/(AW$3-(EDATE(AW$3,-12)+1)+1)))*$W12),MAX(0,AV12-$M12))) | AX12: =IF($K12="","",IF(AND($I12<>"",$I12<=AW$3),0,AV12-AW12)) | AY12: =IF(OR($K12="",$H12=""),"",MIN(MAX(0,IF($O12="WDV",AX12*$P12*MAX(0,(IF($I12="",AY$3,MIN($I12,AY$3)))-(MAX($H12,(EDATE(AY$3,-12)+1)))+1)/(AY$3-(EDATE(AY$3,-12)+1)+1),IF($N12=0,0,$Q12/$N12*MAX(0,(IF($I12="",AY$3,MIN($I12,AY$3)))-(MAX($H12,(EDATE(AY$3,-12)+1)))+1)/(AY$3-(EDATE(AY$3,-12)+1)+1)))*$W12),MAX(0,AX12-$M12))) | AZ12: =IF($K12="","",IF(AND($I12<>"",$I12<=AY$3),0,AX12-AY12)) | BA12: =IF(OR($K12="",$H12=""),"",MIN(MAX(0,IF($O12="WDV",AZ12*$P12*MAX(0,(IF($I12="",BA$3,MIN($I12,BA$3)))-(MAX($H12,(EDATE(BA$3,-12)+1)))+1)/(BA$3-(EDATE(BA$3,-12)+1)+1),IF($N12=0,0,$Q12/$N12*MAX(0,(IF($I12="",BA$3,MIN($I12,BA$3)))-(MAX($H12,(EDATE(BA$3,-12)+1)))+1)/(BA$3-(EDATE(BA$3,-12)+1)+1)))*$W12),MAX(0,AZ12-$M12))) | BB12: =IF($K12="","",IF(AND($I12<>"",$I12<=BA$3),0,AZ12-BA12)) | BC12: =IF(OR($K12="",$H12=""),"",MIN(MAX(0,IF($O12="WDV",BB12*$P12*MAX(0,(IF($I12="",BC$3,MIN($I12,BC$3)))-(MAX($H12,(EDATE(BC$3,-12)+1)))+1)/(BC$3-(EDATE(BC$3,-12)+1)+1),IF($N12=0,0,$Q12/$N12*MAX(0,(IF($I12="",BC$3,MIN($I12,BC$3)))-(MAX($H12,(EDATE(BC$3,-12)+1)))+1)/(BC$3-(EDATE(BC$3,-12)+1)+1)))*$W12),MAX(0,BB12-$M12))) | BD12: =IF($K12="","",IF(AND($I12<>"",$I12<=BC$3),0,BB12-BC12)) | BE12: =IF(OR($K12="",$H12=""),"",MIN(MAX(0,IF($O12="WDV",BD12*$P12*MAX(0,(IF($I12="",BE$3,MIN($I12,BE$3)))-(MAX($H12,(EDATE(BE$3,-12)+1)))+1)/(BE$3-(EDATE(BE$3,-12)+1)+1),IF($N12=0,0,$Q12/$N12*MAX(0,(IF($I12="",BE$3,MIN($I12,BE$3)))-(MAX($H12,(EDATE(BE$3,-12)+1)))+1)/(BE$3-(EDATE(BE$3,-12)+1)+1)))*$W12),MAX(0,BD12-$M12))) | BF12: =IF($K12="","",IF(AND($I12<>"",$I12<=BE$3),0,BD12-BE12))
A13: FA-009 | B13: Electrical Installation | C13: Electrical Installations | D13: Pune Plant | E13: Schneider | F13: INV-EL-033 | G13: 44044 | H13: 44075 | K13: 2200000 | L13: =DefaultResidual | M13: =IF($K13="","",$K13*$L13) | N13: =IF($C13="","",IFERROR(VLOOKUP($C13,ScheduleIITable,3,FALSE),"#N/A")) | O13: =IF($K13="","",GlobalMethod) | P13: =IF(OR($K13="",$N13="",$N13=0,$M13=0),0,1-($M13/$K13)^(1/$N13)) | Q13: =IF($K13="","",$K13-$M13) | R13: =IF($K13="","",INDEX($AA13:$BF13,1,MATCH(ReportingFYEnd,$AA$3:$BF$3,0))) | S13: =IF($K13="","",IF($U13="Disposed",0,$K13-$T13)) | T13: =IF($K13="","",INDEX($AA13:$BF13,1,MATCH(ReportingFYEnd,$AA$3:$BF$3,0)+1)) | U13: =IF($K13="","",IF(AND($I13<>"",$I13<=ReportingFYEnd),"Disposed",IF(OR($H13="",$H13>ReportingFYEnd),"Not Yet in Use","Active"))) | V13: Single | W13: =IF($V13="Double",1.5,IF($V13="Triple",2,1)) | Y13: =IF($K13="","",IF(OR(ISNUMBER(SEARCH("Build",$C13)),ISNUMBER(SEARCH("Lease",$C13))),"Yes","NA")) | AA13: =IF(OR($K13="",$H13=""),"",MIN(MAX(0,IF($O13="WDV",$K13*$P13*MAX(0,(IF($I13="",AA$3,MIN($I13,AA$3)))-(MAX($H13,(EDATE(AA$3,-12)+1)))+1)/(AA$3-(EDATE(AA$3,-12)+1)+1),IF($N13=0,0,$Q13/$N13*MAX(0,(IF($I13="",AA$3,MIN($I13,AA$3)))-(MAX($H13,(EDATE(AA$3,-12)+1)))+1)/(AA$3-(EDATE(AA$3,-12)+1)+1)))*$W13),MAX(0,$K13-$M13))) | AB13: =IF($K13="","",IF(AND($I13<>"",$I13<=AA$3),0,$K13-AA13)) | AC13: =IF(OR($K13="",$H13=""),"",MIN(MAX(0,IF($O13="WDV",AB13*$P13*MAX(0,(IF($I13="",AC$3,MIN($I13,AC$3)))-(MAX($H13,(EDATE(AC$3,-12)+1)))+1)/(AC$3-(EDATE(AC$3,-12)+1)+1),IF($N13=0,0,$Q13/$N13*MAX(0,(IF($I13="",AC$3,MIN($I13,AC$3)))-(MAX($H13,(EDATE(AC$3,-12)+1)))+1)/(AC$3-(EDATE(AC$3,-12)+1)+1)))*$W13),MAX(0,AB13-$M13))) | AD13: =IF($K13="","",IF(AND($I13<>"",$I13<=AC$3),0,AB13-AC13)) | AE13: =IF(OR($K13="",$H13=""),"",MIN(MAX(0,IF($O13="WDV",AD13*$P13*MAX(0,(IF($I13="",AE$3,MIN($I13,AE$3)))-(MAX($H13,(EDATE(AE$3,-12)+1)))+1)/(AE$3-(EDATE(AE$3,-12)+1)+1),IF($N13=0,0,$Q13/$N13*MAX(0,(IF($I13="",AE$3,MIN($I13,AE$3)))-(MAX($H13,(EDATE(AE$3,-12)+1)))+1)/(AE$3-(EDATE(AE$3,-12)+1)+1)))*$W13),MAX(0,AD13-$M13))) | AF13: =IF($K13="","",IF(AND($I13<>"",$I13<=AE$3),0,AD13-AE13)) | AG13: =IF(OR($K13="",$H13=""),"",MIN(MAX(0,IF($O13="WDV",AF13*$P13*MAX(0,(IF($I13="",AG$3,MIN($I13,AG$3)))-(MAX($H13,(EDATE(AG$3,-12)+1)))+1)/(AG$3-(EDATE(AG$3,-12)+1)+1),IF($N13=0,0,$Q13/$N13*MAX(0,(IF($I13="",AG$3,MIN($I13,AG$3)))-(MAX($H13,(EDATE(AG$3,-12)+1)))+1)/(AG$3-(EDATE(AG$3,-12)+1)+1)))*$W13),MAX(0,AF13-$M13))) | AH13: =IF($K13="","",IF(AND($I13<>"",$I13<=AG$3),0,AF13-AG13)) | AI13: =IF(OR($K13="",$H13=""),"",MIN(MAX(0,IF($O13="WDV",AH13*$P13*MAX(0,(IF($I13="",AI$3,MIN($I13,AI$3)))-(MAX($H13,(EDATE(AI$3,-12)+1)))+1)/(AI$3-(EDATE(AI$3,-12)+1)+1),IF($N13=0,0,$Q13/$N13*MAX(0,(IF($I13="",AI$3,MIN($I13,AI$3)))-(MAX($H13,(EDATE(AI$3,-12)+1)))+1)/(AI$3-(EDATE(AI$3,-12)+1)+1)))*$W13),MAX(0,AH13-$M13))) | AJ13: =IF($K13="","",IF(AND($I13<>"",$I13<=AI$3),0,AH13-AI13)) | AK13: =IF(OR($K13="",$H13=""),"",MIN(MAX(0,IF($O13="WDV",AJ13*$P13*MAX(0,(IF($I13="",AK$3,MIN($I13,AK$3)))-(MAX($H13,(EDATE(AK$3,-12)+1)))+1)/(AK$3-(EDATE(AK$3,-12)+1)+1),IF($N13=0,0,$Q13/$N13*MAX(0,(IF($I13="",AK$3,MIN($I13,AK$3)))-(MAX($H13,(EDATE(AK$3,-12)+1)))+1)/(AK$3-(EDATE(AK$3,-12)+1)+1)))*$W13),MAX(0,AJ13-$M13))) | AL13: =IF($K13="","",IF(AND($I13<>"",$I13<=AK$3),0,AJ13-AK13)) | AM13: =IF(OR($K13="",$H13=""),"",MIN(MAX(0,IF($O13="WDV",AL13*$P13*MAX(0,(IF($I13="",AM$3,MIN($I13,AM$3)))-(MAX($H13,(EDATE(AM$3,-12)+1)))+1)/(AM$3-(EDATE(AM$3,-12)+1)+1),IF($N13=0,0,$Q13/$N13*MAX(0,(IF($I13="",AM$3,MIN($I13,AM$3)))-(MAX($H13,(EDATE(AM$3,-12)+1)))+1)/(AM$3-(EDATE(AM$3,-12)+1)+1)))*$W13),MAX(0,AL13-$M13))) | AN13: =IF($K13="","",IF(AND($I13<>"",$I13<=AM$3),0,AL13-AM13)) | AO13: =IF(OR($K13="",$H13=""),"",MIN(MAX(0,IF($O13="WDV",AN13*$P13*MAX(0,(IF($I13="",AO$3,MIN($I13,AO$3)))-(MAX($H13,(EDATE(AO$3,-12)+1)))+1)/(AO$3-(EDATE(AO$3,-12)+1)+1),IF($N13=0,0,$Q13/$N13*MAX(0,(IF($I13="",AO$3,MIN($I13,AO$3)))-(MAX($H13,(EDATE(AO$3,-12)+1)))+1)/(AO$3-(EDATE(AO$3,-12)+1)+1)))*$W13),MAX(0,AN13-$M13))) | AP13: =IF($K13="","",IF(AND($I13<>"",$I13<=AO$3),0,AN13-AO13)) | AQ13: =IF(OR($K13="",$H13=""),"",MIN(MAX(0,IF($O13="WDV",AP13*$P13*MAX(0,(IF($I13="",AQ$3,MIN($I13,AQ$3)))-(MAX($H13,(EDATE(AQ$3,-12)+1)))+1)/(AQ$3-(EDATE(AQ$3,-12)+1)+1),IF($N13=0,0,$Q13/$N13*MAX(0,(IF($I13="",AQ$3,MIN($I13,AQ$3)))-(MAX($H13,(EDATE(AQ$3,-12)+1)))+1)/(AQ$3-(EDATE(AQ$3,-12)+1)+1)))*$W13),MAX(0,AP13-$M13))) | AR13: =IF($K13="","",IF(AND($I13<>"",$I13<=AQ$3),0,AP13-AQ13)) | AS13: =IF(OR($K13="",$H13=""),"",MIN(MAX(0,IF($O13="WDV",AR13*$P13*MAX(0,(IF($I13="",AS$3,MIN($I13,AS$3)))-(MAX($H13,(EDATE(AS$3,-12)+1)))+1)/(AS$3-(EDATE(AS$3,-12)+1)+1),IF($N13=0,0,$Q13/$N13*MAX(0,(IF($I13="",AS$3,MIN($I13,AS$3)))-(MAX($H13,(EDATE(AS$3,-12)+1)))+1)/(AS$3-(EDATE(AS$3,-12)+1)+1)))*$W13),MAX(0,AR13-$M13))) | AT13: =IF($K13="","",IF(AND($I13<>"",$I13<=AS$3),0,AR13-AS13)) | AU13: =IF(OR($K13="",$H13=""),"",MIN(MAX(0,IF($O13="WDV",AT13*$P13*MAX(0,(IF($I13="",AU$3,MIN($I13,AU$3)))-(MAX($H13,(EDATE(AU$3,-12)+1)))+1)/(AU$3-(EDATE(AU$3,-12)+1)+1),IF($N13=0,0,$Q13/$N13*MAX(0,(IF($I13="",AU$3,MIN($I13,AU$3)))-(MAX($H13,(EDATE(AU$3,-12)+1)))+1)/(AU$3-(EDATE(AU$3,-12)+1)+1)))*$W13),MAX(0,AT13-$M13))) | AV13: =IF($K13="","",IF(AND($I13<>"",$I13<=AU$3),0,AT13-AU13)) | AW13: =IF(OR($K13="",$H13=""),"",MIN(MAX(0,IF($O13="WDV",AV13*$P13*MAX(0,(IF($I13="",AW$3,MIN($I13,AW$3)))-(MAX($H13,(EDATE(AW$3,-12)+1)))+1)/(AW$3-(EDATE(AW$3,-12)+1)+1),IF($N13=0,0,$Q13/$N13*MAX(0,(IF($I13="",AW$3,MIN($I13,AW$3)))-(MAX($H13,(EDATE(AW$3,-12)+1)))+1)/(AW$3-(EDATE(AW$3,-12)+1)+1)))*$W13),MAX(0,AV13-$M13))) | AX13: =IF($K13="","",IF(AND($I13<>"",$I13<=AW$3),0,AV13-AW13)) | AY13: =IF(OR($K13="",$H13=""),"",MIN(MAX(0,IF($O13="WDV",AX13*$P13*MAX(0,(IF($I13="",AY$3,MIN($I13,AY$3)))-(MAX($H13,(EDATE(AY$3,-12)+1)))+1)/(AY$3-(EDATE(AY$3,-12)+1)+1),IF($N13=0,0,$Q13/$N13*MAX(0,(IF($I13="",AY$3,MIN($I13,AY$3)))-(MAX($H13,(EDATE(AY$3,-12)+1)))+1)/(AY$3-(EDATE(AY$3,-12)+1)+1)))*$W13),MAX(0,AX13-$M13))) | AZ13: =IF($K13="","",IF(AND($I13<>"",$I13<=AY$3),0,AX13-AY13)) | BA13: =IF(OR($K13="",$H13=""),"",MIN(MAX(0,IF($O13="WDV",AZ13*$P13*MAX(0,(IF($I13="",BA$3,MIN($I13,BA$3)))-(MAX($H13,(EDATE(BA$3,-12)+1)))+1)/(BA$3-(EDATE(BA$3,-12)+1)+1),IF($N13=0,0,$Q13/$N13*MAX(0,(IF($I13="",BA$3,MIN($I13,BA$3)))-(MAX($H13,(EDATE(BA$3,-12)+1)))+1)/(BA$3-(EDATE(BA$3,-12)+1)+1)))*$W13),MAX(0,AZ13-$M13))) | BB13: =IF($K13="","",IF(AND($I13<>"",$I13<=BA$3),0,AZ13-BA13)) | BC13: =IF(OR($K13="",$H13=""),"",MIN(MAX(0,IF($O13="WDV",BB13*$P13*MAX(0,(IF($I13="",BC$3,MIN($I13,BC$3)))-(MAX($H13,(EDATE(BC$3,-12)+1)))+1)/(BC$3-(EDATE(BC$3,-12)+1)+1),IF($N13=0,0,$Q13/$N13*MAX(0,(IF($I13="",BC$3,MIN($I13,BC$3)))-(MAX($H13,(EDATE(BC$3,-12)+1)))+1)/(BC$3-(EDATE(BC$3,-12)+1)+1)))*$W13),MAX(0,BB13-$M13))) | BD13: =IF($K13="","",IF(AND($I13<>"",$I13<=BC$3),0,BB13-BC13)) | BE13: =IF(OR($K13="",$H13=""),"",MIN(MAX(0,IF($O13="WDV",BD13*$P13*MAX(0,(IF($I13="",BE$3,MIN($I13,BE$3)))-(MAX($H13,(EDATE(BE$3,-12)+1)))+1)/(BE$3-(EDATE(BE$3,-12)+1)+1),IF($N13=0,0,$Q13/$N13*MAX(0,(IF($I13="",BE$3,MIN($I13,BE$3)))-(MAX($H13,(EDATE(BE$3,-12)+1)))+1)/(BE$3-(EDATE(BE$3,-12)+1)+1)))*$W13),MAX(0,BD13-$M13))) | BF13: =IF($K13="","",IF(AND($I13<>"",$I13<=BE$3),0,BD13-BE13))
A14: FA-010 | B14: Delivery Van (disposed) | C14: Motor Vehicles - Commercial | D14: Pune Plant | E14: Tata Motors | F14: INV-MV-020 | G14: 43983 | H14: 43992 | I14: 45565 | J14: 350000 | K14: 1400000 | L14: =DefaultResidual | M14: =IF($K14="","",$K14*$L14) | N14: =IF($C14="","",IFERROR(VLOOKUP($C14,ScheduleIITable,3,FALSE),"#N/A")) | O14: =IF($K14="","",GlobalMethod) | P14: =IF(OR($K14="",$N14="",$N14=0,$M14=0),0,1-($M14/$K14)^(1/$N14)) | Q14: =IF($K14="","",$K14-$M14) | R14: =IF($K14="","",INDEX($AA14:$BF14,1,MATCH(ReportingFYEnd,$AA$3:$BF$3,0))) | S14: =IF($K14="","",IF($U14="Disposed",0,$K14-$T14)) | T14: =IF($K14="","",INDEX($AA14:$BF14,1,MATCH(ReportingFYEnd,$AA$3:$BF$3,0)+1)) | U14: =IF($K14="","",IF(AND($I14<>"",$I14<=ReportingFYEnd),"Disposed",IF(OR($H14="",$H14>ReportingFYEnd),"Not Yet in Use","Active"))) | V14: Single | W14: =IF($V14="Double",1.5,IF($V14="Triple",2,1)) | Y14: =IF($K14="","",IF(OR(ISNUMBER(SEARCH("Build",$C14)),ISNUMBER(SEARCH("Lease",$C14))),"Yes","NA")) | AA14: =IF(OR($K14="",$H14=""),"",MIN(MAX(0,IF($O14="WDV",$K14*$P14*MAX(0,(IF($I14="",AA$3,MIN($I14,AA$3)))-(MAX($H14,(EDATE(AA$3,-12)+1)))+1)/(AA$3-(EDATE(AA$3,-12)+1)+1),IF($N14=0,0,$Q14/$N14*MAX(0,(IF($I14="",AA$3,MIN($I14,AA$3)))-(MAX($H14,(EDATE(AA$3,-12)+1)))+1)/(AA$3-(EDATE(AA$3,-12)+1)+1)))*$W14),MAX(0,$K14-$M14))) | AB14: =IF($K14="","",IF(AND($I14<>"",$I14<=AA$3),0,$K14-AA14)) | AC14: =IF(OR($K14="",$H14=""),"",MIN(MAX(0,IF($O14="WDV",AB14*$P14*MAX(0,(IF($I14="",AC$3,MIN($I14,AC$3)))-(MAX($H14,(EDATE(AC$3,-12)+1)))+1)/(AC$3-(EDATE(AC$3,-12)+1)+1),IF($N14=0,0,$Q14/$N14*MAX(0,(IF($I14="",AC$3,MIN($I14,AC$3)))-(MAX($H14,(EDATE(AC$3,-12)+1)))+1)/(AC$3-(EDATE(AC$3,-12)+1)+1)))*$W14),MAX(0,AB14-$M14))) | AD14: =IF($K14="","",IF(AND($I14<>"",$I14<=AC$3),0,AB14-AC14)) | AE14: =IF(OR($K14="",$H14=""),"",MIN(MAX(0,IF($O14="WDV",AD14*$P14*MAX(0,(IF($I14="",AE$3,MIN($I14,AE$3)))-(MAX($H14,(EDATE(AE$3,-12)+1)))+1)/(AE$3-(EDATE(AE$3,-12)+1)+1),IF($N14=0,0,$Q14/$N14*MAX(0,(IF($I14="",AE$3,MIN($I14,AE$3)))-(MAX($H14,(EDATE(AE$3,-12)+1)))+1)/(AE$3-(EDATE(AE$3,-12)+1)+1)))*$W14),MAX(0,AD14-$M14))) | AF14: =IF($K14="","",IF(AND($I14<>"",$I14<=AE$3),0,AD14-AE14)) | AG14: =IF(OR($K14="",$H14=""),"",MIN(MAX(0,IF($O14="WDV",AF14*$P14*MAX(0,(IF($I14="",AG$3,MIN($I14,AG$3)))-(MAX($H14,(EDATE(AG$3,-12)+1)))+1)/(AG$3-(EDATE(AG$3,-12)+1)+1),IF($N14=0,0,$Q14/$N14*MAX(0,(IF($I14="",AG$3,MIN($I14,AG$3)))-(MAX($H14,(EDATE(AG$3,-12)+1)))+1)/(AG$3-(EDATE(AG$3,-12)+1)+1)))*$W14),MAX(0,AF14-$M14))) | AH14: =IF($K14="","",IF(AND($I14<>"",$I14<=AG$3),0,AF14-AG14)) | AI14: =IF(OR($K14="",$H14=""),"",MIN(MAX(0,IF($O14="WDV",AH14*$P14*MAX(0,(IF($I14="",AI$3,MIN($I14,AI$3)))-(MAX($H14,(EDATE(AI$3,-12)+1)))+1)/(AI$3-(EDATE(AI$3,-12)+1)+1),IF($N14=0,0,$Q14/$N14*MAX(0,(IF($I14="",AI$3,MIN($I14,AI$3)))-(MAX($H14,(EDATE(AI$3,-12)+1)))+1)/(AI$3-(EDATE(AI$3,-12)+1)+1)))*$W14),MAX(0,AH14-$M14))) | AJ14: =IF($K14="","",IF(AND($I14<>"",$I14<=AI$3),0,AH14-AI14)) | AK14: =IF(OR($K14="",$H14=""),"",MIN(MAX(0,IF($O14="WDV",AJ14*$P14*MAX(0,(IF($I14="",AK$3,MIN($I14,AK$3)))-(MAX($H14,(EDATE(AK$3,-12)+1)))+1)/(AK$3-(EDATE(AK$3,-12)+1)+1),IF($N14=0,0,$Q14/$N14*MAX(0,(IF($I14="",AK$3,MIN($I14,AK$3)))-(MAX($H14,(EDATE(AK$3,-12)+1)))+1)/(AK$3-(EDATE(AK$3,-12)+1)+1)))*$W14),MAX(0,AJ14-$M14))) | AL14: =IF($K14="","",IF(AND($I14<>"",$I14<=AK$3),0,AJ14-AK14)) | AM14: =IF(OR($K14="",$H14=""),"",MIN(MAX(0,IF($O14="WDV",AL14*$P14*MAX(0,(IF($I14="",AM$3,MIN($I14,AM$3)))-(MAX($H14,(EDATE(AM$3,-12)+1)))+1)/(AM$3-(EDATE(AM$3,-12)+1)+1),IF($N14=0,0,$Q14/$N14*MAX(0,(IF($I14="",AM$3,MIN($I14,AM$3)))-(MAX($H14,(EDATE(AM$3,-12)+1)))+1)/(AM$3-(EDATE(AM$3,-12)+1)+1)))*$W14),MAX(0,AL14-$M14))) | AN14: =IF($K14="","",IF(AND($I14<>"",$I14<=AM$3),0,AL14-AM14)) | AO14: =IF(OR($K14="",$H14=""),"",MIN(MAX(0,IF($O14="WDV",AN14*$P14*MAX(0,(IF($I14="",AO$3,MIN($I14,AO$3)))-(MAX($H14,(EDATE(AO$3,-12)+1)))+1)/(AO$3-(EDATE(AO$3,-12)+1)+1),IF($N14=0,0,$Q14/$N14*MAX(0,(IF($I14="",AO$3,MIN($I14,AO$3)))-(MAX($H14,(EDATE(AO$3,-12)+1)))+1)/(AO$3-(EDATE(AO$3,-12)+1)+1)))*$W14),MAX(0,AN14-$M14))) | AP14: =IF($K14="","",IF(AND($I14<>"",$I14<=AO$3),0,AN14-AO14)) | AQ14: =IF(OR($K14="",$H14=""),"",MIN(MAX(0,IF($O14="WDV",AP14*$P14*MAX(0,(IF($I14="",AQ$3,MIN($I14,AQ$3)))-(MAX($H14,(EDATE(AQ$3,-12)+1)))+1)/(AQ$3-(EDATE(AQ$3,-12)+1)+1),IF($N14=0,0,$Q14/$N14*MAX(0,(IF($I14="",AQ$3,MIN($I14,AQ$3)))-(MAX($H14,(EDATE(AQ$3,-12)+1)))+1)/(AQ$3-(EDATE(AQ$3,-12)+1)+1)))*$W14),MAX(0,AP14-$M14))) | AR14: =IF($K14="","",IF(AND($I14<>"",$I14<=AQ$3),0,AP14-AQ14)) | AS14: =IF(OR($K14="",$H14=""),"",MIN(MAX(0,IF($O14="WDV",AR14*$P14*MAX(0,(IF($I14="",AS$3,MIN($I14,AS$3)))-(MAX($H14,(EDATE(AS$3,-12)+1)))+1)/(AS$3-(EDATE(AS$3,-12)+1)+1),IF($N14=0,0,$Q14/$N14*MAX(0,(IF($I14="",AS$3,MIN($I14,AS$3)))-(MAX($H14,(EDATE(AS$3,-12)+1)))+1)/(AS$3-(EDATE(AS$3,-12)+1)+1)))*$W14),MAX(0,AR14-$M14))) | AT14: =IF($K14="","",IF(AND($I14<>"",$I14<=AS$3),0,AR14-AS14)) | AU14: =IF(OR($K14="",$H14=""),"",MIN(MAX(0,IF($O14="WDV",AT14*$P14*MAX(0,(IF($I14="",AU$3,MIN($I14,AU$3)))-(MAX($H14,(EDATE(AU$3,-12)+1)))+1)/(AU$3-(EDATE(AU$3,-12)+1)+1),IF($N14=0,0,$Q14/$N14*MAX(0,(IF($I14="",AU$3,MIN($I14,AU$3)))-(MAX($H14,(EDATE(AU$3,-12)+1)))+1)/(AU$3-(EDATE(AU$3,-12)+1)+1)))*$W14),MAX(0,AT14-$M14))) | AV14: =IF($K14="","",IF(AND($I14<>"",$I14<=AU$3),0,AT14-AU14)) | AW14: =IF(OR($K14="",$H14=""),"",MIN(MAX(0,IF($O14="WDV",AV14*$P14*MAX(0,(IF($I14="",AW$3,MIN($I14,AW$3)))-(MAX($H14,(EDATE(AW$3,-12)+1)))+1)/(AW$3-(EDATE(AW$3,-12)+1)+1),IF($N14=0,0,$Q14/$N14*MAX(0,(IF($I14="",AW$3,MIN($I14,AW$3)))-(MAX($H14,(EDATE(AW$3,-12)+1)))+1)/(AW$3-(EDATE(AW$3,-12)+1)+1)))*$W14),MAX(0,AV14-$M14))) | AX14: =IF($K14="","",IF(AND($I14<>"",$I14<=AW$3),0,AV14-AW14)) | AY14: =IF(OR($K14="",$H14=""),"",MIN(MAX(0,IF($O14="WDV",AX14*$P14*MAX(0,(IF($I14="",AY$3,MIN($I14,AY$3)))-(MAX($H14,(EDATE(AY$3,-12)+1)))+1)/(AY$3-(EDATE(AY$3,-12)+1)+1),IF($N14=0,0,$Q14/$N14*MAX(0,(IF($I14="",AY$3,MIN($I14,AY$3)))-(MAX($H14,(EDATE(AY$3,-12)+1)))+1)/(AY$3-(EDATE(AY$3,-12)+1)+1)))*$W14),MAX(0,AX14-$M14))) | AZ14: =IF($K14="","",IF(AND($I14<>"",$I14<=AY$3),0,AX14-AY14)) | BA14: =IF(OR($K14="",$H14=""),"",MIN(MAX(0,IF($O14="WDV",AZ14*$P14*MAX(0,(IF($I14="",BA$3,MIN($I14,BA$3)))-(MAX($H14,(EDATE(BA$3,-12)+1)))+1)/(BA$3-(EDATE(BA$3,-12)+1)+1),IF($N14=0,0,$Q14/$N14*MAX(0,(IF($I14="",BA$3,MIN($I14,BA$3)))-(MAX($H14,(EDATE(BA$3,-12)+1)))+1)/(BA$3-(EDATE(BA$3,-12)+1)+1)))*$W14),MAX(0,AZ14-$M14))) | BB14: =IF($K14="","",IF(AND($I14<>"",$I14<=BA$3),0,AZ14-BA14)) | BC14: =IF(OR($K14="",$H14=""),"",MIN(MAX(0,IF($O14="WDV",BB14*$P14*MAX(0,(IF($I14="",BC$3,MIN($I14,BC$3)))-(MAX($H14,(EDATE(BC$3,-12)+1)))+1)/(BC$3-(EDATE(BC$3,-12)+1)+1),IF($N14=0,0,$Q14/$N14*MAX(0,(IF($I14="",BC$3,MIN($I14,BC$3)))-(MAX($H14,(EDATE(BC$3,-12)+1)))+1)/(BC$3-(EDATE(BC$3,-12)+1)+1)))*$W14),MAX(0,BB14-$M14))) | BD14: =IF($K14="","",IF(AND($I14<>"",$I14<=BC$3),0,BB14-BC14)) | BE14: =IF(OR($K14="",$H14=""),"",MIN(MAX(0,IF($O14="WDV",BD14*$P14*MAX(0,(IF($I14="",BE$3,MIN($I14,BE$3)))-(MAX($H14,(EDATE(BE$3,-12)+1)))+1)/(BE$3-(EDATE(BE$3,-12)+1)+1),IF($N14=0,0,$Q14/$N14*MAX(0,(IF($I14="",BE$3,MIN($I14,BE$3)))-(MAX($H14,(EDATE(BE$3,-12)+1)))+1)/(BE$3-(EDATE(BE$3,-12)+1)+1)))*$W14),MAX(0,BD14-$M14))) | BF14: =IF($K14="","",IF(AND($I14<>"",$I14<=BE$3),0,BD14-BE14))
L15: =DefaultResidual | M15: =IF($K15="","",$K15*$L15) | N15: =IF($C15="","",IFERROR(VLOOKUP($C15,ScheduleIITable,3,FALSE),"#N/A")) | O15: =IF($K15="","",GlobalMethod) | P15: =IF(OR($K15="",$N15="",$N15=0,$M15=0),0,1-($M15/$K15)^(1/$N15)) | Q15: =IF($K15="","",$K15-$M15) | R15: =IF($K15="","",INDEX($AA15:$BF15,1,MATCH(ReportingFYEnd,$AA$3:$BF$3,0))) | S15: =IF($K15="","",IF($U15="Disposed",0,$K15-$T15)) | T15: =IF($K15="","",INDEX($AA15:$BF15,1,MATCH(ReportingFYEnd,$AA$3:$BF$3,0)+1)) | U15: =IF($K15="","",IF(AND($I15<>"",$I15<=ReportingFYEnd),"Disposed",IF(OR($H15="",$H15>ReportingFYEnd),"Not Yet in Use","Active"))) | W15: =IF($V15="Double",1.5,IF($V15="Triple",2,1)) | Y15: =IF($K15="","",IF(OR(ISNUMBER(SEARCH("Build",$C15)),ISNUMBER(SEARCH("Lease",$C15))),"Yes","NA")) | AA15: =IF(OR($K15="",$H15=""),"",MIN(MAX(0,IF($O15="WDV",$K15*$P15*MAX(0,(IF($I15="",AA$3,MIN($I15,AA$3)))-(MAX($H15,(EDATE(AA$3,-12)+1)))+1)/(AA$3-(EDATE(AA$3,-12)+1)+1),IF($N15=0,0,$Q15/$N15*MAX(0,(IF($I15="",AA$3,MIN($I15,AA$3)))-(MAX($H15,(EDATE(AA$3,-12)+1)))+1)/(AA$3-(EDATE(AA$3,-12)+1)+1)))*$W15),MAX(0,$K15-$M15))) | AB15: =IF($K15="","",IF(AND($I15<>"",$I15<=AA$3),0,$K15-AA15)) | AC15: =IF(OR($K15="",$H15=""),"",MIN(MAX(0,IF($O15="WDV",AB15*$P15*MAX(0,(IF($I15="",AC$3,MIN($I15,AC$3)))-(MAX($H15,(EDATE(AC$3,-12)+1)))+1)/(AC$3-(EDATE(AC$3,-12)+1)+1),IF($N15=0,0,$Q15/$N15*MAX(0,(IF($I15="",AC$3,MIN($I15,AC$3)))-(MAX($H15,(EDATE(AC$3,-12)+1)))+1)/(AC$3-(EDATE(AC$3,-12)+1)+1)))*$W15),MAX(0,AB15-$M15))) | AD15: =IF($K15="","",IF(AND($I15<>"",$I15<=AC$3),0,AB15-AC15)) | AE15: =IF(OR($K15="",$H15=""),"",MIN(MAX(0,IF($O15="WDV",AD15*$P15*MAX(0,(IF($I15="",AE$3,MIN($I15,AE$3)))-(MAX($H15,(EDATE(AE$3,-12)+1)))+1)/(AE$3-(EDATE(AE$3,-12)+1)+1),IF($N15=0,0,$Q15/$N15*MAX(0,(IF($I15="",AE$3,MIN($I15,AE$3)))-(MAX($H15,(EDATE(AE$3,-12)+1)))+1)/(AE$3-(EDATE(AE$3,-12)+1)+1)))*$W15),MAX(0,AD15-$M15))) | AF15: =IF($K15="","",IF(AND($I15<>"",$I15<=AE$3),0,AD15-AE15)) | AG15: =IF(OR($K15="",$H15=""),"",MIN(MAX(0,IF($O15="WDV",AF15*$P15*MAX(0,(IF($I15="",AG$3,MIN($I15,AG$3)))-(MAX($H15,(EDATE(AG$3,-12)+1)))+1)/(AG$3-(EDATE(AG$3,-12)+1)+1),IF($N15=0,0,$Q15/$N15*MAX(0,(IF($I15="",AG$3,MIN($I15,AG$3)))-(MAX($H15,(EDATE(AG$3,-12)+1)))+1)/(AG$3-(EDATE(AG$3,-12)+1)+1)))*$W15),MAX(0,AF15-$M15))) | AH15: =IF($K15="","",IF(AND($I15<>"",$I15<=AG$3),0,AF15-AG15)) | AI15: =IF(OR($K15="",$H15=""),"",MIN(MAX(0,IF($O15="WDV",AH15*$P15*MAX(0,(IF($I15="",AI$3,MIN($I15,AI$3)))-(MAX($H15,(EDATE(AI$3,-12)+1)))+1)/(AI$3-(EDATE(AI$3,-12)+1)+1),IF($N15=0,0,$Q15/$N15*MAX(0,(IF($I15="",AI$3,MIN($I15,AI$3)))-(MAX($H15,(EDATE(AI$3,-12)+1)))+1)/(AI$3-(EDATE(AI$3,-12)+1)+1)))*$W15),MAX(0,AH15-$M15))) | AJ15: =IF($K15="","",IF(AND($I15<>"",$I15<=AI$3),0,AH15-AI15)) | AK15: =IF(OR($K15="",$H15=""),"",MIN(MAX(0,IF($O15="WDV",AJ15*$P15*MAX(0,(IF($I15="",AK$3,MIN($I15,AK$3)))-(MAX($H15,(EDATE(AK$3,-12)+1)))+1)/(AK$3-(EDATE(AK$3,-12)+1)+1),IF($N15=0,0,$Q15/$N15*MAX(0,(IF($I15="",AK$3,MIN($I15,AK$3)))-(MAX($H15,(EDATE(AK$3,-12)+1)))+1)/(AK$3-(EDATE(AK$3,-12)+1)+1)))*$W15),MAX(0,AJ15-$M15))) | AL15: =IF($K15="","",IF(AND($I15<>"",$I15<=AK$3),0,AJ15-AK15)) | AM15: =IF(OR($K15="",$H15=""),"",MIN(MAX(0,IF($O15="WDV",AL15*$P15*MAX(0,(IF($I15="",AM$3,MIN($I15,AM$3)))-(MAX($H15,(EDATE(AM$3,-12)+1)))+1)/(AM$3-(EDATE(AM$3,-12)+1)+1),IF($N15=0,0,$Q15/$N15*MAX(0,(IF($I15="",AM$3,MIN($I15,AM$3)))-(MAX($H15,(EDATE(AM$3,-12)+1)))+1)/(AM$3-(EDATE(AM$3,-12)+1)+1)))*$W15),MAX(0,AL15-$M15))) | AN15: =IF($K15="","",IF(AND($I15<>"",$I15<=AM$3),0,AL15-AM15)) | AO15: =IF(OR($K15="",$H15=""),"",MIN(MAX(0,IF($O15="WDV",AN15*$P15*MAX(0,(IF($I15="",AO$3,MIN($I15,AO$3)))-(MAX($H15,(EDATE(AO$3,-12)+1)))+1)/(AO$3-(EDATE(AO$3,-12)+1)+1),IF($N15=0,0,$Q15/$N15*MAX(0,(IF($I15="",AO$3,MIN($I15,AO$3)))-(MAX($H15,(EDATE(AO$3,-12)+1)))+1)/(AO$3-(EDATE(AO$3,-12)+1)+1)))*$W15),MAX(0,AN15-$M15))) | AP15: =IF($K15="","",IF(AND($I15<>"",$I15<=AO$3),0,AN15-AO15)) | AQ15: =IF(OR($K15="",$H15=""),"",MIN(MAX(0,IF($O15="WDV",AP15*$P15*MAX(0,(IF($I15="",AQ$3,MIN($I15,AQ$3)))-(MAX($H15,(EDATE(AQ$3,-12)+1)))+1)/(AQ$3-(EDATE(AQ$3,-12)+1)+1),IF($N15=0,0,$Q15/$N15*MAX(0,(IF($I15="",AQ$3,MIN($I15,AQ$3)))-(MAX($H15,(EDATE(AQ$3,-12)+1)))+1)/(AQ$3-(EDATE(AQ$3,-12)+1)+1)))*$W15),MAX(0,AP15-$M15))) | AR15: =IF($K15="","",IF(AND($I15<>"",$I15<=AQ$3),0,AP15-AQ15)) | AS15: =IF(OR($K15="",$H15=""),"",MIN(MAX(0,IF($O15="WDV",AR15*$P15*MAX(0,(IF($I15="",AS$3,MIN($I15,AS$3)))-(MAX($H15,(EDATE(AS$3,-12)+1)))+1)/(AS$3-(EDATE(AS$3,-12)+1)+1),IF($N15=0,0,$Q15/$N15*MAX(0,(IF($I15="",AS$3,MIN($I15,AS$3)))-(MAX($H15,(EDATE(AS$3,-12)+1)))+1)/(AS$3-(EDATE(AS$3,-12)+1)+1)))*$W15),MAX(0,AR15-$M15))) | AT15: =IF($K15="","",IF(AND($I15<>"",$I15<=AS$3),0,AR15-AS15)) | AU15: =IF(OR($K15="",$H15=""),"",MIN(MAX(0,IF($O15="WDV",AT15*$P15*MAX(0,(IF($I15="",AU$3,MIN($I15,AU$3)))-(MAX($H15,(EDATE(AU$3,-12)+1)))+1)/(AU$3-(EDATE(AU$3,-12)+1)+1),IF($N15=0,0,$Q15/$N15*MAX(0,(IF($I15="",AU$3,MIN($I15,AU$3)))-(MAX($H15,(EDATE(AU$3,-12)+1)))+1)/(AU$3-(EDATE(AU$3,-12)+1)+1)))*$W15),MAX(0,AT15-$M15))) | AV15: =IF($K15="","",IF(AND($I15<>"",$I15<=AU$3),0,AT15-AU15)) | AW15: =IF(OR($K15="",$H15=""),"",MIN(MAX(0,IF($O15="WDV",AV15*$P15*MAX(0,(IF($I15="",AW$3,MIN($I15,AW$3)))-(MAX($H15,(EDATE(AW$3,-12)+1)))+1)/(AW$3-(EDATE(AW$3,-12)+1)+1),IF($N15=0,0,$Q15/$N15*MAX(0,(IF($I15="",AW$3,MIN($I15,AW$3)))-(MAX($H15,(EDATE(AW$3,-12)+1)))+1)/(AW$3-(EDATE(AW$3,-12)+1)+1)))*$W15),MAX(0,AV15-$M15))) | AX15: =IF($K15="","",IF(AND($I15<>"",$I15<=AW$3),0,AV15-AW15)) | AY15: =IF(OR($K15="",$H15=""),"",MIN(MAX(0,IF($O15="WDV",AX15*$P15*MAX(0,(IF($I15="",AY$3,MIN($I15,AY$3)))-(MAX($H15,(EDATE(AY$3,-12)+1)))+1)/(AY$3-(EDATE(AY$3,-12)+1)+1),IF($N15=0,0,$Q15/$N15*MAX(0,(IF($I15="",AY$3,MIN($I15,AY$3)))-(MAX($H15,(EDATE(AY$3,-12)+1)))+1)/(AY$3-(EDATE(AY$3,-12)+1)+1)))*$W15),MAX(0,AX15-$M15))) | AZ15: =IF($K15="","",IF(AND($I15<>"",$I15<=AY$3),0,AX15-AY15)) | BA15: =IF(OR($K15="",$H15=""),"",MIN(MAX(0,IF($O15="WDV",AZ15*$P15*MAX(0,(IF($I15="",BA$3,MIN($I15,BA$3)))-(MAX($H15,(EDATE(BA$3,-12)+1)))+1)/(BA$3-(EDATE(BA$3,-12)+1)+1),IF($N15=0,0,$Q15/$N15*MAX(0,(IF($I15="",BA$3,MIN($I15,BA$3)))-(MAX($H15,(EDATE(BA$3,-12)+1)))+1)/(BA$3-(EDATE(BA$3,-12)+1)+1)))*$W15),MAX(0,AZ15-$M15))) | BB15: =IF($K15="","",IF(AND($I15<>"",$I15<=BA$3),0,AZ15-BA15)) | BC15: =IF(OR($K15="",$H15=""),"",MIN(MAX(0,IF($O15="WDV",BB15*$P15*MAX(0,(IF($I15="",BC$3,MIN($I15,BC$3)))-(MAX($H15,(EDATE(BC$3,-12)+1)))+1)/(BC$3-(EDATE(BC$3,-12)+1)+1),IF($N15=0,0,$Q15/$N15*MAX(0,(IF($I15="",BC$3,MIN($I15,BC$3)))-(MAX($H15,(EDATE(BC$3,-12)+1)))+1)/(BC$3-(EDATE(BC$3,-12)+1)+1)))*$W15),MAX(0,BB15-$M15))) | BD15: =IF($K15="","",IF(AND($I15<>"",$I15<=BC$3),0,BB15-BC15)) | BE15: =IF(OR($K15="",$H15=""),"",MIN(MAX(0,IF($O15="WDV",BD15*$P15*MAX(0,(IF($I15="",BE$3,MIN($I15,BE$3)))-(MAX($H15,(EDATE(BE$3,-12)+1)))+1)/(BE$3-(EDATE(BE$3,-12)+1)+1),IF($N15=0,0,$Q15/$N15*MAX(0,(IF($I15="",BE$3,MIN($I15,BE$3)))-(MAX($H15,(EDATE(BE$3,-12)+1)))+1)/(BE$3-(EDATE(BE$3,-12)+1)+1)))*$W15),MAX(0,BD15-$M15))) | BF15: =IF($K15="","",IF(AND($I15<>"",$I15<=BE$3),0,BD15-BE15))
L16: =DefaultResidual | M16: =IF($K16="","",$K16*$L16) | N16: =IF($C16="","",IFERROR(VLOOKUP($C16,ScheduleIITable,3,FALSE),"#N/A")) | O16: =IF($K16="","",GlobalMethod) | P16: =IF(OR($K16="",$N16="",$N16=0,$M16=0),0,1-($M16/$K16)^(1/$N16)) | Q16: =IF($K16="","",$K16-$M16) | R16: =IF($K16="","",INDEX($AA16:$BF16,1,MATCH(ReportingFYEnd,$AA$3:$BF$3,0))) | S16: =IF($K16="","",IF($U16="Disposed",0,$K16-$T16)) | T16: =IF($K16="","",INDEX($AA16:$BF16,1,MATCH(ReportingFYEnd,$AA$3:$BF$3,0)+1)) | U16: =IF($K16="","",IF(AND($I16<>"",$I16<=ReportingFYEnd),"Disposed",IF(OR($H16="",$H16>ReportingFYEnd),"Not Yet in Use","Active"))) | W16: =IF($V16="Double",1.5,IF($V16="Triple",2,1)) | Y16: =IF($K16="","",IF(OR(ISNUMBER(SEARCH("Build",$C16)),ISNUMBER(SEARCH("Lease",$C16))),"Yes","NA")) | AA16: =IF(OR($K16="",$H16=""),"",MIN(MAX(0,IF($O16="WDV",$K16*$P16*MAX(0,(IF($I16="",AA$3,MIN($I16,AA$3)))-(MAX($H16,(EDATE(AA$3,-12)+1)))+1)/(AA$3-(EDATE(AA$3,-12)+1)+1),IF($N16=0,0,$Q16/$N16*MAX(0,(IF($I16="",AA$3,MIN($I16,AA$3)))-(MAX($H16,(EDATE(AA$3,-12)+1)))+1)/(AA$3-(EDATE(AA$3,-12)+1)+1)))*$W16),MAX(0,$K16-$M16))) | AB16: =IF($K16="","",IF(AND($I16<>"",$I16<=AA$3),0,$K16-AA16)) | AC16: =IF(OR($K16="",$H16=""),"",MIN(MAX(0,IF($O16="WDV",AB16*$P16*MAX(0,(IF($I16="",AC$3,MIN($I16,AC$3)))-(MAX($H16,(EDATE(AC$3,-12)+1)))+1)/(AC$3-(EDATE(AC$3,-12)+1)+1),IF($N16=0,0,$Q16/$N16*MAX(0,(IF($I16="",AC$3,MIN($I16,AC$3)))-(MAX($H16,(EDATE(AC$3,-12)+1)))+1)/(AC$3-(EDATE(AC$3,-12)+1)+1)))*$W16),MAX(0,AB16-$M16))) | AD16: =IF($K16="","",IF(AND($I16<>"",$I16<=AC$3),0,AB16-AC16)) | AE16: =IF(OR($K16="",$H16=""),"",MIN(MAX(0,IF($O16="WDV",AD16*$P16*MAX(0,(IF($I16="",AE$3,MIN($I16,AE$3)))-(MAX($H16,(EDATE(AE$3,-12)+1)))+1)/(AE$3-(EDATE(AE$3,-12)+1)+1),IF($N16=0,0,$Q16/$N16*MAX(0,(IF($I16="",AE$3,MIN($I16,AE$3)))-(MAX($H16,(EDATE(AE$3,-12)+1)))+1)/(AE$3-(EDATE(AE$3,-12)+1)+1)))*$W16),MAX(0,AD16-$M16))) | AF16: =IF($K16="","",IF(AND($I16<>"",$I16<=AE$3),0,AD16-AE16)) | AG16: =IF(OR($K16="",$H16=""),"",MIN(MAX(0,IF($O16="WDV",AF16*$P16*MAX(0,(IF($I16="",AG$3,MIN($I16,AG$3)))-(MAX($H16,(EDATE(AG$3,-12)+1)))+1)/(AG$3-(EDATE(AG$3,-12)+1)+1),IF($N16=0,0,$Q16/$N16*MAX(0,(IF($I16="",AG$3,MIN($I16,AG$3)))-(MAX($H16,(EDATE(AG$3,-12)+1)))+1)/(AG$3-(EDATE(AG$3,-12)+1)+1)))*$W16),MAX(0,AF16-$M16))) | AH16: =IF($K16="","",IF(AND($I16<>"",$I16<=AG$3),0,AF16-AG16)) | AI16: =IF(OR($K16="",$H16=""),"",MIN(MAX(0,IF($O16="WDV",AH16*$P16*MAX(0,(IF($I16="",AI$3,MIN($I16,AI$3)))-(MAX($H16,(EDATE(AI$3,-12)+1)))+1)/(AI$3-(EDATE(AI$3,-12)+1)+1),IF($N16=0,0,$Q16/$N16*MAX(0,(IF($I16="",AI$3,MIN($I16,AI$3)))-(MAX($H16,(EDATE(AI$3,-12)+1)))+1)/(AI$3-(EDATE(AI$3,-12)+1)+1)))*$W16),MAX(0,AH16-$M16))) | AJ16: =IF($K16="","",IF(AND($I16<>"",$I16<=AI$3),0,AH16-AI16)) | AK16: =IF(OR($K16="",$H16=""),"",MIN(MAX(0,IF($O16="WDV",AJ16*$P16*MAX(0,(IF($I16="",AK$3,MIN($I16,AK$3)))-(MAX($H16,(EDATE(AK$3,-12)+1)))+1)/(AK$3-(EDATE(AK$3,-12)+1)+1),IF($N16=0,0,$Q16/$N16*MAX(0,(IF($I16="",AK$3,MIN($I16,AK$3)))-(MAX($H16,(EDATE(AK$3,-12)+1)))+1)/(AK$3-(EDATE(AK$3,-12)+1)+1)))*$W16),MAX(0,AJ16-$M16))) | AL16: =IF($K16="","",IF(AND($I16<>"",$I16<=AK$3),0,AJ16-AK16)) | AM16: =IF(OR($K16="",$H16=""),"",MIN(MAX(0,IF($O16="WDV",AL16*$P16*MAX(0,(IF($I16="",AM$3,MIN($I16,AM$3)))-(MAX($H16,(EDATE(AM$3,-12)+1)))+1)/(AM$3-(EDATE(AM$3,-12)+1)+1),IF($N16=0,0,$Q16/$N16*MAX(0,(IF($I16="",AM$3,MIN($I16,AM$3)))-(MAX($H16,(EDATE(AM$3,-12)+1)))+1)/(AM$3-(EDATE(AM$3,-12)+1)+1)))*$W16),MAX(0,AL16-$M16))) | AN16: =IF($K16="","",IF(AND($I16<>"",$I16<=AM$3),0,AL16-AM16)) | AO16: =IF(OR($K16="",$H16=""),"",MIN(MAX(0,IF($O16="WDV",AN16*$P16*MAX(0,(IF($I16="",AO$3,MIN($I16,AO$3)))-(MAX($H16,(EDATE(AO$3,-12)+1)))+1)/(AO$3-(EDATE(AO$3,-12)+1)+1),IF($N16=0,0,$Q16/$N16*MAX(0,(IF($I16="",AO$3,MIN($I16,AO$3)))-(MAX($H16,(EDATE(AO$3,-12)+1)))+1)/(AO$3-(EDATE(AO$3,-12)+1)+1)))*$W16),MAX(0,AN16-$M16))) | AP16: =IF($K16="","",IF(AND($I16<>"",$I16<=AO$3),0,AN16-AO16)) | AQ16: =IF(OR($K16="",$H16=""),"",MIN(MAX(0,IF($O16="WDV",AP16*$P16*MAX(0,(IF($I16="",AQ$3,MIN($I16,AQ$3)))-(MAX($H16,(EDATE(AQ$3,-12)+1)))+1)/(AQ$3-(EDATE(AQ$3,-12)+1)+1),IF($N16=0,0,$Q16/$N16*MAX(0,(IF($I16="",AQ$3,MIN($I16,AQ$3)))-(MAX($H16,(EDATE(AQ$3,-12)+1)))+1)/(AQ$3-(EDATE(AQ$3,-12)+1)+1)))*$W16),MAX(0,AP16-$M16))) | AR16: =IF($K16="","",IF(AND($I16<>"",$I16<=AQ$3),0,AP16-AQ16)) | AS16: =IF(OR($K16="",$H16=""),"",MIN(MAX(0,IF($O16="WDV",AR16*$P16*MAX(0,(IF($I16="",AS$3,MIN($I16,AS$3)))-(MAX($H16,(EDATE(AS$3,-12)+1)))+1)/(AS$3-(EDATE(AS$3,-12)+1)+1),IF($N16=0,0,$Q16/$N16*MAX(0,(IF($I16="",AS$3,MIN($I16,AS$3)))-(MAX($H16,(EDATE(AS$3,-12)+1)))+1)/(AS$3-(EDATE(AS$3,-12)+1)+1)))*$W16),MAX(0,AR16-$M16))) | AT16: =IF($K16="","",IF(AND($I16<>"",$I16<=AS$3),0,AR16-AS16)) | AU16: =IF(OR($K16="",$H16=""),"",MIN(MAX(0,IF($O16="WDV",AT16*$P16*MAX(0,(IF($I16="",AU$3,MIN($I16,AU$3)))-(MAX($H16,(EDATE(AU$3,-12)+1)))+1)/(AU$3-(EDATE(AU$3,-12)+1)+1),IF($N16=0,0,$Q16/$N16*MAX(0,(IF($I16="",AU$3,MIN($I16,AU$3)))-(MAX($H16,(EDATE(AU$3,-12)+1)))+1)/(AU$3-(EDATE(AU$3,-12)+1)+1)))*$W16),MAX(0,AT16-$M16))) | AV16: =IF($K16="","",IF(AND($I16<>"",$I16<=AU$3),0,AT16-AU16)) | AW16: =IF(OR($K16="",$H16=""),"",MIN(MAX(0,IF($O16="WDV",AV16*$P16*MAX(0,(IF($I16="",AW$3,MIN($I16,AW$3)))-(MAX($H16,(EDATE(AW$3,-12)+1)))+1)/(AW$3-(EDATE(AW$3,-12)+1)+1),IF($N16=0,0,$Q16/$N16*MAX(0,(IF($I16="",AW$3,MIN($I16,AW$3)))-(MAX($H16,(EDATE(AW$3,-12)+1)))+1)/(AW$3-(EDATE(AW$3,-12)+1)+1)))*$W16),MAX(0,AV16-$M16))) | AX16: =IF($K16="","",IF(AND($I16<>"",$I16<=AW$3),0,AV16-AW16)) | AY16: =IF(OR($K16="",$H16=""),"",MIN(MAX(0,IF($O16="WDV",AX16*$P16*MAX(0,(IF($I16="",AY$3,MIN($I16,AY$3)))-(MAX($H16,(EDATE(AY$3,-12)+1)))+1)/(AY$3-(EDATE(AY$3,-12)+1)+1),IF($N16=0,0,$Q16/$N16*MAX(0,(IF($I16="",AY$3,MIN($I16,AY$3)))-(MAX($H16,(EDATE(AY$3,-12)+1)))+1)/(AY$3-(EDATE(AY$3,-12)+1)+1)))*$W16),MAX(0,AX16-$M16))) | AZ16: =IF($K16="","",IF(AND($I16<>"",$I16<=AY$3),0,AX16-AY16)) | BA16: =IF(OR($K16="",$H16=""),"",MIN(MAX(0,IF($O16="WDV",AZ16*$P16*MAX(0,(IF($I16="",BA$3,MIN($I16,BA$3)))-(MAX($H16,(EDATE(BA$3,-12)+1)))+1)/(BA$3-(EDATE(BA$3,-12)+1)+1),IF($N16=0,0,$Q16/$N16*MAX(0,(IF($I16="",BA$3,MIN($I16,BA$3)))-(MAX($H16,(EDATE(BA$3,-12)+1)))+1)/(BA$3-(EDATE(BA$3,-12)+1)+1)))*$W16),MAX(0,AZ16-$M16))) | BB16: =IF($K16="","",IF(AND($I16<>"",$I16<=BA$3),0,AZ16-BA16)) | BC16: =IF(OR($K16="",$H16=""),"",MIN(MAX(0,IF($O16="WDV",BB16*$P16*MAX(0,(IF($I16="",BC$3,MIN($I16,BC$3)))-(MAX($H16,(EDATE(BC$3,-12)+1)))+1)/(BC$3-(EDATE(BC$3,-12)+1)+1),IF($N16=0,0,$Q16/$N16*MAX(0,(IF($I16="",BC$3,MIN($I16,BC$3)))-(MAX($H16,(EDATE(BC$3,-12)+1)))+1)/(BC$3-(EDATE(BC$3,-12)+1)+1)))*$W16),MAX(0,BB16-$M16))) | BD16: =IF($K16="","",IF(AND($I16<>"",$I16<=BC$3),0,BB16-BC16)) | BE16: =IF(OR($K16="",$H16=""),"",MIN(MAX(0,IF($O16="WDV",BD16*$P16*MAX(0,(IF($I16="",BE$3,MIN($I16,BE$3)))-(MAX($H16,(EDATE(BE$3,-12)+1)))+1)/(BE$3-(EDATE(BE$3,-12)+1)+1),IF($N16=0,0,$Q16/$N16*MAX(0,(IF($I16="",BE$3,MIN($I16,BE$3)))-(MAX($H16,(EDATE(BE$3,-12)+1)))+1)/(BE$3-(EDATE(BE$3,-12)+1)+1)))*$W16),MAX(0,BD16-$M16))) | BF16: =IF($K16="","",IF(AND($I16<>"",$I16<=BE$3),0,BD16-BE16))
L17: =DefaultResidual | M17: =IF($K17="","",$K17*$L17) | N17: =IF($C17="","",IFERROR(VLOOKUP($C17,ScheduleIITable,3,FALSE),"#N/A")) | O17: =IF($K17="","",GlobalMethod) | P17: =IF(OR($K17="",$N17="",$N17=0,$M17=0),0,1-($M17/$K17)^(1/$N17)) | Q17: =IF($K17="","",$K17-$M17) | R17: =IF($K17="","",INDEX($AA17:$BF17,1,MATCH(ReportingFYEnd,$AA$3:$BF$3,0))) | S17: =IF($K17="","",IF($U17="Disposed",0,$K17-$T17)) | T17: =IF($K17="","",INDEX($AA17:$BF17,1,MATCH(ReportingFYEnd,$AA$3:$BF$3,0)+1)) | U17: =IF($K17="","",IF(AND($I17<>"",$I17<=ReportingFYEnd),"Disposed",IF(OR($H17="",$H17>ReportingFYEnd),"Not Yet in Use","Active"))) | W17: =IF($V17="Double",1.5,IF($V17="Triple",2,1)) | Y17: =IF($K17="","",IF(OR(ISNUMBER(SEARCH("Build",$C17)),ISNUMBER(SEARCH("Lease",$C17))),"Yes","NA")) | AA17: =IF(OR($K17="",$H17=""),"",MIN(MAX(0,IF($O17="WDV",$K17*$P17*MAX(0,(IF($I17="",AA$3,MIN($I17,AA$3)))-(MAX($H17,(EDATE(AA$3,-12)+1)))+1)/(AA$3-(EDATE(AA$3,-12)+1)+1),IF($N17=0,0,$Q17/$N17*MAX(0,(IF($I17="",AA$3,MIN($I17,AA$3)))-(MAX($H17,(EDATE(AA$3,-12)+1)))+1)/(AA$3-(EDATE(AA$3,-12)+1)+1)))*$W17),MAX(0,$K17-$M17))) | AB17: =IF($K17="","",IF(AND($I17<>"",$I17<=AA$3),0,$K17-AA17)) | AC17: =IF(OR($K17="",$H17=""),"",MIN(MAX(0,IF($O17="WDV",AB17*$P17*MAX(0,(IF($I17="",AC$3,MIN($I17,AC$3)))-(MAX($H17,(EDATE(AC$3,-12)+1)))+1)/(AC$3-(EDATE(AC$3,-12)+1)+1),IF($N17=0,0,$Q17/$N17*MAX(0,(IF($I17="",AC$3,MIN($I17,AC$3)))-(MAX($H17,(EDATE(AC$3,-12)+1)))+1)/(AC$3-(EDATE(AC$3,-12)+1)+1)))*$W17),MAX(0,AB17-$M17))) | AD17: =IF($K17="","",IF(AND($I17<>"",$I17<=AC$3),0,AB17-AC17)) | AE17: =IF(OR($K17="",$H17=""),"",MIN(MAX(0,IF($O17="WDV",AD17*$P17*MAX(0,(IF($I17="",AE$3,MIN($I17,AE$3)))-(MAX($H17,(EDATE(AE$3,-12)+1)))+1)/(AE$3-(EDATE(AE$3,-12)+1)+1),IF($N17=0,0,$Q17/$N17*MAX(0,(IF($I17="",AE$3,MIN($I17,AE$3)))-(MAX($H17,(EDATE(AE$3,-12)+1)))+1)/(AE$3-(EDATE(AE$3,-12)+1)+1)))*$W17),MAX(0,AD17-$M17))) | AF17: =IF($K17="","",IF(AND($I17<>"",$I17<=AE$3),0,AD17-AE17)) | AG17: =IF(OR($K17="",$H17=""),"",MIN(MAX(0,IF($O17="WDV",AF17*$P17*MAX(0,(IF($I17="",AG$3,MIN($I17,AG$3)))-(MAX($H17,(EDATE(AG$3,-12)+1)))+1)/(AG$3-(EDATE(AG$3,-12)+1)+1),IF($N17=0,0,$Q17/$N17*MAX(0,(IF($I17="",AG$3,MIN($I17,AG$3)))-(MAX($H17,(EDATE(AG$3,-12)+1)))+1)/(AG$3-(EDATE(AG$3,-12)+1)+1)))*$W17),MAX(0,AF17-$M17))) | AH17: =IF($K17="","",IF(AND($I17<>"",$I17<=AG$3),0,AF17-AG17)) | AI17: =IF(OR($K17="",$H17=""),"",MIN(MAX(0,IF($O17="WDV",AH17*$P17*MAX(0,(IF($I17="",AI$3,MIN($I17,AI$3)))-(MAX($H17,(EDATE(AI$3,-12)+1)))+1)/(AI$3-(EDATE(AI$3,-12)+1)+1),IF($N17=0,0,$Q17/$N17*MAX(0,(IF($I17="",AI$3,MIN($I17,AI$3)))-(MAX($H17,(EDATE(AI$3,-12)+1)))+1)/(AI$3-(EDATE(AI$3,-12)+1)+1)))*$W17),MAX(0,AH17-$M17))) | AJ17: =IF($K17="","",IF(AND($I17<>"",$I17<=AI$3),0,AH17-AI17)) | AK17: =IF(OR($K17="",$H17=""),"",MIN(MAX(0,IF($O17="WDV",AJ17*$P17*MAX(0,(IF($I17="",AK$3,MIN($I17,AK$3)))-(MAX($H17,(EDATE(AK$3,-12)+1)))+1)/(AK$3-(EDATE(AK$3,-12)+1)+1),IF($N17=0,0,$Q17/$N17*MAX(0,(IF($I17="",AK$3,MIN($I17,AK$3)))-(MAX($H17,(EDATE(AK$3,-12)+1)))+1)/(AK$3-(EDATE(AK$3,-12)+1)+1)))*$W17),MAX(0,AJ17-$M17))) | AL17: =IF($K17="","",IF(AND($I17<>"",$I17<=AK$3),0,AJ17-AK17)) | AM17: =IF(OR($K17="",$H17=""),"",MIN(MAX(0,IF($O17="WDV",AL17*$P17*MAX(0,(IF($I17="",AM$3,MIN($I17,AM$3)))-(MAX($H17,(EDATE(AM$3,-12)+1)))+1)/(AM$3-(EDATE(AM$3,-12)+1)+1),IF($N17=0,0,$Q17/$N17*MAX(0,(IF($I17="",AM$3,MIN($I17,AM$3)))-(MAX($H17,(EDATE(AM$3,-12)+1)))+1)/(AM$3-(EDATE(AM$3,-12)+1)+1)))*$W17),MAX(0,AL17-$M17))) | AN17: =IF($K17="","",IF(AND($I17<>"",$I17<=AM$3),0,AL17-AM17)) | AO17: =IF(OR($K17="",$H17=""),"",MIN(MAX(0,IF($O17="WDV",AN17*$P17*MAX(0,(IF($I17="",AO$3,MIN($I17,AO$3)))-(MAX($H17,(EDATE(AO$3,-12)+1)))+1)/(AO$3-(EDATE(AO$3,-12)+1)+1),IF($N17=0,0,$Q17/$N17*MAX(0,(IF($I17="",AO$3,MIN($I17,AO$3)))-(MAX($H17,(EDATE(AO$3,-12)+1)))+1)/(AO$3-(EDATE(AO$3,-12)+1)+1)))*$W17),MAX(0,AN17-$M17))) | AP17: =IF($K17="","",IF(AND($I17<>"",$I17<=AO$3),0,AN17-AO17)) | AQ17: =IF(OR($K17="",$H17=""),"",MIN(MAX(0,IF($O17="WDV",AP17*$P17*MAX(0,(IF($I17="",AQ$3,MIN($I17,AQ$3)))-(MAX($H17,(EDATE(AQ$3,-12)+1)))+1)/(AQ$3-(EDATE(AQ$3,-12)+1)+1),IF($N17=0,0,$Q17/$N17*MAX(0,(IF($I17="",AQ$3,MIN($I17,AQ$3)))-(MAX($H17,(EDATE(AQ$3,-12)+1)))+1)/(AQ$3-(EDATE(AQ$3,-12)+1)+1)))*$W17),MAX(0,AP17-$M17))) | AR17: =IF($K17="","",IF(AND($I17<>"",$I17<=AQ$3),0,AP17-AQ17)) | AS17: =IF(OR($K17="",$H17=""),"",MIN(MAX(0,IF($O17="WDV",AR17*$P17*MAX(0,(IF($I17="",AS$3,MIN($I17,AS$3)))-(MAX($H17,(EDATE(AS$3,-12)+1)))+1)/(AS$3-(EDATE(AS$3,-12)+1)+1),IF($N17=0,0,$Q17/$N17*MAX(0,(IF($I17="",AS$3,MIN($I17,AS$3)))-(MAX($H17,(EDATE(AS$3,-12)+1)))+1)/(AS$3-(EDATE(AS$3,-12)+1)+1)))*$W17),MAX(0,AR17-$M17))) | AT17: =IF($K17="","",IF(AND($I17<>"",$I17<=AS$3),0,AR17-AS17)) | AU17: =IF(OR($K17="",$H17=""),"",MIN(MAX(0,IF($O17="WDV",AT17*$P17*MAX(0,(IF($I17="",AU$3,MIN($I17,AU$3)))-(MAX($H17,(EDATE(AU$3,-12)+1)))+1)/(AU$3-(EDATE(AU$3,-12)+1)+1),IF($N17=0,0,$Q17/$N17*MAX(0,(IF($I17="",AU$3,MIN($I17,AU$3)))-(MAX($H17,(EDATE(AU$3,-12)+1)))+1)/(AU$3-(EDATE(AU$3,-12)+1)+1)))*$W17),MAX(0,AT17-$M17))) | AV17: =IF($K17="","",IF(AND($I17<>"",$I17<=AU$3),0,AT17-AU17)) | AW17: =IF(OR($K17="",$H17=""),"",MIN(MAX(0,IF($O17="WDV",AV17*$P17*MAX(0,(IF($I17="",AW$3,MIN($I17,AW$3)))-(MAX($H17,(EDATE(AW$3,-12)+1)))+1)/(AW$3-(EDATE(AW$3,-12)+1)+1),IF($N17=0,0,$Q17/$N17*MAX(0,(IF($I17="",AW$3,MIN($I17,AW$3)))-(MAX($H17,(EDATE(AW$3,-12)+1)))+1)/(AW$3-(EDATE(AW$3,-12)+1)+1)))*$W17),MAX(0,AV17-$M17))) | AX17: =IF($K17="","",IF(AND($I17<>"",$I17<=AW$3),0,AV17-AW17)) | AY17: =IF(OR($K17="",$H17=""),"",MIN(MAX(0,IF($O17="WDV",AX17*$P17*MAX(0,(IF($I17="",AY$3,MIN($I17,AY$3)))-(MAX($H17,(EDATE(AY$3,-12)+1)))+1)/(AY$3-(EDATE(AY$3,-12)+1)+1),IF($N17=0,0,$Q17/$N17*MAX(0,(IF($I17="",AY$3,MIN($I17,AY$3)))-(MAX($H17,(EDATE(AY$3,-12)+1)))+1)/(AY$3-(EDATE(AY$3,-12)+1)+1)))*$W17),MAX(0,AX17-$M17))) | AZ17: =IF($K17="","",IF(AND($I17<>"",$I17<=AY$3),0,AX17-AY17)) | BA17: =IF(OR($K17="",$H17=""),"",MIN(MAX(0,IF($O17="WDV",AZ17*$P17*MAX(0,(IF($I17="",BA$3,MIN($I17,BA$3)))-(MAX($H17,(EDATE(BA$3,-12)+1)))+1)/(BA$3-(EDATE(BA$3,-12)+1)+1),IF($N17=0,0,$Q17/$N17*MAX(0,(IF($I17="",BA$3,MIN($I17,BA$3)))-(MAX($H17,(EDATE(BA$3,-12)+1)))+1)/(BA$3-(EDATE(BA$3,-12)+1)+1)))*$W17),MAX(0,AZ17-$M17))) | BB17: =IF($K17="","",IF(AND($I17<>"",$I17<=BA$3),0,AZ17-BA17)) | BC17: =IF(OR($K17="",$H17=""),"",MIN(MAX(0,IF($O17="WDV",BB17*$P17*MAX(0,(IF($I17="",BC$3,MIN($I17,BC$3)))-(MAX($H17,(EDATE(BC$3,-12)+1)))+1)/(BC$3-(EDATE(BC$3,-12)+1)+1),IF($N17=0,0,$Q17/$N17*MAX(0,(IF($I17="",BC$3,MIN($I17,BC$3)))-(MAX($H17,(EDATE(BC$3,-12)+1)))+1)/(BC$3-(EDATE(BC$3,-12)+1)+1)))*$W17),MAX(0,BB17-$M17))) | BD17: =IF($K17="","",IF(AND($I17<>"",$I17<=BC$3),0,BB17-BC17)) | BE17: =IF(OR($K17="",$H17=""),"",MIN(MAX(0,IF($O17="WDV",BD17*$P17*MAX(0,(IF($I17="",BE$3,MIN($I17,BE$3)))-(MAX($H17,(EDATE(BE$3,-12)+1)))+1)/(BE$3-(EDATE(BE$3,-12)+1)+1),IF($N17=0,0,$Q17/$N17*MAX(0,(IF($I17="",BE$3,MIN($I17,BE$3)))-(MAX($H17,(EDATE(BE$3,-12)+1)))+1)/(BE$3-(EDATE(BE$3,-12)+1)+1)))*$W17),MAX(0,BD17-$M17))) | BF17: =IF($K17="","",IF(AND($I17<>"",$I17<=BE$3),0,BD17-BE17))
L18: =DefaultResidual | M18: =IF($K18="","",$K18*$L18) | N18: =IF($C18="","",IFERROR(VLOOKUP($C18,ScheduleIITable,3,FALSE),"#N/A")) | O18: =IF($K18="","",GlobalMethod) | P18: =IF(OR($K18="",$N18="",$N18=0,$M18=0),0,1-($M18/$K18)^(1/$N18)) | Q18: =IF($K18="","",$K18-$M18) | R18: =IF($K18="","",INDEX($AA18:$BF18,1,MATCH(ReportingFYEnd,$AA$3:$BF$3,0))) | S18: =IF($K18="","",IF($U18="Disposed",0,$K18-$T18)) | T18: =IF($K18="","",INDEX($AA18:$BF18,1,MATCH(ReportingFYEnd,$AA$3:$BF$3,0)+1)) | U18: =IF($K18="","",IF(AND($I18<>"",$I18<=ReportingFYEnd),"Disposed",IF(OR($H18="",$H18>ReportingFYEnd),"Not Yet in Use","Active"))) | W18: =IF($V18="Double",1.5,IF($V18="Triple",2,1)) | Y18: =IF($K18="","",IF(OR(ISNUMBER(SEARCH("Build",$C18)),ISNUMBER(SEARCH("Lease",$C18))),"Yes","NA")) | AA18: =IF(OR($K18="",$H18=""),"",MIN(MAX(0,IF($O18="WDV",$K18*$P18*MAX(0,(IF($I18="",AA$3,MIN($I18,AA$3)))-(MAX($H18,(EDATE(AA$3,-12)+1)))+1)/(AA$3-(EDATE(AA$3,-12)+1)+1),IF($N18=0,0,$Q18/$N18*MAX(0,(IF($I18="",AA$3,MIN($I18,AA$3)))-(MAX($H18,(EDATE(AA$3,-12)+1)))+1)/(AA$3-(EDATE(AA$3,-12)+1)+1)))*$W18),MAX(0,$K18-$M18))) | AB18: =IF($K18="","",IF(AND($I18<>"",$I18<=AA$3),0,$K18-AA18)) | AC18: =IF(OR($K18="",$H18=""),"",MIN(MAX(0,IF($O18="WDV",AB18*$P18*MAX(0,(IF($I18="",AC$3,MIN($I18,AC$3)))-(MAX($H18,(EDATE(AC$3,-12)+1)))+1)/(AC$3-(EDATE(AC$3,-12)+1)+1),IF($N18=0,0,$Q18/$N18*MAX(0,(IF($I18="",AC$3,MIN($I18,AC$3)))-(MAX($H18,(EDATE(AC$3,-12)+1)))+1)/(AC$3-(EDATE(AC$3,-12)+1)+1)))*$W18),MAX(0,AB18-$M18))) | AD18: =IF($K18="","",IF(AND($I18<>"",$I18<=AC$3),0,AB18-AC18)) | AE18: =IF(OR($K18="",$H18=""),"",MIN(MAX(0,IF($O18="WDV",AD18*$P18*MAX(0,(IF($I18="",AE$3,MIN($I18,AE$3)))-(MAX($H18,(EDATE(AE$3,-12)+1)))+1)/(AE$3-(EDATE(AE$3,-12)+1)+1),IF($N18=0,0,$Q18/$N18*MAX(0,(IF($I18="",AE$3,MIN($I18,AE$3)))-(MAX($H18,(EDATE(AE$3,-12)+1)))+1)/(AE$3-(EDATE(AE$3,-12)+1)+1)))*$W18),MAX(0,AD18-$M18))) | AF18: =IF($K18="","",IF(AND($I18<>"",$I18<=AE$3),0,AD18-AE18)) | AG18: =IF(OR($K18="",$H18=""),"",MIN(MAX(0,IF($O18="WDV",AF18*$P18*MAX(0,(IF($I18="",AG$3,MIN($I18,AG$3)))-(MAX($H18,(EDATE(AG$3,-12)+1)))+1)/(AG$3-(EDATE(AG$3,-12)+1)+1),IF($N18=0,0,$Q18/$N18*MAX(0,(IF($I18="",AG$3,MIN($I18,AG$3)))-(MAX($H18,(EDATE(AG$3,-12)+1)))+1)/(AG$3-(EDATE(AG$3,-12)+1)+1)))*$W18),MAX(0,AF18-$M18))) | AH18: =IF($K18="","",IF(AND($I18<>"",$I18<=AG$3),0,AF18-AG18)) | AI18: =IF(OR($K18="",$H18=""),"",MIN(MAX(0,IF($O18="WDV",AH18*$P18*MAX(0,(IF($I18="",AI$3,MIN($I18,AI$3)))-(MAX($H18,(EDATE(AI$3,-12)+1)))+1)/(AI$3-(EDATE(AI$3,-12)+1)+1),IF($N18=0,0,$Q18/$N18*MAX(0,(IF($I18="",AI$3,MIN($I18,AI$3)))-(MAX($H18,(EDATE(AI$3,-12)+1)))+1)/(AI$3-(EDATE(AI$3,-12)+1)+1)))*$W18),MAX(0,AH18-$M18))) | AJ18: =IF($K18="","",IF(AND($I18<>"",$I18<=AI$3),0,AH18-AI18)) | AK18: =IF(OR($K18="",$H18=""),"",MIN(MAX(0,IF($O18="WDV",AJ18*$P18*MAX(0,(IF($I18="",AK$3,MIN($I18,AK$3)))-(MAX($H18,(EDATE(AK$3,-12)+1)))+1)/(AK$3-(EDATE(AK$3,-12)+1)+1),IF($N18=0,0,$Q18/$N18*MAX(0,(IF($I18="",AK$3,MIN($I18,AK$3)))-(MAX($H18,(EDATE(AK$3,-12)+1)))+1)/(AK$3-(EDATE(AK$3,-12)+1)+1)))*$W18),MAX(0,AJ18-$M18))) | AL18: =IF($K18="","",IF(AND($I18<>"",$I18<=AK$3),0,AJ18-AK18)) | AM18: =IF(OR($K18="",$H18=""),"",MIN(MAX(0,IF($O18="WDV",AL18*$P18*MAX(0,(IF($I18="",AM$3,MIN($I18,AM$3)))-(MAX($H18,(EDATE(AM$3,-12)+1)))+1)/(AM$3-(EDATE(AM$3,-12)+1)+1),IF($N18=0,0,$Q18/$N18*MAX(0,(IF($I18="",AM$3,MIN($I18,AM$3)))-(MAX($H18,(EDATE(AM$3,-12)+1)))+1)/(AM$3-(EDATE(AM$3,-12)+1)+1)))*$W18),MAX(0,AL18-$M18))) | AN18: =IF($K18="","",IF(AND($I18<>"",$I18<=AM$3),0,AL18-AM18)) | AO18: =IF(OR($K18="",$H18=""),"",MIN(MAX(0,IF($O18="WDV",AN18*$P18*MAX(0,(IF($I18="",AO$3,MIN($I18,AO$3)))-(MAX($H18,(EDATE(AO$3,-12)+1)))+1)/(AO$3-(EDATE(AO$3,-12)+1)+1),IF($N18=0,0,$Q18/$N18*MAX(0,(IF($I18="",AO$3,MIN($I18,AO$3)))-(MAX($H18,(EDATE(AO$3,-12)+1)))+1)/(AO$3-(EDATE(AO$3,-12)+1)+1)))*$W18),MAX(0,AN18-$M18))) | AP18: =IF($K18="","",IF(AND($I18<>"",$I18<=AO$3),0,AN18-AO18)) | AQ18: =IF(OR($K18="",$H18=""),"",MIN(MAX(0,IF($O18="WDV",AP18*$P18*MAX(0,(IF($I18="",AQ$3,MIN($I18,AQ$3)))-(MAX($H18,(EDATE(AQ$3,-12)+1)))+1)/(AQ$3-(EDATE(AQ$3,-12)+1)+1),IF($N18=0,0,$Q18/$N18*MAX(0,(IF($I18="",AQ$3,MIN($I18,AQ$3)))-(MAX($H18,(EDATE(AQ$3,-12)+1)))+1)/(AQ$3-(EDATE(AQ$3,-12)+1)+1)))*$W18),MAX(0,AP18-$M18))) | AR18: =IF($K18="","",IF(AND($I18<>"",$I18<=AQ$3),0,AP18-AQ18)) | AS18: =IF(OR($K18="",$H18=""),"",MIN(MAX(0,IF($O18="WDV",AR18*$P18*MAX(0,(IF($I18="",AS$3,MIN($I18,AS$3)))-(MAX($H18,(EDATE(AS$3,-12)+1)))+1)/(AS$3-(EDATE(AS$3,-12)+1)+1),IF($N18=0,0,$Q18/$N18*MAX(0,(IF($I18="",AS$3,MIN($I18,AS$3)))-(MAX($H18,(EDATE(AS$3,-12)+1)))+1)/(AS$3-(EDATE(AS$3,-12)+1)+1)))*$W18),MAX(0,AR18-$M18))) | AT18: =IF($K18="","",IF(AND($I18<>"",$I18<=AS$3),0,AR18-AS18)) | AU18: =IF(OR($K18="",$H18=""),"",MIN(MAX(0,IF($O18="WDV",AT18*$P18*MAX(0,(IF($I18="",AU$3,MIN($I18,AU$3)))-(MAX($H18,(EDATE(AU$3,-12)+1)))+1)/(AU$3-(EDATE(AU$3,-12)+1)+1),IF($N18=0,0,$Q18/$N18*MAX(0,(IF($I18="",AU$3,MIN($I18,AU$3)))-(MAX($H18,(EDATE(AU$3,-12)+1)))+1)/(AU$3-(EDATE(AU$3,-12)+1)+1)))*$W18),MAX(0,AT18-$M18))) | AV18: =IF($K18="","",IF(AND($I18<>"",$I18<=AU$3),0,AT18-AU18)) | AW18: =IF(OR($K18="",$H18=""),"",MIN(MAX(0,IF($O18="WDV",AV18*$P18*MAX(0,(IF($I18="",AW$3,MIN($I18,AW$3)))-(MAX($H18,(EDATE(AW$3,-12)+1)))+1)/(AW$3-(EDATE(AW$3,-12)+1)+1),IF($N18=0,0,$Q18/$N18*MAX(0,(IF($I18="",AW$3,MIN($I18,AW$3)))-(MAX($H18,(EDATE(AW$3,-12)+1)))+1)/(AW$3-(EDATE(AW$3,-12)+1)+1)))*$W18),MAX(0,AV18-$M18))) | AX18: =IF($K18="","",IF(AND($I18<>"",$I18<=AW$3),0,AV18-AW18)) | AY18: =IF(OR($K18="",$H18=""),"",MIN(MAX(0,IF($O18="WDV",AX18*$P18*MAX(0,(IF($I18="",AY$3,MIN($I18,AY$3)))-(MAX($H18,(EDATE(AY$3,-12)+1)))+1)/(AY$3-(EDATE(AY$3,-12)+1)+1),IF($N18=0,0,$Q18/$N18*MAX(0,(IF($I18="",AY$3,MIN($I18,AY$3)))-(MAX($H18,(EDATE(AY$3,-12)+1)))+1)/(AY$3-(EDATE(AY$3,-12)+1)+1)))*$W18),MAX(0,AX18-$M18))) | AZ18: =IF($K18="","",IF(AND($I18<>"",$I18<=AY$3),0,AX18-AY18)) | BA18: =IF(OR($K18="",$H18=""),"",MIN(MAX(0,IF($O18="WDV",AZ18*$P18*MAX(0,(IF($I18="",BA$3,MIN($I18,BA$3)))-(MAX($H18,(EDATE(BA$3,-12)+1)))+1)/(BA$3-(EDATE(BA$3,-12)+1)+1),IF($N18=0,0,$Q18/$N18*MAX(0,(IF($I18="",BA$3,MIN($I18,BA$3)))-(MAX($H18,(EDATE(BA$3,-12)+1)))+1)/(BA$3-(EDATE(BA$3,-12)+1)+1)))*$W18),MAX(0,AZ18-$M18))) | BB18: =IF($K18="","",IF(AND($I18<>"",$I18<=BA$3),0,AZ18-BA18)) | BC18: =IF(OR($K18="",$H18=""),"",MIN(MAX(0,IF($O18="WDV",BB18*$P18*MAX(0,(IF($I18="",BC$3,MIN($I18,BC$3)))-(MAX($H18,(EDATE(BC$3,-12)+1)))+1)/(BC$3-(EDATE(BC$3,-12)+1)+1),IF($N18=0,0,$Q18/$N18*MAX(0,(IF($I18="",BC$3,MIN($I18,BC$3)))-(MAX($H18,(EDATE(BC$3,-12)+1)))+1)/(BC$3-(EDATE(BC$3,-12)+1)+1)))*$W18),MAX(0,BB18-$M18))) | BD18: =IF($K18="","",IF(AND($I18<>"",$I18<=BC$3),0,BB18-BC18)) | BE18: =IF(OR($K18="",$H18=""),"",MIN(MAX(0,IF($O18="WDV",BD18*$P18*MAX(0,(IF($I18="",BE$3,MIN($I18,BE$3)))-(MAX($H18,(EDATE(BE$3,-12)+1)))+1)/(BE$3-(EDATE(BE$3,-12)+1)+1),IF($N18=0,0,$Q18/$N18*MAX(0,(IF($I18="",BE$3,MIN($I18,BE$3)))-(MAX($H18,(EDATE(BE$3,-12)+1)))+1)/(BE$3-(EDATE(BE$3,-12)+1)+1)))*$W18),MAX(0,BD18-$M18))) | BF18: =IF($K18="","",IF(AND($I18<>"",$I18<=BE$3),0,BD18-BE18))
L19: =DefaultResidual | M19: =IF($K19="","",$K19*$L19) | N19: =IF($C19="","",IFERROR(VLOOKUP($C19,ScheduleIITable,3,FALSE),"#N/A")) | O19: =IF($K19="","",GlobalMethod) | P19: =IF(OR($K19="",$N19="",$N19=0,$M19=0),0,1-($M19/$K19)^(1/$N19)) | Q19: =IF($K19="","",$K19-$M19) | R19: =IF($K19="","",INDEX($AA19:$BF19,1,MATCH(ReportingFYEnd,$AA$3:$BF$3,0))) | S19: =IF($K19="","",IF($U19="Disposed",0,$K19-$T19)) | T19: =IF($K19="","",INDEX($AA19:$BF19,1,MATCH(ReportingFYEnd,$AA$3:$BF$3,0)+1)) | U19: =IF($K19="","",IF(AND($I19<>"",$I19<=ReportingFYEnd),"Disposed",IF(OR($H19="",$H19>ReportingFYEnd),"Not Yet in Use","Active"))) | W19: =IF($V19="Double",1.5,IF($V19="Triple",2,1)) | Y19: =IF($K19="","",IF(OR(ISNUMBER(SEARCH("Build",$C19)),ISNUMBER(SEARCH("Lease",$C19))),"Yes","NA")) | AA19: =IF(OR($K19="",$H19=""),"",MIN(MAX(0,IF($O19="WDV",$K19*$P19*MAX(0,(IF($I19="",AA$3,MIN($I19,AA$3)))-(MAX($H19,(EDATE(AA$3,-12)+1)))+1)/(AA$3-(EDATE(AA$3,-12)+1)+1),IF($N19=0,0,$Q19/$N19*MAX(0,(IF($I19="",AA$3,MIN($I19,AA$3)))-(MAX($H19,(EDATE(AA$3,-12)+1)))+1)/(AA$3-(EDATE(AA$3,-12)+1)+1)))*$W19),MAX(0,$K19-$M19))) | AB19: =IF($K19="","",IF(AND($I19<>"",$I19<=AA$3),0,$K19-AA19)) | AC19: =IF(OR($K19="",$H19=""),"",MIN(MAX(0,IF($O19="WDV",AB19*$P19*MAX(0,(IF($I19="",AC$3,MIN($I19,AC$3)))-(MAX($H19,(EDATE(AC$3,-12)+1)))+1)/(AC$3-(EDATE(AC$3,-12)+1)+1),IF($N19=0,0,$Q19/$N19*MAX(0,(IF($I19="",AC$3,MIN($I19,AC$3)))-(MAX($H19,(EDATE(AC$3,-12)+1)))+1)/(AC$3-(EDATE(AC$3,-12)+1)+1)))*$W19),MAX(0,AB19-$M19))) | AD19: =IF($K19="","",IF(AND($I19<>"",$I19<=AC$3),0,AB19-AC19)) | AE19: =IF(OR($K19="",$H19=""),"",MIN(MAX(0,IF($O19="WDV",AD19*$P19*MAX(0,(IF($I19="",AE$3,MIN($I19,AE$3)))-(MAX($H19,(EDATE(AE$3,-12)+1)))+1)/(AE$3-(EDATE(AE$3,-12)+1)+1),IF($N19=0,0,$Q19/$N19*MAX(0,(IF($I19="",AE$3,MIN($I19,AE$3)))-(MAX($H19,(EDATE(AE$3,-12)+1)))+1)/(AE$3-(EDATE(AE$3,-12)+1)+1)))*$W19),MAX(0,AD19-$M19))) | AF19: =IF($K19="","",IF(AND($I19<>"",$I19<=AE$3),0,AD19-AE19)) | AG19: =IF(OR($K19="",$H19=""),"",MIN(MAX(0,IF($O19="WDV",AF19*$P19*MAX(0,(IF($I19="",AG$3,MIN($I19,AG$3)))-(MAX($H19,(EDATE(AG$3,-12)+1)))+1)/(AG$3-(EDATE(AG$3,-12)+1)+1),IF($N19=0,0,$Q19/$N19*MAX(0,(IF($I19="",AG$3,MIN($I19,AG$3)))-(MAX($H19,(EDATE(AG$3,-12)+1)))+1)/(AG$3-(EDATE(AG$3,-12)+1)+1)))*$W19),MAX(0,AF19-$M19))) | AH19: =IF($K19="","",IF(AND($I19<>"",$I19<=AG$3),0,AF19-AG19)) | AI19: =IF(OR($K19="",$H19=""),"",MIN(MAX(0,IF($O19="WDV",AH19*$P19*MAX(0,(IF($I19="",AI$3,MIN($I19,AI$3)))-(MAX($H19,(EDATE(AI$3,-12)+1)))+1)/(AI$3-(EDATE(AI$3,-12)+1)+1),IF($N19=0,0,$Q19/$N19*MAX(0,(IF($I19="",AI$3,MIN($I19,AI$3)))-(MAX($H19,(EDATE(AI$3,-12)+1)))+1)/(AI$3-(EDATE(AI$3,-12)+1)+1)))*$W19),MAX(0,AH19-$M19))) | AJ19: =IF($K19="","",IF(AND($I19<>"",$I19<=AI$3),0,AH19-AI19)) | AK19: =IF(OR($K19="",$H19=""),"",MIN(MAX(0,IF($O19="WDV",AJ19*$P19*MAX(0,(IF($I19="",AK$3,MIN($I19,AK$3)))-(MAX($H19,(EDATE(AK$3,-12)+1)))+1)/(AK$3-(EDATE(AK$3,-12)+1)+1),IF($N19=0,0,$Q19/$N19*MAX(0,(IF($I19="",AK$3,MIN($I19,AK$3)))-(MAX($H19,(EDATE(AK$3,-12)+1)))+1)/(AK$3-(EDATE(AK$3,-12)+1)+1)))*$W19),MAX(0,AJ19-$M19))) | AL19: =IF($K19="","",IF(AND($I19<>"",$I19<=AK$3),0,AJ19-AK19)) | AM19: =IF(OR($K19="",$H19=""),"",MIN(MAX(0,IF($O19="WDV",AL19*$P19*MAX(0,(IF($I19="",AM$3,MIN($I19,AM$3)))-(MAX($H19,(EDATE(AM$3,-12)+1)))+1)/(AM$3-(EDATE(AM$3,-12)+1)+1),IF($N19=0,0,$Q19/$N19*MAX(0,(IF($I19="",AM$3,MIN($I19,AM$3)))-(MAX($H19,(EDATE(AM$3,-12)+1)))+1)/(AM$3-(EDATE(AM$3,-12)+1)+1)))*$W19),MAX(0,AL19-$M19))) | AN19: =IF($K19="","",IF(AND($I19<>"",$I19<=AM$3),0,AL19-AM19)) | AO19: =IF(OR($K19="",$H19=""),"",MIN(MAX(0,IF($O19="WDV",AN19*$P19*MAX(0,(IF($I19="",AO$3,MIN($I19,AO$3)))-(MAX($H19,(EDATE(AO$3,-12)+1)))+1)/(AO$3-(EDATE(AO$3,-12)+1)+1),IF($N19=0,0,$Q19/$N19*MAX(0,(IF($I19="",AO$3,MIN($I19,AO$3)))-(MAX($H19,(EDATE(AO$3,-12)+1)))+1)/(AO$3-(EDATE(AO$3,-12)+1)+1)))*$W19),MAX(0,AN19-$M19))) | AP19: =IF($K19="","",IF(AND($I19<>"",$I19<=AO$3),0,AN19-AO19)) | AQ19: =IF(OR($K19="",$H19=""),"",MIN(MAX(0,IF($O19="WDV",AP19*$P19*MAX(0,(IF($I19="",AQ$3,MIN($I19,AQ$3)))-(MAX($H19,(EDATE(AQ$3,-12)+1)))+1)/(AQ$3-(EDATE(AQ$3,-12)+1)+1),IF($N19=0,0,$Q19/$N19*MAX(0,(IF($I19="",AQ$3,MIN($I19,AQ$3)))-(MAX($H19,(EDATE(AQ$3,-12)+1)))+1)/(AQ$3-(EDATE(AQ$3,-12)+1)+1)))*$W19),MAX(0,AP19-$M19))) | AR19: =IF($K19="","",IF(AND($I19<>"",$I19<=AQ$3),0,AP19-AQ19)) | AS19: =IF(OR($K19="",$H19=""),"",MIN(MAX(0,IF($O19="WDV",AR19*$P19*MAX(0,(IF($I19="",AS$3,MIN($I19,AS$3)))-(MAX($H19,(EDATE(AS$3,-12)+1)))+1)/(AS$3-(EDATE(AS$3,-12)+1)+1),IF($N19=0,0,$Q19/$N19*MAX(0,(IF($I19="",AS$3,MIN($I19,AS$3)))-(MAX($H19,(EDATE(AS$3,-12)+1)))+1)/(AS$3-(EDATE(AS$3,-12)+1)+1)))*$W19),MAX(0,AR19-$M19))) | AT19: =IF($K19="","",IF(AND($I19<>"",$I19<=AS$3),0,AR19-AS19)) | AU19: =IF(OR($K19="",$H19=""),"",MIN(MAX(0,IF($O19="WDV",AT19*$P19*MAX(0,(IF($I19="",AU$3,MIN($I19,AU$3)))-(MAX($H19,(EDATE(AU$3,-12)+1)))+1)/(AU$3-(EDATE(AU$3,-12)+1)+1),IF($N19=0,0,$Q19/$N19*MAX(0,(IF($I19="",AU$3,MIN($I19,AU$3)))-(MAX($H19,(EDATE(AU$3,-12)+1)))+1)/(AU$3-(EDATE(AU$3,-12)+1)+1)))*$W19),MAX(0,AT19-$M19))) | AV19: =IF($K19="","",IF(AND($I19<>"",$I19<=AU$3),0,AT19-AU19)) | AW19: =IF(OR($K19="",$H19=""),"",MIN(MAX(0,IF($O19="WDV",AV19*$P19*MAX(0,(IF($I19="",AW$3,MIN($I19,AW$3)))-(MAX($H19,(EDATE(AW$3,-12)+1)))+1)/(AW$3-(EDATE(AW$3,-12)+1)+1),IF($N19=0,0,$Q19/$N19*MAX(0,(IF($I19="",AW$3,MIN($I19,AW$3)))-(MAX($H19,(EDATE(AW$3,-12)+1)))+1)/(AW$3-(EDATE(AW$3,-12)+1)+1)))*$W19),MAX(0,AV19-$M19))) | AX19: =IF($K19="","",IF(AND($I19<>"",$I19<=AW$3),0,AV19-AW19)) | AY19: =IF(OR($K19="",$H19=""),"",MIN(MAX(0,IF($O19="WDV",AX19*$P19*MAX(0,(IF($I19="",AY$3,MIN($I19,AY$3)))-(MAX($H19,(EDATE(AY$3,-12)+1)))+1)/(AY$3-(EDATE(AY$3,-12)+1)+1),IF($N19=0,0,$Q19/$N19*MAX(0,(IF($I19="",AY$3,MIN($I19,AY$3)))-(MAX($H19,(EDATE(AY$3,-12)+1)))+1)/(AY$3-(EDATE(AY$3,-12)+1)+1)))*$W19),MAX(0,AX19-$M19))) | AZ19: =IF($K19="","",IF(AND($I19<>"",$I19<=AY$3),0,AX19-AY19)) | BA19: =IF(OR($K19="",$H19=""),"",MIN(MAX(0,IF($O19="WDV",AZ19*$P19*MAX(0,(IF($I19="",BA$3,MIN($I19,BA$3)))-(MAX($H19,(EDATE(BA$3,-12)+1)))+1)/(BA$3-(EDATE(BA$3,-12)+1)+1),IF($N19=0,0,$Q19/$N19*MAX(0,(IF($I19="",BA$3,MIN($I19,BA$3)))-(MAX($H19,(EDATE(BA$3,-12)+1)))+1)/(BA$3-(EDATE(BA$3,-12)+1)+1)))*$W19),MAX(0,AZ19-$M19))) | BB19: =IF($K19="","",IF(AND($I19<>"",$I19<=BA$3),0,AZ19-BA19)) | BC19: =IF(OR($K19="",$H19=""),"",MIN(MAX(0,IF($O19="WDV",BB19*$P19*MAX(0,(IF($I19="",BC$3,MIN($I19,BC$3)))-(MAX($H19,(EDATE(BC$3,-12)+1)))+1)/(BC$3-(EDATE(BC$3,-12)+1)+1),IF($N19=0,0,$Q19/$N19*MAX(0,(IF($I19="",BC$3,MIN($I19,BC$3)))-(MAX($H19,(EDATE(BC$3,-12)+1)))+1)/(BC$3-(EDATE(BC$3,-12)+1)+1)))*$W19),MAX(0,BB19-$M19))) | BD19: =IF($K19="","",IF(AND($I19<>"",$I19<=BC$3),0,BB19-BC19)) | BE19: =IF(OR($K19="",$H19=""),"",MIN(MAX(0,IF($O19="WDV",BD19*$P19*MAX(0,(IF($I19="",BE$3,MIN($I19,BE$3)))-(MAX($H19,(EDATE(BE$3,-12)+1)))+1)/(BE$3-(EDATE(BE$3,-12)+1)+1),IF($N19=0,0,$Q19/$N19*MAX(0,(IF($I19="",BE$3,MIN($I19,BE$3)))-(MAX($H19,(EDATE(BE$3,-12)+1)))+1)/(BE$3-(EDATE(BE$3,-12)+1)+1)))*$W19),MAX(0,BD19-$M19))) | BF19: =IF($K19="","",IF(AND($I19<>"",$I19<=BE$3),0,BD19-BE19))
L20: =DefaultResidual | M20: =IF($K20="","",$K20*$L20) | N20: =IF($C20="","",IFERROR(VLOOKUP($C20,ScheduleIITable,3,FALSE),"#N/A")) | O20: =IF($K20="","",GlobalMethod) | P20: =IF(OR($K20="",$N20="",$N20=0,$M20=0),0,1-($M20/$K20)^(1/$N20)) | Q20: =IF($K20="","",$K20-$M20) | R20: =IF($K20="","",INDEX($AA20:$BF20,1,MATCH(ReportingFYEnd,$AA$3:$BF$3,0))) | S20: =IF($K20="","",IF($U20="Disposed",0,$K20-$T20)) | T20: =IF($K20="","",INDEX($AA20:$BF20,1,MATCH(ReportingFYEnd,$AA$3:$BF$3,0)+1)) | U20: =IF($K20="","",IF(AND($I20<>"",$I20<=ReportingFYEnd),"Disposed",IF(OR($H20="",$H20>ReportingFYEnd),"Not Yet in Use","Active"))) | W20: =IF($V20="Double",1.5,IF($V20="Triple",2,1)) | Y20: =IF($K20="","",IF(OR(ISNUMBER(SEARCH("Build",$C20)),ISNUMBER(SEARCH("Lease",$C20))),"Yes","NA")) | AA20: =IF(OR($K20="",$H20=""),"",MIN(MAX(0,IF($O20="WDV",$K20*$P20*MAX(0,(IF($I20="",AA$3,MIN($I20,AA$3)))-(MAX($H20,(EDATE(AA$3,-12)+1)))+1)/(AA$3-(EDATE(AA$3,-12)+1)+1),IF($N20=0,0,$Q20/$N20*MAX(0,(IF($I20="",AA$3,MIN($I20,AA$3)))-(MAX($H20,(EDATE(AA$3,-12)+1)))+1)/(AA$3-(EDATE(AA$3,-12)+1)+1)))*$W20),MAX(0,$K20-$M20))) | AB20: =IF($K20="","",IF(AND($I20<>"",$I20<=AA$3),0,$K20-AA20)) | AC20: =IF(OR($K20="",$H20=""),"",MIN(MAX(0,IF($O20="WDV",AB20*$P20*MAX(0,(IF($I20="",AC$3,MIN($I20,AC$3)))-(MAX($H20,(EDATE(AC$3,-12)+1)))+1)/(AC$3-(EDATE(AC$3,-12)+1)+1),IF($N20=0,0,$Q20/$N20*MAX(0,(IF($I20="",AC$3,MIN($I20,AC$3)))-(MAX($H20,(EDATE(AC$3,-12)+1)))+1)/(AC$3-(EDATE(AC$3,-12)+1)+1)))*$W20),MAX(0,AB20-$M20))) | AD20: =IF($K20="","",IF(AND($I20<>"",$I20<=AC$3),0,AB20-AC20)) | AE20: =IF(OR($K20="",$H20=""),"",MIN(MAX(0,IF($O20="WDV",AD20*$P20*MAX(0,(IF($I20="",AE$3,MIN($I20,AE$3)))-(MAX($H20,(EDATE(AE$3,-12)+1)))+1)/(AE$3-(EDATE(AE$3,-12)+1)+1),IF($N20=0,0,$Q20/$N20*MAX(0,(IF($I20="",AE$3,MIN($I20,AE$3)))-(MAX($H20,(EDATE(AE$3,-12)+1)))+1)/(AE$3-(EDATE(AE$3,-12)+1)+1)))*$W20),MAX(0,AD20-$M20))) | AF20: =IF($K20="","",IF(AND($I20<>"",$I20<=AE$3),0,AD20-AE20)) | AG20: =IF(OR($K20="",$H20=""),"",MIN(MAX(0,IF($O20="WDV",AF20*$P20*MAX(0,(IF($I20="",AG$3,MIN($I20,AG$3)))-(MAX($H20,(EDATE(AG$3,-12)+1)))+1)/(AG$3-(EDATE(AG$3,-12)+1)+1),IF($N20=0,0,$Q20/$N20*MAX(0,(IF($I20="",AG$3,MIN($I20,AG$3)))-(MAX($H20,(EDATE(AG$3,-12)+1)))+1)/(AG$3-(EDATE(AG$3,-12)+1)+1)))*$W20),MAX(0,AF20-$M20))) | AH20: =IF($K20="","",IF(AND($I20<>"",$I20<=AG$3),0,AF20-AG20)) | AI20: =IF(OR($K20="",$H20=""),"",MIN(MAX(0,IF($O20="WDV",AH20*$P20*MAX(0,(IF($I20="",AI$3,MIN($I20,AI$3)))-(MAX($H20,(EDATE(AI$3,-12)+1)))+1)/(AI$3-(EDATE(AI$3,-12)+1)+1),IF($N20=0,0,$Q20/$N20*MAX(0,(IF($I20="",AI$3,MIN($I20,AI$3)))-(MAX($H20,(EDATE(AI$3,-12)+1)))+1)/(AI$3-(EDATE(AI$3,-12)+1)+1)))*$W20),MAX(0,AH20-$M20))) | AJ20: =IF($K20="","",IF(AND($I20<>"",$I20<=AI$3),0,AH20-AI20)) | AK20: =IF(OR($K20="",$H20=""),"",MIN(MAX(0,IF($O20="WDV",AJ20*$P20*MAX(0,(IF($I20="",AK$3,MIN($I20,AK$3)))-(MAX($H20,(EDATE(AK$3,-12)+1)))+1)/(AK$3-(EDATE(AK$3,-12)+1)+1),IF($N20=0,0,$Q20/$N20*MAX(0,(IF($I20="",AK$3,MIN($I20,AK$3)))-(MAX($H20,(EDATE(AK$3,-12)+1)))+1)/(AK$3-(EDATE(AK$3,-12)+1)+1)))*$W20),MAX(0,AJ20-$M20))) | AL20: =IF($K20="","",IF(AND($I20<>"",$I20<=AK$3),0,AJ20-AK20)) | AM20: =IF(OR($K20="",$H20=""),"",MIN(MAX(0,IF($O20="WDV",AL20*$P20*MAX(0,(IF($I20="",AM$3,MIN($I20,AM$3)))-(MAX($H20,(EDATE(AM$3,-12)+1)))+1)/(AM$3-(EDATE(AM$3,-12)+1)+1),IF($N20=0,0,$Q20/$N20*MAX(0,(IF($I20="",AM$3,MIN($I20,AM$3)))-(MAX($H20,(EDATE(AM$3,-12)+1)))+1)/(AM$3-(EDATE(AM$3,-12)+1)+1)))*$W20),MAX(0,AL20-$M20))) | AN20: =IF($K20="","",IF(AND($I20<>"",$I20<=AM$3),0,AL20-AM20)) | AO20: =IF(OR($K20="",$H20=""),"",MIN(MAX(0,IF($O20="WDV",AN20*$P20*MAX(0,(IF($I20="",AO$3,MIN($I20,AO$3)))-(MAX($H20,(EDATE(AO$3,-12)+1)))+1)/(AO$3-(EDATE(AO$3,-12)+1)+1),IF($N20=0,0,$Q20/$N20*MAX(0,(IF($I20="",AO$3,MIN($I20,AO$3)))-(MAX($H20,(EDATE(AO$3,-12)+1)))+1)/(AO$3-(EDATE(AO$3,-12)+1)+1)))*$W20),MAX(0,AN20-$M20))) | AP20: =IF($K20="","",IF(AND($I20<>"",$I20<=AO$3),0,AN20-AO20)) | AQ20: =IF(OR($K20="",$H20=""),"",MIN(MAX(0,IF($O20="WDV",AP20*$P20*MAX(0,(IF($I20="",AQ$3,MIN($I20,AQ$3)))-(MAX($H20,(EDATE(AQ$3,-12)+1)))+1)/(AQ$3-(EDATE(AQ$3,-12)+1)+1),IF($N20=0,0,$Q20/$N20*MAX(0,(IF($I20="",AQ$3,MIN($I20,AQ$3)))-(MAX($H20,(EDATE(AQ$3,-12)+1)))+1)/(AQ$3-(EDATE(AQ$3,-12)+1)+1)))*$W20),MAX(0,AP20-$M20))) | AR20: =IF($K20="","",IF(AND($I20<>"",$I20<=AQ$3),0,AP20-AQ20)) | AS20: =IF(OR($K20="",$H20=""),"",MIN(MAX(0,IF($O20="WDV",AR20*$P20*MAX(0,(IF($I20="",AS$3,MIN($I20,AS$3)))-(MAX($H20,(EDATE(AS$3,-12)+1)))+1)/(AS$3-(EDATE(AS$3,-12)+1)+1),IF($N20=0,0,$Q20/$N20*MAX(0,(IF($I20="",AS$3,MIN($I20,AS$3)))-(MAX($H20,(EDATE(AS$3,-12)+1)))+1)/(AS$3-(EDATE(AS$3,-12)+1)+1)))*$W20),MAX(0,AR20-$M20))) | AT20: =IF($K20="","",IF(AND($I20<>"",$I20<=AS$3),0,AR20-AS20)) | AU20: =IF(OR($K20="",$H20=""),"",MIN(MAX(0,IF($O20="WDV",AT20*$P20*MAX(0,(IF($I20="",AU$3,MIN($I20,AU$3)))-(MAX($H20,(EDATE(AU$3,-12)+1)))+1)/(AU$3-(EDATE(AU$3,-12)+1)+1),IF($N20=0,0,$Q20/$N20*MAX(0,(IF($I20="",AU$3,MIN($I20,AU$3)))-(MAX($H20,(EDATE(AU$3,-12)+1)))+1)/(AU$3-(EDATE(AU$3,-12)+1)+1)))*$W20),MAX(0,AT20-$M20))) | AV20: =IF($K20="","",IF(AND($I20<>"",$I20<=AU$3),0,AT20-AU20)) | AW20: =IF(OR($K20="",$H20=""),"",MIN(MAX(0,IF($O20="WDV",AV20*$P20*MAX(0,(IF($I20="",AW$3,MIN($I20,AW$3)))-(MAX($H20,(EDATE(AW$3,-12)+1)))+1)/(AW$3-(EDATE(AW$3,-12)+1)+1),IF($N20=0,0,$Q20/$N20*MAX(0,(IF($I20="",AW$3,MIN($I20,AW$3)))-(MAX($H20,(EDATE(AW$3,-12)+1)))+1)/(AW$3-(EDATE(AW$3,-12)+1)+1)))*$W20),MAX(0,AV20-$M20))) | AX20: =IF($K20="","",IF(AND($I20<>"",$I20<=AW$3),0,AV20-AW20)) | AY20: =IF(OR($K20="",$H20=""),"",MIN(MAX(0,IF($O20="WDV",AX20*$P20*MAX(0,(IF($I20="",AY$3,MIN($I20,AY$3)))-(MAX($H20,(EDATE(AY$3,-12)+1)))+1)/(AY$3-(EDATE(AY$3,-12)+1)+1),IF($N20=0,0,$Q20/$N20*MAX(0,(IF($I20="",AY$3,MIN($I20,AY$3)))-(MAX($H20,(EDATE(AY$3,-12)+1)))+1)/(AY$3-(EDATE(AY$3,-12)+1)+1)))*$W20),MAX(0,AX20-$M20))) | AZ20: =IF($K20="","",IF(AND($I20<>"",$I20<=AY$3),0,AX20-AY20)) | BA20: =IF(OR($K20="",$H20=""),"",MIN(MAX(0,IF($O20="WDV",AZ20*$P20*MAX(0,(IF($I20="",BA$3,MIN($I20,BA$3)))-(MAX($H20,(EDATE(BA$3,-12)+1)))+1)/(BA$3-(EDATE(BA$3,-12)+1)+1),IF($N20=0,0,$Q20/$N20*MAX(0,(IF($I20="",BA$3,MIN($I20,BA$3)))-(MAX($H20,(EDATE(BA$3,-12)+1)))+1)/(BA$3-(EDATE(BA$3,-12)+1)+1)))*$W20),MAX(0,AZ20-$M20))) | BB20: =IF($K20="","",IF(AND($I20<>"",$I20<=BA$3),0,AZ20-BA20)) | BC20: =IF(OR($K20="",$H20=""),"",MIN(MAX(0,IF($O20="WDV",BB20*$P20*MAX(0,(IF($I20="",BC$3,MIN($I20,BC$3)))-(MAX($H20,(EDATE(BC$3,-12)+1)))+1)/(BC$3-(EDATE(BC$3,-12)+1)+1),IF($N20=0,0,$Q20/$N20*MAX(0,(IF($I20="",BC$3,MIN($I20,BC$3)))-(MAX($H20,(EDATE(BC$3,-12)+1)))+1)/(BC$3-(EDATE(BC$3,-12)+1)+1)))*$W20),MAX(0,BB20-$M20))) | BD20: =IF($K20="","",IF(AND($I20<>"",$I20<=BC$3),0,BB20-BC20)) | BE20: =IF(OR($K20="",$H20=""),"",MIN(MAX(0,IF($O20="WDV",BD20*$P20*MAX(0,(IF($I20="",BE$3,MIN($I20,BE$3)))-(MAX($H20,(EDATE(BE$3,-12)+1)))+1)/(BE$3-(EDATE(BE$3,-12)+1)+1),IF($N20=0,0,$Q20/$N20*MAX(0,(IF($I20="",BE$3,MIN($I20,BE$3)))-(MAX($H20,(EDATE(BE$3,-12)+1)))+1)/(BE$3-(EDATE(BE$3,-12)+1)+1)))*$W20),MAX(0,BD20-$M20))) | BF20: =IF($K20="","",IF(AND($I20<>"",$I20<=BE$3),0,BD20-BE20))
L21: =DefaultResidual | M21: =IF($K21="","",$K21*$L21) | N21: =IF($C21="","",IFERROR(VLOOKUP($C21,ScheduleIITable,3,FALSE),"#N/A")) | O21: =IF($K21="","",GlobalMethod) | P21: =IF(OR($K21="",$N21="",$N21=0,$M21=0),0,1-($M21/$K21)^(1/$N21)) | Q21: =IF($K21="","",$K21-$M21) | R21: =IF($K21="","",INDEX($AA21:$BF21,1,MATCH(ReportingFYEnd,$AA$3:$BF$3,0))) | S21: =IF($K21="","",IF($U21="Disposed",0,$K21-$T21)) | T21: =IF($K21="","",INDEX($AA21:$BF21,1,MATCH(ReportingFYEnd,$AA$3:$BF$3,0)+1)) | U21: =IF($K21="","",IF(AND($I21<>"",$I21<=ReportingFYEnd),"Disposed",IF(OR($H21="",$H21>ReportingFYEnd),"Not Yet in Use","Active"))) | W21: =IF($V21="Double",1.5,IF($V21="Triple",2,1)) | Y21: =IF($K21="","",IF(OR(ISNUMBER(SEARCH("Build",$C21)),ISNUMBER(SEARCH("Lease",$C21))),"Yes","NA")) | AA21: =IF(OR($K21="",$H21=""),"",MIN(MAX(0,IF($O21="WDV",$K21*$P21*MAX(0,(IF($I21="",AA$3,MIN($I21,AA$3)))-(MAX($H21,(EDATE(AA$3,-12)+1)))+1)/(AA$3-(EDATE(AA$3,-12)+1)+1),IF($N21=0,0,$Q21/$N21*MAX(0,(IF($I21="",AA$3,MIN($I21,AA$3)))-(MAX($H21,(EDATE(AA$3,-12)+1)))+1)/(AA$3-(EDATE(AA$3,-12)+1)+1)))*$W21),MAX(0,$K21-$M21))) | AB21: =IF($K21="","",IF(AND($I21<>"",$I21<=AA$3),0,$K21-AA21)) | AC21: =IF(OR($K21="",$H21=""),"",MIN(MAX(0,IF($O21="WDV",AB21*$P21*MAX(0,(IF($I21="",AC$3,MIN($I21,AC$3)))-(MAX($H21,(EDATE(AC$3,-12)+1)))+1)/(AC$3-(EDATE(AC$3,-12)+1)+1),IF($N21=0,0,$Q21/$N21*MAX(0,(IF($I21="",AC$3,MIN($I21,AC$3)))-(MAX($H21,(EDATE(AC$3,-12)+1)))+1)/(AC$3-(EDATE(AC$3,-12)+1)+1)))*$W21),MAX(0,AB21-$M21))) | AD21: =IF($K21="","",IF(AND($I21<>"",$I21<=AC$3),0,AB21-AC21)) | AE21: =IF(OR($K21="",$H21=""),"",MIN(MAX(0,IF($O21="WDV",AD21*$P21*MAX(0,(IF($I21="",AE$3,MIN($I21,AE$3)))-(MAX($H21,(EDATE(AE$3,-12)+1)))+1)/(AE$3-(EDATE(AE$3,-12)+1)+1),IF($N21=0,0,$Q21/$N21*MAX(0,(IF($I21="",AE$3,MIN($I21,AE$3)))-(MAX($H21,(EDATE(AE$3,-12)+1)))+1)/(AE$3-(EDATE(AE$3,-12)+1)+1)))*$W21),MAX(0,AD21-$M21))) | AF21: =IF($K21="","",IF(AND($I21<>"",$I21<=AE$3),0,AD21-AE21)) | AG21: =IF(OR($K21="",$H21=""),"",MIN(MAX(0,IF($O21="WDV",AF21*$P21*MAX(0,(IF($I21="",AG$3,MIN($I21,AG$3)))-(MAX($H21,(EDATE(AG$3,-12)+1)))+1)/(AG$3-(EDATE(AG$3,-12)+1)+1),IF($N21=0,0,$Q21/$N21*MAX(0,(IF($I21="",AG$3,MIN($I21,AG$3)))-(MAX($H21,(EDATE(AG$3,-12)+1)))+1)/(AG$3-(EDATE(AG$3,-12)+1)+1)))*$W21),MAX(0,AF21-$M21))) | AH21: =IF($K21="","",IF(AND($I21<>"",$I21<=AG$3),0,AF21-AG21)) | AI21: =IF(OR($K21="",$H21=""),"",MIN(MAX(0,IF($O21="WDV",AH21*$P21*MAX(0,(IF($I21="",AI$3,MIN($I21,AI$3)))-(MAX($H21,(EDATE(AI$3,-12)+1)))+1)/(AI$3-(EDATE(AI$3,-12)+1)+1),IF($N21=0,0,$Q21/$N21*MAX(0,(IF($I21="",AI$3,MIN($I21,AI$3)))-(MAX($H21,(EDATE(AI$3,-12)+1)))+1)/(AI$3-(EDATE(AI$3,-12)+1)+1)))*$W21),MAX(0,AH21-$M21))) | AJ21: =IF($K21="","",IF(AND($I21<>"",$I21<=AI$3),0,AH21-AI21)) | AK21: =IF(OR($K21="",$H21=""),"",MIN(MAX(0,IF($O21="WDV",AJ21*$P21*MAX(0,(IF($I21="",AK$3,MIN($I21,AK$3)))-(MAX($H21,(EDATE(AK$3,-12)+1)))+1)/(AK$3-(EDATE(AK$3,-12)+1)+1),IF($N21=0,0,$Q21/$N21*MAX(0,(IF($I21="",AK$3,MIN($I21,AK$3)))-(MAX($H21,(EDATE(AK$3,-12)+1)))+1)/(AK$3-(EDATE(AK$3,-12)+1)+1)))*$W21),MAX(0,AJ21-$M21))) | AL21: =IF($K21="","",IF(AND($I21<>"",$I21<=AK$3),0,AJ21-AK21)) | AM21: =IF(OR($K21="",$H21=""),"",MIN(MAX(0,IF($O21="WDV",AL21*$P21*MAX(0,(IF($I21="",AM$3,MIN($I21,AM$3)))-(MAX($H21,(EDATE(AM$3,-12)+1)))+1)/(AM$3-(EDATE(AM$3,-12)+1)+1),IF($N21=0,0,$Q21/$N21*MAX(0,(IF($I21="",AM$3,MIN($I21,AM$3)))-(MAX($H21,(EDATE(AM$3,-12)+1)))+1)/(AM$3-(EDATE(AM$3,-12)+1)+1)))*$W21),MAX(0,AL21-$M21))) | AN21: =IF($K21="","",IF(AND($I21<>"",$I21<=AM$3),0,AL21-AM21)) | AO21: =IF(OR($K21="",$H21=""),"",MIN(MAX(0,IF($O21="WDV",AN21*$P21*MAX(0,(IF($I21="",AO$3,MIN($I21,AO$3)))-(MAX($H21,(EDATE(AO$3,-12)+1)))+1)/(AO$3-(EDATE(AO$3,-12)+1)+1),IF($N21=0,0,$Q21/$N21*MAX(0,(IF($I21="",AO$3,MIN($I21,AO$3)))-(MAX($H21,(EDATE(AO$3,-12)+1)))+1)/(AO$3-(EDATE(AO$3,-12)+1)+1)))*$W21),MAX(0,AN21-$M21))) | AP21: =IF($K21="","",IF(AND($I21<>"",$I21<=AO$3),0,AN21-AO21)) | AQ21: =IF(OR($K21="",$H21=""),"",MIN(MAX(0,IF($O21="WDV",AP21*$P21*MAX(0,(IF($I21="",AQ$3,MIN($I21,AQ$3)))-(MAX($H21,(EDATE(AQ$3,-12)+1)))+1)/(AQ$3-(EDATE(AQ$3,-12)+1)+1),IF($N21=0,0,$Q21/$N21*MAX(0,(IF($I21="",AQ$3,MIN($I21,AQ$3)))-(MAX($H21,(EDATE(AQ$3,-12)+1)))+1)/(AQ$3-(EDATE(AQ$3,-12)+1)+1)))*$W21),MAX(0,AP21-$M21))) | AR21: =IF($K21="","",IF(AND($I21<>"",$I21<=AQ$3),0,AP21-AQ21)) | AS21: =IF(OR($K21="",$H21=""),"",MIN(MAX(0,IF($O21="WDV",AR21*$P21*MAX(0,(IF($I21="",AS$3,MIN($I21,AS$3)))-(MAX($H21,(EDATE(AS$3,-12)+1)))+1)/(AS$3-(EDATE(AS$3,-12)+1)+1),IF($N21=0,0,$Q21/$N21*MAX(0,(IF($I21="",AS$3,MIN($I21,AS$3)))-(MAX($H21,(EDATE(AS$3,-12)+1)))+1)/(AS$3-(EDATE(AS$3,-12)+1)+1)))*$W21),MAX(0,AR21-$M21))) | AT21: =IF($K21="","",IF(AND($I21<>"",$I21<=AS$3),0,AR21-AS21)) | AU21: =IF(OR($K21="",$H21=""),"",MIN(MAX(0,IF($O21="WDV",AT21*$P21*MAX(0,(IF($I21="",AU$3,MIN($I21,AU$3)))-(MAX($H21,(EDATE(AU$3,-12)+1)))+1)/(AU$3-(EDATE(AU$3,-12)+1)+1),IF($N21=0,0,$Q21/$N21*MAX(0,(IF($I21="",AU$3,MIN($I21,AU$3)))-(MAX($H21,(EDATE(AU$3,-12)+1)))+1)/(AU$3-(EDATE(AU$3,-12)+1)+1)))*$W21),MAX(0,AT21-$M21))) | AV21: =IF($K21="","",IF(AND($I21<>"",$I21<=AU$3),0,AT21-AU21)) | AW21: =IF(OR($K21="",$H21=""),"",MIN(MAX(0,IF($O21="WDV",AV21*$P21*MAX(0,(IF($I21="",AW$3,MIN($I21,AW$3)))-(MAX($H21,(EDATE(AW$3,-12)+1)))+1)/(AW$3-(EDATE(AW$3,-12)+1)+1),IF($N21=0,0,$Q21/$N21*MAX(0,(IF($I21="",AW$3,MIN($I21,AW$3)))-(MAX($H21,(EDATE(AW$3,-12)+1)))+1)/(AW$3-(EDATE(AW$3,-12)+1)+1)))*$W21),MAX(0,AV21-$M21))) | AX21: =IF($K21="","",IF(AND($I21<>"",$I21<=AW$3),0,AV21-AW21)) | AY21: =IF(OR($K21="",$H21=""),"",MIN(MAX(0,IF($O21="WDV",AX21*$P21*MAX(0,(IF($I21="",AY$3,MIN($I21,AY$3)))-(MAX($H21,(EDATE(AY$3,-12)+1)))+1)/(AY$3-(EDATE(AY$3,-12)+1)+1),IF($N21=0,0,$Q21/$N21*MAX(0,(IF($I21="",AY$3,MIN($I21,AY$3)))-(MAX($H21,(EDATE(AY$3,-12)+1)))+1)/(AY$3-(EDATE(AY$3,-12)+1)+1)))*$W21),MAX(0,AX21-$M21))) | AZ21: =IF($K21="","",IF(AND($I21<>"",$I21<=AY$3),0,AX21-AY21)) | BA21: =IF(OR($K21="",$H21=""),"",MIN(MAX(0,IF($O21="WDV",AZ21*$P21*MAX(0,(IF($I21="",BA$3,MIN($I21,BA$3)))-(MAX($H21,(EDATE(BA$3,-12)+1)))+1)/(BA$3-(EDATE(BA$3,-12)+1)+1),IF($N21=0,0,$Q21/$N21*MAX(0,(IF($I21="",BA$3,MIN($I21,BA$3)))-(MAX($H21,(EDATE(BA$3,-12)+1)))+1)/(BA$3-(EDATE(BA$3,-12)+1)+1)))*$W21),MAX(0,AZ21-$M21))) | BB21: =IF($K21="","",IF(AND($I21<>"",$I21<=BA$3),0,AZ21-BA21)) | BC21: =IF(OR($K21="",$H21=""),"",MIN(MAX(0,IF($O21="WDV",BB21*$P21*MAX(0,(IF($I21="",BC$3,MIN($I21,BC$3)))-(MAX($H21,(EDATE(BC$3,-12)+1)))+1)/(BC$3-(EDATE(BC$3,-12)+1)+1),IF($N21=0,0,$Q21/$N21*MAX(0,(IF($I21="",BC$3,MIN($I21,BC$3)))-(MAX($H21,(EDATE(BC$3,-12)+1)))+1)/(BC$3-(EDATE(BC$3,-12)+1)+1)))*$W21),MAX(0,BB21-$M21))) | BD21: =IF($K21="","",IF(AND($I21<>"",$I21<=BC$3),0,BB21-BC21)) | BE21: =IF(OR($K21="",$H21=""),"",MIN(MAX(0,IF($O21="WDV",BD21*$P21*MAX(0,(IF($I21="",BE$3,MIN($I21,BE$3)))-(MAX($H21,(EDATE(BE$3,-12)+1)))+1)/(BE$3-(EDATE(BE$3,-12)+1)+1),IF($N21=0,0,$Q21/$N21*MAX(0,(IF($I21="",BE$3,MIN($I21,BE$3)))-(MAX($H21,(EDATE(BE$3,-12)+1)))+1)/(BE$3-(EDATE(BE$3,-12)+1)+1)))*$W21),MAX(0,BD21-$M21))) | BF21: =IF($K21="","",IF(AND($I21<>"",$I21<=BE$3),0,BD21-BE21))
L22: =DefaultResidual | M22: =IF($K22="","",$K22*$L22) | N22: =IF($C22="","",IFERROR(VLOOKUP($C22,ScheduleIITable,3,FALSE),"#N/A")) | O22: =IF($K22="","",GlobalMethod) | P22: =IF(OR($K22="",$N22="",$N22=0,$M22=0),0,1-($M22/$K22)^(1/$N22)) | Q22: =IF($K22="","",$K22-$M22) | R22: =IF($K22="","",INDEX($AA22:$BF22,1,MATCH(ReportingFYEnd,$AA$3:$BF$3,0))) | S22: =IF($K22="","",IF($U22="Disposed",0,$K22-$T22)) | T22: =IF($K22="","",INDEX($AA22:$BF22,1,MATCH(ReportingFYEnd,$AA$3:$BF$3,0)+1)) | U22: =IF($K22="","",IF(AND($I22<>"",$I22<=ReportingFYEnd),"Disposed",IF(OR($H22="",$H22>ReportingFYEnd),"Not Yet in Use","Active"))) | W22: =IF($V22="Double",1.5,IF($V22="Triple",2,1)) | Y22: =IF($K22="","",IF(OR(ISNUMBER(SEARCH("Build",$C22)),ISNUMBER(SEARCH("Lease",$C22))),"Yes","NA")) | AA22: =IF(OR($K22="",$H22=""),"",MIN(MAX(0,IF($O22="WDV",$K22*$P22*MAX(0,(IF($I22="",AA$3,MIN($I22,AA$3)))-(MAX($H22,(EDATE(AA$3,-12)+1)))+1)/(AA$3-(EDATE(AA$3,-12)+1)+1),IF($N22=0,0,$Q22/$N22*MAX(0,(IF($I22="",AA$3,MIN($I22,AA$3)))-(MAX($H22,(EDATE(AA$3,-12)+1)))+1)/(AA$3-(EDATE(AA$3,-12)+1)+1)))*$W22),MAX(0,$K22-$M22))) | AB22: =IF($K22="","",IF(AND($I22<>"",$I22<=AA$3),0,$K22-AA22)) | AC22: =IF(OR($K22="",$H22=""),"",MIN(MAX(0,IF($O22="WDV",AB22*$P22*MAX(0,(IF($I22="",AC$3,MIN($I22,AC$3)))-(MAX($H22,(EDATE(AC$3,-12)+1)))+1)/(AC$3-(EDATE(AC$3,-12)+1)+1),IF($N22=0,0,$Q22/$N22*MAX(0,(IF($I22="",AC$3,MIN($I22,AC$3)))-(MAX($H22,(EDATE(AC$3,-12)+1)))+1)/(AC$3-(EDATE(AC$3,-12)+1)+1)))*$W22),MAX(0,AB22-$M22))) | AD22: =IF($K22="","",IF(AND($I22<>"",$I22<=AC$3),0,AB22-AC22)) | AE22: =IF(OR($K22="",$H22=""),"",MIN(MAX(0,IF($O22="WDV",AD22*$P22*MAX(0,(IF($I22="",AE$3,MIN($I22,AE$3)))-(MAX($H22,(EDATE(AE$3,-12)+1)))+1)/(AE$3-(EDATE(AE$3,-12)+1)+1),IF($N22=0,0,$Q22/$N22*MAX(0,(IF($I22="",AE$3,MIN($I22,AE$3)))-(MAX($H22,(EDATE(AE$3,-12)+1)))+1)/(AE$3-(EDATE(AE$3,-12)+1)+1)))*$W22),MAX(0,AD22-$M22))) | AF22: =IF($K22="","",IF(AND($I22<>"",$I22<=AE$3),0,AD22-AE22)) | AG22: =IF(OR($K22="",$H22=""),"",MIN(MAX(0,IF($O22="WDV",AF22*$P22*MAX(0,(IF($I22="",AG$3,MIN($I22,AG$3)))-(MAX($H22,(EDATE(AG$3,-12)+1)))+1)/(AG$3-(EDATE(AG$3,-12)+1)+1),IF($N22=0,0,$Q22/$N22*MAX(0,(IF($I22="",AG$3,MIN($I22,AG$3)))-(MAX($H22,(EDATE(AG$3,-12)+1)))+1)/(AG$3-(EDATE(AG$3,-12)+1)+1)))*$W22),MAX(0,AF22-$M22))) | AH22: =IF($K22="","",IF(AND($I22<>"",$I22<=AG$3),0,AF22-AG22)) | AI22: =IF(OR($K22="",$H22=""),"",MIN(MAX(0,IF($O22="WDV",AH22*$P22*MAX(0,(IF($I22="",AI$3,MIN($I22,AI$3)))-(MAX($H22,(EDATE(AI$3,-12)+1)))+1)/(AI$3-(EDATE(AI$3,-12)+1)+1),IF($N22=0,0,$Q22/$N22*MAX(0,(IF($I22="",AI$3,MIN($I22,AI$3)))-(MAX($H22,(EDATE(AI$3,-12)+1)))+1)/(AI$3-(EDATE(AI$3,-12)+1)+1)))*$W22),MAX(0,AH22-$M22))) | AJ22: =IF($K22="","",IF(AND($I22<>"",$I22<=AI$3),0,AH22-AI22)) | AK22: =IF(OR($K22="",$H22=""),"",MIN(MAX(0,IF($O22="WDV",AJ22*$P22*MAX(0,(IF($I22="",AK$3,MIN($I22,AK$3)))-(MAX($H22,(EDATE(AK$3,-12)+1)))+1)/(AK$3-(EDATE(AK$3,-12)+1)+1),IF($N22=0,0,$Q22/$N22*MAX(0,(IF($I22="",AK$3,MIN($I22,AK$3)))-(MAX($H22,(EDATE(AK$3,-12)+1)))+1)/(AK$3-(EDATE(AK$3,-12)+1)+1)))*$W22),MAX(0,AJ22-$M22))) | AL22: =IF($K22="","",IF(AND($I22<>"",$I22<=AK$3),0,AJ22-AK22)) | AM22: =IF(OR($K22="",$H22=""),"",MIN(MAX(0,IF($O22="WDV",AL22*$P22*MAX(0,(IF($I22="",AM$3,MIN($I22,AM$3)))-(MAX($H22,(EDATE(AM$3,-12)+1)))+1)/(AM$3-(EDATE(AM$3,-12)+1)+1),IF($N22=0,0,$Q22/$N22*MAX(0,(IF($I22="",AM$3,MIN($I22,AM$3)))-(MAX($H22,(EDATE(AM$3,-12)+1)))+1)/(AM$3-(EDATE(AM$3,-12)+1)+1)))*$W22),MAX(0,AL22-$M22))) | AN22: =IF($K22="","",IF(AND($I22<>"",$I22<=AM$3),0,AL22-AM22)) | AO22: =IF(OR($K22="",$H22=""),"",MIN(MAX(0,IF($O22="WDV",AN22*$P22*MAX(0,(IF($I22="",AO$3,MIN($I22,AO$3)))-(MAX($H22,(EDATE(AO$3,-12)+1)))+1)/(AO$3-(EDATE(AO$3,-12)+1)+1),IF($N22=0,0,$Q22/$N22*MAX(0,(IF($I22="",AO$3,MIN($I22,AO$3)))-(MAX($H22,(EDATE(AO$3,-12)+1)))+1)/(AO$3-(EDATE(AO$3,-12)+1)+1)))*$W22),MAX(0,AN22-$M22))) | AP22: =IF($K22="","",IF(AND($I22<>"",$I22<=AO$3),0,AN22-AO22)) | AQ22: =IF(OR($K22="",$H22=""),"",MIN(MAX(0,IF($O22="WDV",AP22*$P22*MAX(0,(IF($I22="",AQ$3,MIN($I22,AQ$3)))-(MAX($H22,(EDATE(AQ$3,-12)+1)))+1)/(AQ$3-(EDATE(AQ$3,-12)+1)+1),IF($N22=0,0,$Q22/$N22*MAX(0,(IF($I22="",AQ$3,MIN($I22,AQ$3)))-(MAX($H22,(EDATE(AQ$3,-12)+1)))+1)/(AQ$3-(EDATE(AQ$3,-12)+1)+1)))*$W22),MAX(0,AP22-$M22))) | AR22: =IF($K22="","",IF(AND($I22<>"",$I22<=AQ$3),0,AP22-AQ22)) | AS22: =IF(OR($K22="",$H22=""),"",MIN(MAX(0,IF($O22="WDV",AR22*$P22*MAX(0,(IF($I22="",AS$3,MIN($I22,AS$3)))-(MAX($H22,(EDATE(AS$3,-12)+1)))+1)/(AS$3-(EDATE(AS$3,-12)+1)+1),IF($N22=0,0,$Q22/$N22*MAX(0,(IF($I22="",AS$3,MIN($I22,AS$3)))-(MAX($H22,(EDATE(AS$3,-12)+1)))+1)/(AS$3-(EDATE(AS$3,-12)+1)+1)))*$W22),MAX(0,AR22-$M22))) | AT22: =IF($K22="","",IF(AND($I22<>"",$I22<=AS$3),0,AR22-AS22)) | AU22: =IF(OR($K22="",$H22=""),"",MIN(MAX(0,IF($O22="WDV",AT22*$P22*MAX(0,(IF($I22="",AU$3,MIN($I22,AU$3)))-(MAX($H22,(EDATE(AU$3,-12)+1)))+1)/(AU$3-(EDATE(AU$3,-12)+1)+1),IF($N22=0,0,$Q22/$N22*MAX(0,(IF($I22="",AU$3,MIN($I22,AU$3)))-(MAX($H22,(EDATE(AU$3,-12)+1)))+1)/(AU$3-(EDATE(AU$3,-12)+1)+1)))*$W22),MAX(0,AT22-$M22))) | AV22: =IF($K22="","",IF(AND($I22<>"",$I22<=AU$3),0,AT22-AU22)) | AW22: =IF(OR($K22="",$H22=""),"",MIN(MAX(0,IF($O22="WDV",AV22*$P22*MAX(0,(IF($I22="",AW$3,MIN($I22,AW$3)))-(MAX($H22,(EDATE(AW$3,-12)+1)))+1)/(AW$3-(EDATE(AW$3,-12)+1)+1),IF($N22=0,0,$Q22/$N22*MAX(0,(IF($I22="",AW$3,MIN($I22,AW$3)))-(MAX($H22,(EDATE(AW$3,-12)+1)))+1)/(AW$3-(EDATE(AW$3,-12)+1)+1)))*$W22),MAX(0,AV22-$M22))) | AX22: =IF($K22="","",IF(AND($I22<>"",$I22<=AW$3),0,AV22-AW22)) | AY22: =IF(OR($K22="",$H22=""),"",MIN(MAX(0,IF($O22="WDV",AX22*$P22*MAX(0,(IF($I22="",AY$3,MIN($I22,AY$3)))-(MAX($H22,(EDATE(AY$3,-12)+1)))+1)/(AY$3-(EDATE(AY$3,-12)+1)+1),IF($N22=0,0,$Q22/$N22*MAX(0,(IF($I22="",AY$3,MIN($I22,AY$3)))-(MAX($H22,(EDATE(AY$3,-12)+1)))+1)/(AY$3-(EDATE(AY$3,-12)+1)+1)))*$W22),MAX(0,AX22-$M22))) | AZ22: =IF($K22="","",IF(AND($I22<>"",$I22<=AY$3),0,AX22-AY22)) | BA22: =IF(OR($K22="",$H22=""),"",MIN(MAX(0,IF($O22="WDV",AZ22*$P22*MAX(0,(IF($I22="",BA$3,MIN($I22,BA$3)))-(MAX($H22,(EDATE(BA$3,-12)+1)))+1)/(BA$3-(EDATE(BA$3,-12)+1)+1),IF($N22=0,0,$Q22/$N22*MAX(0,(IF($I22="",BA$3,MIN($I22,BA$3)))-(MAX($H22,(EDATE(BA$3,-12)+1)))+1)/(BA$3-(EDATE(BA$3,-12)+1)+1)))*$W22),MAX(0,AZ22-$M22))) | BB22: =IF($K22="","",IF(AND($I22<>"",$I22<=BA$3),0,AZ22-BA22)) | BC22: =IF(OR($K22="",$H22=""),"",MIN(MAX(0,IF($O22="WDV",BB22*$P22*MAX(0,(IF($I22="",BC$3,MIN($I22,BC$3)))-(MAX($H22,(EDATE(BC$3,-12)+1)))+1)/(BC$3-(EDATE(BC$3,-12)+1)+1),IF($N22=0,0,$Q22/$N22*MAX(0,(IF($I22="",BC$3,MIN($I22,BC$3)))-(MAX($H22,(EDATE(BC$3,-12)+1)))+1)/(BC$3-(EDATE(BC$3,-12)+1)+1)))*$W22),MAX(0,BB22-$M22))) | BD22: =IF($K22="","",IF(AND($I22<>"",$I22<=BC$3),0,BB22-BC22)) | BE22: =IF(OR($K22="",$H22=""),"",MIN(MAX(0,IF($O22="WDV",BD22*$P22*MAX(0,(IF($I22="",BE$3,MIN($I22,BE$3)))-(MAX($H22,(EDATE(BE$3,-12)+1)))+1)/(BE$3-(EDATE(BE$3,-12)+1)+1),IF($N22=0,0,$Q22/$N22*MAX(0,(IF($I22="",BE$3,MIN($I22,BE$3)))-(MAX($H22,(EDATE(BE$3,-12)+1)))+1)/(BE$3-(EDATE(BE$3,-12)+1)+1)))*$W22),MAX(0,BD22-$M22))) | BF22: =IF($K22="","",IF(AND($I22<>"",$I22<=BE$3),0,BD22-BE22))
L23: =DefaultResidual | M23: =IF($K23="","",$K23*$L23) | N23: =IF($C23="","",IFERROR(VLOOKUP($C23,ScheduleIITable,3,FALSE),"#N/A")) | O23: =IF($K23="","",GlobalMethod) | P23: =IF(OR($K23="",$N23="",$N23=0,$M23=0),0,1-($M23/$K23)^(1/$N23)) | Q23: =IF($K23="","",$K23-$M23) | R23: =IF($K23="","",INDEX($AA23:$BF23,1,MATCH(ReportingFYEnd,$AA$3:$BF$3,0))) | S23: =IF($K23="","",IF($U23="Disposed",0,$K23-$T23)) | T23: =IF($K23="","",INDEX($AA23:$BF23,1,MATCH(ReportingFYEnd,$AA$3:$BF$3,0)+1)) | U23: =IF($K23="","",IF(AND($I23<>"",$I23<=ReportingFYEnd),"Disposed",IF(OR($H23="",$H23>ReportingFYEnd),"Not Yet in Use","Active"))) | W23: =IF($V23="Double",1.5,IF($V23="Triple",2,1)) | Y23: =IF($K23="","",IF(OR(ISNUMBER(SEARCH("Build",$C23)),ISNUMBER(SEARCH("Lease",$C23))),"Yes","NA")) | AA23: =IF(OR($K23="",$H23=""),"",MIN(MAX(0,IF($O23="WDV",$K23*$P23*MAX(0,(IF($I23="",AA$3,MIN($I23,AA$3)))-(MAX($H23,(EDATE(AA$3,-12)+1)))+1)/(AA$3-(EDATE(AA$3,-12)+1)+1),IF($N23=0,0,$Q23/$N23*MAX(0,(IF($I23="",AA$3,MIN($I23,AA$3)))-(MAX($H23,(EDATE(AA$3,-12)+1)))+1)/(AA$3-(EDATE(AA$3,-12)+1)+1)))*$W23),MAX(0,$K23-$M23))) | AB23: =IF($K23="","",IF(AND($I23<>"",$I23<=AA$3),0,$K23-AA23)) | AC23: =IF(OR($K23="",$H23=""),"",MIN(MAX(0,IF($O23="WDV",AB23*$P23*MAX(0,(IF($I23="",AC$3,MIN($I23,AC$3)))-(MAX($H23,(EDATE(AC$3,-12)+1)))+1)/(AC$3-(EDATE(AC$3,-12)+1)+1),IF($N23=0,0,$Q23/$N23*MAX(0,(IF($I23="",AC$3,MIN($I23,AC$3)))-(MAX($H23,(EDATE(AC$3,-12)+1)))+1)/(AC$3-(EDATE(AC$3,-12)+1)+1)))*$W23),MAX(0,AB23-$M23))) | AD23: =IF($K23="","",IF(AND($I23<>"",$I23<=AC$3),0,AB23-AC23)) | AE23: =IF(OR($K23="",$H23=""),"",MIN(MAX(0,IF($O23="WDV",AD23*$P23*MAX(0,(IF($I23="",AE$3,MIN($I23,AE$3)))-(MAX($H23,(EDATE(AE$3,-12)+1)))+1)/(AE$3-(EDATE(AE$3,-12)+1)+1),IF($N23=0,0,$Q23/$N23*MAX(0,(IF($I23="",AE$3,MIN($I23,AE$3)))-(MAX($H23,(EDATE(AE$3,-12)+1)))+1)/(AE$3-(EDATE(AE$3,-12)+1)+1)))*$W23),MAX(0,AD23-$M23))) | AF23: =IF($K23="","",IF(AND($I23<>"",$I23<=AE$3),0,AD23-AE23)) | AG23: =IF(OR($K23="",$H23=""),"",MIN(MAX(0,IF($O23="WDV",AF23*$P23*MAX(0,(IF($I23="",AG$3,MIN($I23,AG$3)))-(MAX($H23,(EDATE(AG$3,-12)+1)))+1)/(AG$3-(EDATE(AG$3,-12)+1)+1),IF($N23=0,0,$Q23/$N23*MAX(0,(IF($I23="",AG$3,MIN($I23,AG$3)))-(MAX($H23,(EDATE(AG$3,-12)+1)))+1)/(AG$3-(EDATE(AG$3,-12)+1)+1)))*$W23),MAX(0,AF23-$M23))) | AH23: =IF($K23="","",IF(AND($I23<>"",$I23<=AG$3),0,AF23-AG23)) | AI23: =IF(OR($K23="",$H23=""),"",MIN(MAX(0,IF($O23="WDV",AH23*$P23*MAX(0,(IF($I23="",AI$3,MIN($I23,AI$3)))-(MAX($H23,(EDATE(AI$3,-12)+1)))+1)/(AI$3-(EDATE(AI$3,-12)+1)+1),IF($N23=0,0,$Q23/$N23*MAX(0,(IF($I23="",AI$3,MIN($I23,AI$3)))-(MAX($H23,(EDATE(AI$3,-12)+1)))+1)/(AI$3-(EDATE(AI$3,-12)+1)+1)))*$W23),MAX(0,AH23-$M23))) | AJ23: =IF($K23="","",IF(AND($I23<>"",$I23<=AI$3),0,AH23-AI23)) | AK23: =IF(OR($K23="",$H23=""),"",MIN(MAX(0,IF($O23="WDV",AJ23*$P23*MAX(0,(IF($I23="",AK$3,MIN($I23,AK$3)))-(MAX($H23,(EDATE(AK$3,-12)+1)))+1)/(AK$3-(EDATE(AK$3,-12)+1)+1),IF($N23=0,0,$Q23/$N23*MAX(0,(IF($I23="",AK$3,MIN($I23,AK$3)))-(MAX($H23,(EDATE(AK$3,-12)+1)))+1)/(AK$3-(EDATE(AK$3,-12)+1)+1)))*$W23),MAX(0,AJ23-$M23))) | AL23: =IF($K23="","",IF(AND($I23<>"",$I23<=AK$3),0,AJ23-AK23)) | AM23: =IF(OR($K23="",$H23=""),"",MIN(MAX(0,IF($O23="WDV",AL23*$P23*MAX(0,(IF($I23="",AM$3,MIN($I23,AM$3)))-(MAX($H23,(EDATE(AM$3,-12)+1)))+1)/(AM$3-(EDATE(AM$3,-12)+1)+1),IF($N23=0,0,$Q23/$N23*MAX(0,(IF($I23="",AM$3,MIN($I23,AM$3)))-(MAX($H23,(EDATE(AM$3,-12)+1)))+1)/(AM$3-(EDATE(AM$3,-12)+1)+1)))*$W23),MAX(0,AL23-$M23))) | AN23: =IF($K23="","",IF(AND($I23<>"",$I23<=AM$3),0,AL23-AM23)) | AO23: =IF(OR($K23="",$H23=""),"",MIN(MAX(0,IF($O23="WDV",AN23*$P23*MAX(0,(IF($I23="",AO$3,MIN($I23,AO$3)))-(MAX($H23,(EDATE(AO$3,-12)+1)))+1)/(AO$3-(EDATE(AO$3,-12)+1)+1),IF($N23=0,0,$Q23/$N23*MAX(0,(IF($I23="",AO$3,MIN($I23,AO$3)))-(MAX($H23,(EDATE(AO$3,-12)+1)))+1)/(AO$3-(EDATE(AO$3,-12)+1)+1)))*$W23),MAX(0,AN23-$M23))) | AP23: =IF($K23="","",IF(AND($I23<>"",$I23<=AO$3),0,AN23-AO23)) | AQ23: =IF(OR($K23="",$H23=""),"",MIN(MAX(0,IF($O23="WDV",AP23*$P23*MAX(0,(IF($I23="",AQ$3,MIN($I23,AQ$3)))-(MAX($H23,(EDATE(AQ$3,-12)+1)))+1)/(AQ$3-(EDATE(AQ$3,-12)+1)+1),IF($N23=0,0,$Q23/$N23*MAX(0,(IF($I23="",AQ$3,MIN($I23,AQ$3)))-(MAX($H23,(EDATE(AQ$3,-12)+1)))+1)/(AQ$3-(EDATE(AQ$3,-12)+1)+1)))*$W23),MAX(0,AP23-$M23))) | AR23: =IF($K23="","",IF(AND($I23<>"",$I23<=AQ$3),0,AP23-AQ23)) | AS23: =IF(OR($K23="",$H23=""),"",MIN(MAX(0,IF($O23="WDV",AR23*$P23*MAX(0,(IF($I23="",AS$3,MIN($I23,AS$3)))-(MAX($H23,(EDATE(AS$3,-12)+1)))+1)/(AS$3-(EDATE(AS$3,-12)+1)+1),IF($N23=0,0,$Q23/$N23*MAX(0,(IF($I23="",AS$3,MIN($I23,AS$3)))-(MAX($H23,(EDATE(AS$3,-12)+1)))+1)/(AS$3-(EDATE(AS$3,-12)+1)+1)))*$W23),MAX(0,AR23-$M23))) | AT23: =IF($K23="","",IF(AND($I23<>"",$I23<=AS$3),0,AR23-AS23)) | AU23: =IF(OR($K23="",$H23=""),"",MIN(MAX(0,IF($O23="WDV",AT23*$P23*MAX(0,(IF($I23="",AU$3,MIN($I23,AU$3)))-(MAX($H23,(EDATE(AU$3,-12)+1)))+1)/(AU$3-(EDATE(AU$3,-12)+1)+1),IF($N23=0,0,$Q23/$N23*MAX(0,(IF($I23="",AU$3,MIN($I23,AU$3)))-(MAX($H23,(EDATE(AU$3,-12)+1)))+1)/(AU$3-(EDATE(AU$3,-12)+1)+1)))*$W23),MAX(0,AT23-$M23))) | AV23: =IF($K23="","",IF(AND($I23<>"",$I23<=AU$3),0,AT23-AU23)) | AW23: =IF(OR($K23="",$H23=""),"",MIN(MAX(0,IF($O23="WDV",AV23*$P23*MAX(0,(IF($I23="",AW$3,MIN($I23,AW$3)))-(MAX($H23,(EDATE(AW$3,-12)+1)))+1)/(AW$3-(EDATE(AW$3,-12)+1)+1),IF($N23=0,0,$Q23/$N23*MAX(0,(IF($I23="",AW$3,MIN($I23,AW$3)))-(MAX($H23,(EDATE(AW$3,-12)+1)))+1)/(AW$3-(EDATE(AW$3,-12)+1)+1)))*$W23),MAX(0,AV23-$M23))) | AX23: =IF($K23="","",IF(AND($I23<>"",$I23<=AW$3),0,AV23-AW23)) | AY23: =IF(OR($K23="",$H23=""),"",MIN(MAX(0,IF($O23="WDV",AX23*$P23*MAX(0,(IF($I23="",AY$3,MIN($I23,AY$3)))-(MAX($H23,(EDATE(AY$3,-12)+1)))+1)/(AY$3-(EDATE(AY$3,-12)+1)+1),IF($N23=0,0,$Q23/$N23*MAX(0,(IF($I23="",AY$3,MIN($I23,AY$3)))-(MAX($H23,(EDATE(AY$3,-12)+1)))+1)/(AY$3-(EDATE(AY$3,-12)+1)+1)))*$W23),MAX(0,AX23-$M23))) | AZ23: =IF($K23="","",IF(AND($I23<>"",$I23<=AY$3),0,AX23-AY23)) | BA23: =IF(OR($K23="",$H23=""),"",MIN(MAX(0,IF($O23="WDV",AZ23*$P23*MAX(0,(IF($I23="",BA$3,MIN($I23,BA$3)))-(MAX($H23,(EDATE(BA$3,-12)+1)))+1)/(BA$3-(EDATE(BA$3,-12)+1)+1),IF($N23=0,0,$Q23/$N23*MAX(0,(IF($I23="",BA$3,MIN($I23,BA$3)))-(MAX($H23,(EDATE(BA$3,-12)+1)))+1)/(BA$3-(EDATE(BA$3,-12)+1)+1)))*$W23),MAX(0,AZ23-$M23))) | BB23: =IF($K23="","",IF(AND($I23<>"",$I23<=BA$3),0,AZ23-BA23)) | BC23: =IF(OR($K23="",$H23=""),"",MIN(MAX(0,IF($O23="WDV",BB23*$P23*MAX(0,(IF($I23="",BC$3,MIN($I23,BC$3)))-(MAX($H23,(EDATE(BC$3,-12)+1)))+1)/(BC$3-(EDATE(BC$3,-12)+1)+1),IF($N23=0,0,$Q23/$N23*MAX(0,(IF($I23="",BC$3,MIN($I23,BC$3)))-(MAX($H23,(EDATE(BC$3,-12)+1)))+1)/(BC$3-(EDATE(BC$3,-12)+1)+1)))*$W23),MAX(0,BB23-$M23))) | BD23: =IF($K23="","",IF(AND($I23<>"",$I23<=BC$3),0,BB23-BC23)) | BE23: =IF(OR($K23="",$H23=""),"",MIN(MAX(0,IF($O23="WDV",BD23*$P23*MAX(0,(IF($I23="",BE$3,MIN($I23,BE$3)))-(MAX($H23,(EDATE(BE$3,-12)+1)))+1)/(BE$3-(EDATE(BE$3,-12)+1)+1),IF($N23=0,0,$Q23/$N23*MAX(0,(IF($I23="",BE$3,MIN($I23,BE$3)))-(MAX($H23,(EDATE(BE$3,-12)+1)))+1)/(BE$3-(EDATE(BE$3,-12)+1)+1)))*$W23),MAX(0,BD23-$M23))) | BF23: =IF($K23="","",IF(AND($I23<>"",$I23<=BE$3),0,BD23-BE23))
L24: =DefaultResidual | M24: =IF($K24="","",$K24*$L24) | N24: =IF($C24="","",IFERROR(VLOOKUP($C24,ScheduleIITable,3,FALSE),"#N/A")) | O24: =IF($K24="","",GlobalMethod) | P24: =IF(OR($K24="",$N24="",$N24=0,$M24=0),0,1-($M24/$K24)^(1/$N24)) | Q24: =IF($K24="","",$K24-$M24) | R24: =IF($K24="","",INDEX($AA24:$BF24,1,MATCH(ReportingFYEnd,$AA$3:$BF$3,0))) | S24: =IF($K24="","",IF($U24="Disposed",0,$K24-$T24)) | T24: =IF($K24="","",INDEX($AA24:$BF24,1,MATCH(ReportingFYEnd,$AA$3:$BF$3,0)+1)) | U24: =IF($K24="","",IF(AND($I24<>"",$I24<=ReportingFYEnd),"Disposed",IF(OR($H24="",$H24>ReportingFYEnd),"Not Yet in Use","Active"))) | W24: =IF($V24="Double",1.5,IF($V24="Triple",2,1)) | Y24: =IF($K24="","",IF(OR(ISNUMBER(SEARCH("Build",$C24)),ISNUMBER(SEARCH("Lease",$C24))),"Yes","NA")) | AA24: =IF(OR($K24="",$H24=""),"",MIN(MAX(0,IF($O24="WDV",$K24*$P24*MAX(0,(IF($I24="",AA$3,MIN($I24,AA$3)))-(MAX($H24,(EDATE(AA$3,-12)+1)))+1)/(AA$3-(EDATE(AA$3,-12)+1)+1),IF($N24=0,0,$Q24/$N24*MAX(0,(IF($I24="",AA$3,MIN($I24,AA$3)))-(MAX($H24,(EDATE(AA$3,-12)+1)))+1)/(AA$3-(EDATE(AA$3,-12)+1)+1)))*$W24),MAX(0,$K24-$M24))) | AB24: =IF($K24="","",IF(AND($I24<>"",$I24<=AA$3),0,$K24-AA24)) | AC24: =IF(OR($K24="",$H24=""),"",MIN(MAX(0,IF($O24="WDV",AB24*$P24*MAX(0,(IF($I24="",AC$3,MIN($I24,AC$3)))-(MAX($H24,(EDATE(AC$3,-12)+1)))+1)/(AC$3-(EDATE(AC$3,-12)+1)+1),IF($N24=0,0,$Q24/$N24*MAX(0,(IF($I24="",AC$3,MIN($I24,AC$3)))-(MAX($H24,(EDATE(AC$3,-12)+1)))+1)/(AC$3-(EDATE(AC$3,-12)+1)+1)))*$W24),MAX(0,AB24-$M24))) | AD24: =IF($K24="","",IF(AND($I24<>"",$I24<=AC$3),0,AB24-AC24)) | AE24: =IF(OR($K24="",$H24=""),"",MIN(MAX(0,IF($O24="WDV",AD24*$P24*MAX(0,(IF($I24="",AE$3,MIN($I24,AE$3)))-(MAX($H24,(EDATE(AE$3,-12)+1)))+1)/(AE$3-(EDATE(AE$3,-12)+1)+1),IF($N24=0,0,$Q24/$N24*MAX(0,(IF($I24="",AE$3,MIN($I24,AE$3)))-(MAX($H24,(EDATE(AE$3,-12)+1)))+1)/(AE$3-(EDATE(AE$3,-12)+1)+1)))*$W24),MAX(0,AD24-$M24))) | AF24: =IF($K24="","",IF(AND($I24<>"",$I24<=AE$3),0,AD24-AE24)) | AG24: =IF(OR($K24="",$H24=""),"",MIN(MAX(0,IF($O24="WDV",AF24*$P24*MAX(0,(IF($I24="",AG$3,MIN($I24,AG$3)))-(MAX($H24,(EDATE(AG$3,-12)+1)))+1)/(AG$3-(EDATE(AG$3,-12)+1)+1),IF($N24=0,0,$Q24/$N24*MAX(0,(IF($I24="",AG$3,MIN($I24,AG$3)))-(MAX($H24,(EDATE(AG$3,-12)+1)))+1)/(AG$3-(EDATE(AG$3,-12)+1)+1)))*$W24),MAX(0,AF24-$M24))) | AH24: =IF($K24="","",IF(AND($I24<>"",$I24<=AG$3),0,AF24-AG24)) | AI24: =IF(OR($K24="",$H24=""),"",MIN(MAX(0,IF($O24="WDV",AH24*$P24*MAX(0,(IF($I24="",AI$3,MIN($I24,AI$3)))-(MAX($H24,(EDATE(AI$3,-12)+1)))+1)/(AI$3-(EDATE(AI$3,-12)+1)+1),IF($N24=0,0,$Q24/$N24*MAX(0,(IF($I24="",AI$3,MIN($I24,AI$3)))-(MAX($H24,(EDATE(AI$3,-12)+1)))+1)/(AI$3-(EDATE(AI$3,-12)+1)+1)))*$W24),MAX(0,AH24-$M24))) | AJ24: =IF($K24="","",IF(AND($I24<>"",$I24<=AI$3),0,AH24-AI24)) | AK24: =IF(OR($K24="",$H24=""),"",MIN(MAX(0,IF($O24="WDV",AJ24*$P24*MAX(0,(IF($I24="",AK$3,MIN($I24,AK$3)))-(MAX($H24,(EDATE(AK$3,-12)+1)))+1)/(AK$3-(EDATE(AK$3,-12)+1)+1),IF($N24=0,0,$Q24/$N24*MAX(0,(IF($I24="",AK$3,MIN($I24,AK$3)))-(MAX($H24,(EDATE(AK$3,-12)+1)))+1)/(AK$3-(EDATE(AK$3,-12)+1)+1)))*$W24),MAX(0,AJ24-$M24))) | AL24: =IF($K24="","",IF(AND($I24<>"",$I24<=AK$3),0,AJ24-AK24)) | AM24: =IF(OR($K24="",$H24=""),"",MIN(MAX(0,IF($O24="WDV",AL24*$P24*MAX(0,(IF($I24="",AM$3,MIN($I24,AM$3)))-(MAX($H24,(EDATE(AM$3,-12)+1)))+1)/(AM$3-(EDATE(AM$3,-12)+1)+1),IF($N24=0,0,$Q24/$N24*MAX(0,(IF($I24="",AM$3,MIN($I24,AM$3)))-(MAX($H24,(EDATE(AM$3,-12)+1)))+1)/(AM$3-(EDATE(AM$3,-12)+1)+1)))*$W24),MAX(0,AL24-$M24))) | AN24: =IF($K24="","",IF(AND($I24<>"",$I24<=AM$3),0,AL24-AM24)) | AO24: =IF(OR($K24="",$H24=""),"",MIN(MAX(0,IF($O24="WDV",AN24*$P24*MAX(0,(IF($I24="",AO$3,MIN($I24,AO$3)))-(MAX($H24,(EDATE(AO$3,-12)+1)))+1)/(AO$3-(EDATE(AO$3,-12)+1)+1),IF($N24=0,0,$Q24/$N24*MAX(0,(IF($I24="",AO$3,MIN($I24,AO$3)))-(MAX($H24,(EDATE(AO$3,-12)+1)))+1)/(AO$3-(EDATE(AO$3,-12)+1)+1)))*$W24),MAX(0,AN24-$M24))) | AP24: =IF($K24="","",IF(AND($I24<>"",$I24<=AO$3),0,AN24-AO24)) | AQ24: =IF(OR($K24="",$H24=""),"",MIN(MAX(0,IF($O24="WDV",AP24*$P24*MAX(0,(IF($I24="",AQ$3,MIN($I24,AQ$3)))-(MAX($H24,(EDATE(AQ$3,-12)+1)))+1)/(AQ$3-(EDATE(AQ$3,-12)+1)+1),IF($N24=0,0,$Q24/$N24*MAX(0,(IF($I24="",AQ$3,MIN($I24,AQ$3)))-(MAX($H24,(EDATE(AQ$3,-12)+1)))+1)/(AQ$3-(EDATE(AQ$3,-12)+1)+1)))*$W24),MAX(0,AP24-$M24))) | AR24: =IF($K24="","",IF(AND($I24<>"",$I24<=AQ$3),0,AP24-AQ24)) | AS24: =IF(OR($K24="",$H24=""),"",MIN(MAX(0,IF($O24="WDV",AR24*$P24*MAX(0,(IF($I24="",AS$3,MIN($I24,AS$3)))-(MAX($H24,(EDATE(AS$3,-12)+1)))+1)/(AS$3-(EDATE(AS$3,-12)+1)+1),IF($N24=0,0,$Q24/$N24*MAX(0,(IF($I24="",AS$3,MIN($I24,AS$3)))-(MAX($H24,(EDATE(AS$3,-12)+1)))+1)/(AS$3-(EDATE(AS$3,-12)+1)+1)))*$W24),MAX(0,AR24-$M24))) | AT24: =IF($K24="","",IF(AND($I24<>"",$I24<=AS$3),0,AR24-AS24)) | AU24: =IF(OR($K24="",$H24=""),"",MIN(MAX(0,IF($O24="WDV",AT24*$P24*MAX(0,(IF($I24="",AU$3,MIN($I24,AU$3)))-(MAX($H24,(EDATE(AU$3,-12)+1)))+1)/(AU$3-(EDATE(AU$3,-12)+1)+1),IF($N24=0,0,$Q24/$N24*MAX(0,(IF($I24="",AU$3,MIN($I24,AU$3)))-(MAX($H24,(EDATE(AU$3,-12)+1)))+1)/(AU$3-(EDATE(AU$3,-12)+1)+1)))*$W24),MAX(0,AT24-$M24))) | AV24: =IF($K24="","",IF(AND($I24<>"",$I24<=AU$3),0,AT24-AU24)) | AW24: =IF(OR($K24="",$H24=""),"",MIN(MAX(0,IF($O24="WDV",AV24*$P24*MAX(0,(IF($I24="",AW$3,MIN($I24,AW$3)))-(MAX($H24,(EDATE(AW$3,-12)+1)))+1)/(AW$3-(EDATE(AW$3,-12)+1)+1),IF($N24=0,0,$Q24/$N24*MAX(0,(IF($I24="",AW$3,MIN($I24,AW$3)))-(MAX($H24,(EDATE(AW$3,-12)+1)))+1)/(AW$3-(EDATE(AW$3,-12)+1)+1)))*$W24),MAX(0,AV24-$M24))) | AX24: =IF($K24="","",IF(AND($I24<>"",$I24<=AW$3),0,AV24-AW24)) | AY24: =IF(OR($K24="",$H24=""),"",MIN(MAX(0,IF($O24="WDV",AX24*$P24*MAX(0,(IF($I24="",AY$3,MIN($I24,AY$3)))-(MAX($H24,(EDATE(AY$3,-12)+1)))+1)/(AY$3-(EDATE(AY$3,-12)+1)+1),IF($N24=0,0,$Q24/$N24*MAX(0,(IF($I24="",AY$3,MIN($I24,AY$3)))-(MAX($H24,(EDATE(AY$3,-12)+1)))+1)/(AY$3-(EDATE(AY$3,-12)+1)+1)))*$W24),MAX(0,AX24-$M24))) | AZ24: =IF($K24="","",IF(AND($I24<>"",$I24<=AY$3),0,AX24-AY24)) | BA24: =IF(OR($K24="",$H24=""),"",MIN(MAX(0,IF($O24="WDV",AZ24*$P24*MAX(0,(IF($I24="",BA$3,MIN($I24,BA$3)))-(MAX($H24,(EDATE(BA$3,-12)+1)))+1)/(BA$3-(EDATE(BA$3,-12)+1)+1),IF($N24=0,0,$Q24/$N24*MAX(0,(IF($I24="",BA$3,MIN($I24,BA$3)))-(MAX($H24,(EDATE(BA$3,-12)+1)))+1)/(BA$3-(EDATE(BA$3,-12)+1)+1)))*$W24),MAX(0,AZ24-$M24))) | BB24: =IF($K24="","",IF(AND($I24<>"",$I24<=BA$3),0,AZ24-BA24)) | BC24: =IF(OR($K24="",$H24=""),"",MIN(MAX(0,IF($O24="WDV",BB24*$P24*MAX(0,(IF($I24="",BC$3,MIN($I24,BC$3)))-(MAX($H24,(EDATE(BC$3,-12)+1)))+1)/(BC$3-(EDATE(BC$3,-12)+1)+1),IF($N24=0,0,$Q24/$N24*MAX(0,(IF($I24="",BC$3,MIN($I24,BC$3)))-(MAX($H24,(EDATE(BC$3,-12)+1)))+1)/(BC$3-(EDATE(BC$3,-12)+1)+1)))*$W24),MAX(0,BB24-$M24))) | BD24: =IF($K24="","",IF(AND($I24<>"",$I24<=BC$3),0,BB24-BC24)) | BE24: =IF(OR($K24="",$H24=""),"",MIN(MAX(0,IF($O24="WDV",BD24*$P24*MAX(0,(IF($I24="",BE$3,MIN($I24,BE$3)))-(MAX($H24,(EDATE(BE$3,-12)+1)))+1)/(BE$3-(EDATE(BE$3,-12)+1)+1),IF($N24=0,0,$Q24/$N24*MAX(0,(IF($I24="",BE$3,MIN($I24,BE$3)))-(MAX($H24,(EDATE(BE$3,-12)+1)))+1)/(BE$3-(EDATE(BE$3,-12)+1)+1)))*$W24),MAX(0,BD24-$M24))) | BF24: =IF($K24="","",IF(AND($I24<>"",$I24<=BE$3),0,BD24-BE24))
L25: =DefaultResidual | M25: =IF($K25="","",$K25*$L25) | N25: =IF($C25="","",IFERROR(VLOOKUP($C25,ScheduleIITable,3,FALSE),"#N/A")) | O25: =IF($K25="","",GlobalMethod) | P25: =IF(OR($K25="",$N25="",$N25=0,$M25=0),0,1-($M25/$K25)^(1/$N25)) | Q25: =IF($K25="","",$K25-$M25) | R25: =IF($K25="","",INDEX($AA25:$BF25,1,MATCH(ReportingFYEnd,$AA$3:$BF$3,0))) | S25: =IF($K25="","",IF($U25="Disposed",0,$K25-$T25)) | T25: =IF($K25="","",INDEX($AA25:$BF25,1,MATCH(ReportingFYEnd,$AA$3:$BF$3,0)+1)) | U25: =IF($K25="","",IF(AND($I25<>"",$I25<=ReportingFYEnd),"Disposed",IF(OR($H25="",$H25>ReportingFYEnd),"Not Yet in Use","Active"))) | W25: =IF($V25="Double",1.5,IF($V25="Triple",2,1)) | Y25: =IF($K25="","",IF(OR(ISNUMBER(SEARCH("Build",$C25)),ISNUMBER(SEARCH("Lease",$C25))),"Yes","NA")) | AA25: =IF(OR($K25="",$H25=""),"",MIN(MAX(0,IF($O25="WDV",$K25*$P25*MAX(0,(IF($I25="",AA$3,MIN($I25,AA$3)))-(MAX($H25,(EDATE(AA$3,-12)+1)))+1)/(AA$3-(EDATE(AA$3,-12)+1)+1),IF($N25=0,0,$Q25/$N25*MAX(0,(IF($I25="",AA$3,MIN($I25,AA$3)))-(MAX($H25,(EDATE(AA$3,-12)+1)))+1)/(AA$3-(EDATE(AA$3,-12)+1)+1)))*$W25),MAX(0,$K25-$M25))) | AB25: =IF($K25="","",IF(AND($I25<>"",$I25<=AA$3),0,$K25-AA25)) | AC25: =IF(OR($K25="",$H25=""),"",MIN(MAX(0,IF($O25="WDV",AB25*$P25*MAX(0,(IF($I25="",AC$3,MIN($I25,AC$3)))-(MAX($H25,(EDATE(AC$3,-12)+1)))+1)/(AC$3-(EDATE(AC$3,-12)+1)+1),IF($N25=0,0,$Q25/$N25*MAX(0,(IF($I25="",AC$3,MIN($I25,AC$3)))-(MAX($H25,(EDATE(AC$3,-12)+1)))+1)/(AC$3-(EDATE(AC$3,-12)+1)+1)))*$W25),MAX(0,AB25-$M25))) | AD25: =IF($K25="","",IF(AND($I25<>"",$I25<=AC$3),0,AB25-AC25)) | AE25: =IF(OR($K25="",$H25=""),"",MIN(MAX(0,IF($O25="WDV",AD25*$P25*MAX(0,(IF($I25="",AE$3,MIN($I25,AE$3)))-(MAX($H25,(EDATE(AE$3,-12)+1)))+1)/(AE$3-(EDATE(AE$3,-12)+1)+1),IF($N25=0,0,$Q25/$N25*MAX(0,(IF($I25="",AE$3,MIN($I25,AE$3)))-(MAX($H25,(EDATE(AE$3,-12)+1)))+1)/(AE$3-(EDATE(AE$3,-12)+1)+1)))*$W25),MAX(0,AD25-$M25))) | AF25: =IF($K25="","",IF(AND($I25<>"",$I25<=AE$3),0,AD25-AE25)) | AG25: =IF(OR($K25="",$H25=""),"",MIN(MAX(0,IF($O25="WDV",AF25*$P25*MAX(0,(IF($I25="",AG$3,MIN($I25,AG$3)))-(MAX($H25,(EDATE(AG$3,-12)+1)))+1)/(AG$3-(EDATE(AG$3,-12)+1)+1),IF($N25=0,0,$Q25/$N25*MAX(0,(IF($I25="",AG$3,MIN($I25,AG$3)))-(MAX($H25,(EDATE(AG$3,-12)+1)))+1)/(AG$3-(EDATE(AG$3,-12)+1)+1)))*$W25),MAX(0,AF25-$M25))) | AH25: =IF($K25="","",IF(AND($I25<>"",$I25<=AG$3),0,AF25-AG25)) | AI25: =IF(OR($K25="",$H25=""),"",MIN(MAX(0,IF($O25="WDV",AH25*$P25*MAX(0,(IF($I25="",AI$3,MIN($I25,AI$3)))-(MAX($H25,(EDATE(AI$3,-12)+1)))+1)/(AI$3-(EDATE(AI$3,-12)+1)+1),IF($N25=0,0,$Q25/$N25*MAX(0,(IF($I25="",AI$3,MIN($I25,AI$3)))-(MAX($H25,(EDATE(AI$3,-12)+1)))+1)/(AI$3-(EDATE(AI$3,-12)+1)+1)))*$W25),MAX(0,AH25-$M25))) | AJ25: =IF($K25="","",IF(AND($I25<>"",$I25<=AI$3),0,AH25-AI25)) | AK25: =IF(OR($K25="",$H25=""),"",MIN(MAX(0,IF($O25="WDV",AJ25*$P25*MAX(0,(IF($I25="",AK$3,MIN($I25,AK$3)))-(MAX($H25,(EDATE(AK$3,-12)+1)))+1)/(AK$3-(EDATE(AK$3,-12)+1)+1),IF($N25=0,0,$Q25/$N25*MAX(0,(IF($I25="",AK$3,MIN($I25,AK$3)))-(MAX($H25,(EDATE(AK$3,-12)+1)))+1)/(AK$3-(EDATE(AK$3,-12)+1)+1)))*$W25),MAX(0,AJ25-$M25))) | AL25: =IF($K25="","",IF(AND($I25<>"",$I25<=AK$3),0,AJ25-AK25)) | AM25: =IF(OR($K25="",$H25=""),"",MIN(MAX(0,IF($O25="WDV",AL25*$P25*MAX(0,(IF($I25="",AM$3,MIN($I25,AM$3)))-(MAX($H25,(EDATE(AM$3,-12)+1)))+1)/(AM$3-(EDATE(AM$3,-12)+1)+1),IF($N25=0,0,$Q25/$N25*MAX(0,(IF($I25="",AM$3,MIN($I25,AM$3)))-(MAX($H25,(EDATE(AM$3,-12)+1)))+1)/(AM$3-(EDATE(AM$3,-12)+1)+1)))*$W25),MAX(0,AL25-$M25))) | AN25: =IF($K25="","",IF(AND($I25<>"",$I25<=AM$3),0,AL25-AM25)) | AO25: =IF(OR($K25="",$H25=""),"",MIN(MAX(0,IF($O25="WDV",AN25*$P25*MAX(0,(IF($I25="",AO$3,MIN($I25,AO$3)))-(MAX($H25,(EDATE(AO$3,-12)+1)))+1)/(AO$3-(EDATE(AO$3,-12)+1)+1),IF($N25=0,0,$Q25/$N25*MAX(0,(IF($I25="",AO$3,MIN($I25,AO$3)))-(MAX($H25,(EDATE(AO$3,-12)+1)))+1)/(AO$3-(EDATE(AO$3,-12)+1)+1)))*$W25),MAX(0,AN25-$M25))) | AP25: =IF($K25="","",IF(AND($I25<>"",$I25<=AO$3),0,AN25-AO25)) | AQ25: =IF(OR($K25="",$H25=""),"",MIN(MAX(0,IF($O25="WDV",AP25*$P25*MAX(0,(IF($I25="",AQ$3,MIN($I25,AQ$3)))-(MAX($H25,(EDATE(AQ$3,-12)+1)))+1)/(AQ$3-(EDATE(AQ$3,-12)+1)+1),IF($N25=0,0,$Q25/$N25*MAX(0,(IF($I25="",AQ$3,MIN($I25,AQ$3)))-(MAX($H25,(EDATE(AQ$3,-12)+1)))+1)/(AQ$3-(EDATE(AQ$3,-12)+1)+1)))*$W25),MAX(0,AP25-$M25))) | AR25: =IF($K25="","",IF(AND($I25<>"",$I25<=AQ$3),0,AP25-AQ25)) | AS25: =IF(OR($K25="",$H25=""),"",MIN(MAX(0,IF($O25="WDV",AR25*$P25*MAX(0,(IF($I25="",AS$3,MIN($I25,AS$3)))-(MAX($H25,(EDATE(AS$3,-12)+1)))+1)/(AS$3-(EDATE(AS$3,-12)+1)+1),IF($N25=0,0,$Q25/$N25*MAX(0,(IF($I25="",AS$3,MIN($I25,AS$3)))-(MAX($H25,(EDATE(AS$3,-12)+1)))+1)/(AS$3-(EDATE(AS$3,-12)+1)+1)))*$W25),MAX(0,AR25-$M25))) | AT25: =IF($K25="","",IF(AND($I25<>"",$I25<=AS$3),0,AR25-AS25)) | AU25: =IF(OR($K25="",$H25=""),"",MIN(MAX(0,IF($O25="WDV",AT25*$P25*MAX(0,(IF($I25="",AU$3,MIN($I25,AU$3)))-(MAX($H25,(EDATE(AU$3,-12)+1)))+1)/(AU$3-(EDATE(AU$3,-12)+1)+1),IF($N25=0,0,$Q25/$N25*MAX(0,(IF($I25="",AU$3,MIN($I25,AU$3)))-(MAX($H25,(EDATE(AU$3,-12)+1)))+1)/(AU$3-(EDATE(AU$3,-12)+1)+1)))*$W25),MAX(0,AT25-$M25))) | AV25: =IF($K25="","",IF(AND($I25<>"",$I25<=AU$3),0,AT25-AU25)) | AW25: =IF(OR($K25="",$H25=""),"",MIN(MAX(0,IF($O25="WDV",AV25*$P25*MAX(0,(IF($I25="",AW$3,MIN($I25,AW$3)))-(MAX($H25,(EDATE(AW$3,-12)+1)))+1)/(AW$3-(EDATE(AW$3,-12)+1)+1),IF($N25=0,0,$Q25/$N25*MAX(0,(IF($I25="",AW$3,MIN($I25,AW$3)))-(MAX($H25,(EDATE(AW$3,-12)+1)))+1)/(AW$3-(EDATE(AW$3,-12)+1)+1)))*$W25),MAX(0,AV25-$M25))) | AX25: =IF($K25="","",IF(AND($I25<>"",$I25<=AW$3),0,AV25-AW25)) | AY25: =IF(OR($K25="",$H25=""),"",MIN(MAX(0,IF($O25="WDV",AX25*$P25*MAX(0,(IF($I25="",AY$3,MIN($I25,AY$3)))-(MAX($H25,(EDATE(AY$3,-12)+1)))+1)/(AY$3-(EDATE(AY$3,-12)+1)+1),IF($N25=0,0,$Q25/$N25*MAX(0,(IF($I25="",AY$3,MIN($I25,AY$3)))-(MAX($H25,(EDATE(AY$3,-12)+1)))+1)/(AY$3-(EDATE(AY$3,-12)+1)+1)))*$W25),MAX(0,AX25-$M25))) | AZ25: =IF($K25="","",IF(AND($I25<>"",$I25<=AY$3),0,AX25-AY25)) | BA25: =IF(OR($K25="",$H25=""),"",MIN(MAX(0,IF($O25="WDV",AZ25*$P25*MAX(0,(IF($I25="",BA$3,MIN($I25,BA$3)))-(MAX($H25,(EDATE(BA$3,-12)+1)))+1)/(BA$3-(EDATE(BA$3,-12)+1)+1),IF($N25=0,0,$Q25/$N25*MAX(0,(IF($I25="",BA$3,MIN($I25,BA$3)))-(MAX($H25,(EDATE(BA$3,-12)+1)))+1)/(BA$3-(EDATE(BA$3,-12)+1)+1)))*$W25),MAX(0,AZ25-$M25))) | BB25: =IF($K25="","",IF(AND($I25<>"",$I25<=BA$3),0,AZ25-BA25)) | BC25: =IF(OR($K25="",$H25=""),"",MIN(MAX(0,IF($O25="WDV",BB25*$P25*MAX(0,(IF($I25="",BC$3,MIN($I25,BC$3)))-(MAX($H25,(EDATE(BC$3,-12)+1)))+1)/(BC$3-(EDATE(BC$3,-12)+1)+1),IF($N25=0,0,$Q25/$N25*MAX(0,(IF($I25="",BC$3,MIN($I25,BC$3)))-(MAX($H25,(EDATE(BC$3,-12)+1)))+1)/(BC$3-(EDATE(BC$3,-12)+1)+1)))*$W25),MAX(0,BB25-$M25))) | BD25: =IF($K25="","",IF(AND($I25<>"",$I25<=BC$3),0,BB25-BC25)) | BE25: =IF(OR($K25="",$H25=""),"",MIN(MAX(0,IF($O25="WDV",BD25*$P25*MAX(0,(IF($I25="",BE$3,MIN($I25,BE$3)))-(MAX($H25,(EDATE(BE$3,-12)+1)))+1)/(BE$3-(EDATE(BE$3,-12)+1)+1),IF($N25=0,0,$Q25/$N25*MAX(0,(IF($I25="",BE$3,MIN($I25,BE$3)))-(MAX($H25,(EDATE(BE$3,-12)+1)))+1)/(BE$3-(EDATE(BE$3,-12)+1)+1)))*$W25),MAX(0,BD25-$M25))) | BF25: =IF($K25="","",IF(AND($I25<>"",$I25<=BE$3),0,BD25-BE25))
L26: =DefaultResidual | M26: =IF($K26="","",$K26*$L26) | N26: =IF($C26="","",IFERROR(VLOOKUP($C26,ScheduleIITable,3,FALSE),"#N/A")) | O26: =IF($K26="","",GlobalMethod) | P26: =IF(OR($K26="",$N26="",$N26=0,$M26=0),0,1-($M26/$K26)^(1/$N26)) | Q26: =IF($K26="","",$K26-$M26) | R26: =IF($K26="","",INDEX($AA26:$BF26,1,MATCH(ReportingFYEnd,$AA$3:$BF$3,0))) | S26: =IF($K26="","",IF($U26="Disposed",0,$K26-$T26)) | T26: =IF($K26="","",INDEX($AA26:$BF26,1,MATCH(ReportingFYEnd,$AA$3:$BF$3,0)+1)) | U26: =IF($K26="","",IF(AND($I26<>"",$I26<=ReportingFYEnd),"Disposed",IF(OR($H26="",$H26>ReportingFYEnd),"Not Yet in Use","Active"))) | W26: =IF($V26="Double",1.5,IF($V26="Triple",2,1)) | Y26: =IF($K26="","",IF(OR(ISNUMBER(SEARCH("Build",$C26)),ISNUMBER(SEARCH("Lease",$C26))),"Yes","NA")) | AA26: =IF(OR($K26="",$H26=""),"",MIN(MAX(0,IF($O26="WDV",$K26*$P26*MAX(0,(IF($I26="",AA$3,MIN($I26,AA$3)))-(MAX($H26,(EDATE(AA$3,-12)+1)))+1)/(AA$3-(EDATE(AA$3,-12)+1)+1),IF($N26=0,0,$Q26/$N26*MAX(0,(IF($I26="",AA$3,MIN($I26,AA$3)))-(MAX($H26,(EDATE(AA$3,-12)+1)))+1)/(AA$3-(EDATE(AA$3,-12)+1)+1)))*$W26),MAX(0,$K26-$M26))) | AB26: =IF($K26="","",IF(AND($I26<>"",$I26<=AA$3),0,$K26-AA26)) | AC26: =IF(OR($K26="",$H26=""),"",MIN(MAX(0,IF($O26="WDV",AB26*$P26*MAX(0,(IF($I26="",AC$3,MIN($I26,AC$3)))-(MAX($H26,(EDATE(AC$3,-12)+1)))+1)/(AC$3-(EDATE(AC$3,-12)+1)+1),IF($N26=0,0,$Q26/$N26*MAX(0,(IF($I26="",AC$3,MIN($I26,AC$3)))-(MAX($H26,(EDATE(AC$3,-12)+1)))+1)/(AC$3-(EDATE(AC$3,-12)+1)+1)))*$W26),MAX(0,AB26-$M26))) | AD26: =IF($K26="","",IF(AND($I26<>"",$I26<=AC$3),0,AB26-AC26)) | AE26: =IF(OR($K26="",$H26=""),"",MIN(MAX(0,IF($O26="WDV",AD26*$P26*MAX(0,(IF($I26="",AE$3,MIN($I26,AE$3)))-(MAX($H26,(EDATE(AE$3,-12)+1)))+1)/(AE$3-(EDATE(AE$3,-12)+1)+1),IF($N26=0,0,$Q26/$N26*MAX(0,(IF($I26="",AE$3,MIN($I26,AE$3)))-(MAX($H26,(EDATE(AE$3,-12)+1)))+1)/(AE$3-(EDATE(AE$3,-12)+1)+1)))*$W26),MAX(0,AD26-$M26))) | AF26: =IF($K26="","",IF(AND($I26<>"",$I26<=AE$3),0,AD26-AE26)) | AG26: =IF(OR($K26="",$H26=""),"",MIN(MAX(0,IF($O26="WDV",AF26*$P26*MAX(0,(IF($I26="",AG$3,MIN($I26,AG$3)))-(MAX($H26,(EDATE(AG$3,-12)+1)))+1)/(AG$3-(EDATE(AG$3,-12)+1)+1),IF($N26=0,0,$Q26/$N26*MAX(0,(IF($I26="",AG$3,MIN($I26,AG$3)))-(MAX($H26,(EDATE(AG$3,-12)+1)))+1)/(AG$3-(EDATE(AG$3,-12)+1)+1)))*$W26),MAX(0,AF26-$M26))) | AH26: =IF($K26="","",IF(AND($I26<>"",$I26<=AG$3),0,AF26-AG26)) | AI26: =IF(OR($K26="",$H26=""),"",MIN(MAX(0,IF($O26="WDV",AH26*$P26*MAX(0,(IF($I26="",AI$3,MIN($I26,AI$3)))-(MAX($H26,(EDATE(AI$3,-12)+1)))+1)/(AI$3-(EDATE(AI$3,-12)+1)+1),IF($N26=0,0,$Q26/$N26*MAX(0,(IF($I26="",AI$3,MIN($I26,AI$3)))-(MAX($H26,(EDATE(AI$3,-12)+1)))+1)/(AI$3-(EDATE(AI$3,-12)+1)+1)))*$W26),MAX(0,AH26-$M26))) | AJ26: =IF($K26="","",IF(AND($I26<>"",$I26<=AI$3),0,AH26-AI26)) | AK26: =IF(OR($K26="",$H26=""),"",MIN(MAX(0,IF($O26="WDV",AJ26*$P26*MAX(0,(IF($I26="",AK$3,MIN($I26,AK$3)))-(MAX($H26,(EDATE(AK$3,-12)+1)))+1)/(AK$3-(EDATE(AK$3,-12)+1)+1),IF($N26=0,0,$Q26/$N26*MAX(0,(IF($I26="",AK$3,MIN($I26,AK$3)))-(MAX($H26,(EDATE(AK$3,-12)+1)))+1)/(AK$3-(EDATE(AK$3,-12)+1)+1)))*$W26),MAX(0,AJ26-$M26))) | AL26: =IF($K26="","",IF(AND($I26<>"",$I26<=AK$3),0,AJ26-AK26)) | AM26: =IF(OR($K26="",$H26=""),"",MIN(MAX(0,IF($O26="WDV",AL26*$P26*MAX(0,(IF($I26="",AM$3,MIN($I26,AM$3)))-(MAX($H26,(EDATE(AM$3,-12)+1)))+1)/(AM$3-(EDATE(AM$3,-12)+1)+1),IF($N26=0,0,$Q26/$N26*MAX(0,(IF($I26="",AM$3,MIN($I26,AM$3)))-(MAX($H26,(EDATE(AM$3,-12)+1)))+1)/(AM$3-(EDATE(AM$3,-12)+1)+1)))*$W26),MAX(0,AL26-$M26))) | AN26: =IF($K26="","",IF(AND($I26<>"",$I26<=AM$3),0,AL26-AM26)) | AO26: =IF(OR($K26="",$H26=""),"",MIN(MAX(0,IF($O26="WDV",AN26*$P26*MAX(0,(IF($I26="",AO$3,MIN($I26,AO$3)))-(MAX($H26,(EDATE(AO$3,-12)+1)))+1)/(AO$3-(EDATE(AO$3,-12)+1)+1),IF($N26=0,0,$Q26/$N26*MAX(0,(IF($I26="",AO$3,MIN($I26,AO$3)))-(MAX($H26,(EDATE(AO$3,-12)+1)))+1)/(AO$3-(EDATE(AO$3,-12)+1)+1)))*$W26),MAX(0,AN26-$M26))) | AP26: =IF($K26="","",IF(AND($I26<>"",$I26<=AO$3),0,AN26-AO26)) | AQ26: =IF(OR($K26="",$H26=""),"",MIN(MAX(0,IF($O26="WDV",AP26*$P26*MAX(0,(IF($I26="",AQ$3,MIN($I26,AQ$3)))-(MAX($H26,(EDATE(AQ$3,-12)+1)))+1)/(AQ$3-(EDATE(AQ$3,-12)+1)+1),IF($N26=0,0,$Q26/$N26*MAX(0,(IF($I26="",AQ$3,MIN($I26,AQ$3)))-(MAX($H26,(EDATE(AQ$3,-12)+1)))+1)/(AQ$3-(EDATE(AQ$3,-12)+1)+1)))*$W26),MAX(0,AP26-$M26))) | AR26: =IF($K26="","",IF(AND($I26<>"",$I26<=AQ$3),0,AP26-AQ26)) | AS26: =IF(OR($K26="",$H26=""),"",MIN(MAX(0,IF($O26="WDV",AR26*$P26*MAX(0,(IF($I26="",AS$3,MIN($I26,AS$3)))-(MAX($H26,(EDATE(AS$3,-12)+1)))+1)/(AS$3-(EDATE(AS$3,-12)+1)+1),IF($N26=0,0,$Q26/$N26*MAX(0,(IF($I26="",AS$3,MIN($I26,AS$3)))-(MAX($H26,(EDATE(AS$3,-12)+1)))+1)/(AS$3-(EDATE(AS$3,-12)+1)+1)))*$W26),MAX(0,AR26-$M26))) | AT26: =IF($K26="","",IF(AND($I26<>"",$I26<=AS$3),0,AR26-AS26)) | AU26: =IF(OR($K26="",$H26=""),"",MIN(MAX(0,IF($O26="WDV",AT26*$P26*MAX(0,(IF($I26="",AU$3,MIN($I26,AU$3)))-(MAX($H26,(EDATE(AU$3,-12)+1)))+1)/(AU$3-(EDATE(AU$3,-12)+1)+1),IF($N26=0,0,$Q26/$N26*MAX(0,(IF($I26="",AU$3,MIN($I26,AU$3)))-(MAX($H26,(EDATE(AU$3,-12)+1)))+1)/(AU$3-(EDATE(AU$3,-12)+1)+1)))*$W26),MAX(0,AT26-$M26))) | AV26: =IF($K26="","",IF(AND($I26<>"",$I26<=AU$3),0,AT26-AU26)) | AW26: =IF(OR($K26="",$H26=""),"",MIN(MAX(0,IF($O26="WDV",AV26*$P26*MAX(0,(IF($I26="",AW$3,MIN($I26,AW$3)))-(MAX($H26,(EDATE(AW$3,-12)+1)))+1)/(AW$3-(EDATE(AW$3,-12)+1)+1),IF($N26=0,0,$Q26/$N26*MAX(0,(IF($I26="",AW$3,MIN($I26,AW$3)))-(MAX($H26,(EDATE(AW$3,-12)+1)))+1)/(AW$3-(EDATE(AW$3,-12)+1)+1)))*$W26),MAX(0,AV26-$M26))) | AX26: =IF($K26="","",IF(AND($I26<>"",$I26<=AW$3),0,AV26-AW26)) | AY26: =IF(OR($K26="",$H26=""),"",MIN(MAX(0,IF($O26="WDV",AX26*$P26*MAX(0,(IF($I26="",AY$3,MIN($I26,AY$3)))-(MAX($H26,(EDATE(AY$3,-12)+1)))+1)/(AY$3-(EDATE(AY$3,-12)+1)+1),IF($N26=0,0,$Q26/$N26*MAX(0,(IF($I26="",AY$3,MIN($I26,AY$3)))-(MAX($H26,(EDATE(AY$3,-12)+1)))+1)/(AY$3-(EDATE(AY$3,-12)+1)+1)))*$W26),MAX(0,AX26-$M26))) | AZ26: =IF($K26="","",IF(AND($I26<>"",$I26<=AY$3),0,AX26-AY26)) | BA26: =IF(OR($K26="",$H26=""),"",MIN(MAX(0,IF($O26="WDV",AZ26*$P26*MAX(0,(IF($I26="",BA$3,MIN($I26,BA$3)))-(MAX($H26,(EDATE(BA$3,-12)+1)))+1)/(BA$3-(EDATE(BA$3,-12)+1)+1),IF($N26=0,0,$Q26/$N26*MAX(0,(IF($I26="",BA$3,MIN($I26,BA$3)))-(MAX($H26,(EDATE(BA$3,-12)+1)))+1)/(BA$3-(EDATE(BA$3,-12)+1)+1)))*$W26),MAX(0,AZ26-$M26))) | BB26: =IF($K26="","",IF(AND($I26<>"",$I26<=BA$3),0,AZ26-BA26)) | BC26: =IF(OR($K26="",$H26=""),"",MIN(MAX(0,IF($O26="WDV",BB26*$P26*MAX(0,(IF($I26="",BC$3,MIN($I26,BC$3)))-(MAX($H26,(EDATE(BC$3,-12)+1)))+1)/(BC$3-(EDATE(BC$3,-12)+1)+1),IF($N26=0,0,$Q26/$N26*MAX(0,(IF($I26="",BC$3,MIN($I26,BC$3)))-(MAX($H26,(EDATE(BC$3,-12)+1)))+1)/(BC$3-(EDATE(BC$3,-12)+1)+1)))*$W26),MAX(0,BB26-$M26))) | BD26: =IF($K26="","",IF(AND($I26<>"",$I26<=BC$3),0,BB26-BC26)) | BE26: =IF(OR($K26="",$H26=""),"",MIN(MAX(0,IF($O26="WDV",BD26*$P26*MAX(0,(IF($I26="",BE$3,MIN($I26,BE$3)))-(MAX($H26,(EDATE(BE$3,-12)+1)))+1)/(BE$3-(EDATE(BE$3,-12)+1)+1),IF($N26=0,0,$Q26/$N26*MAX(0,(IF($I26="",BE$3,MIN($I26,BE$3)))-(MAX($H26,(EDATE(BE$3,-12)+1)))+1)/(BE$3-(EDATE(BE$3,-12)+1)+1)))*$W26),MAX(0,BD26-$M26))) | BF26: =IF($K26="","",IF(AND($I26<>"",$I26<=BE$3),0,BD26-BE26))
... L64: =DefaultResidual | M64: =IF($K64="","",$K64*$L64) | N64: =IF($C64="","",IFERROR(VLOOKUP($C64,ScheduleIITable,3,FALSE),"#N/A")) | O64: =IF($K64="","",GlobalMethod) | P64: =IF(OR($K64="",$N64="",$N64=0,$M64=0),0,1-($M64/$K64)^(1/$N64)) | Q64: =IF($K64="","",$K64-$M64) | R64: =IF($K64="","",INDEX($AA64:$BF64,1,MATCH(ReportingFYEnd,$AA$3:$BF$3,0))) | S64: =IF($K64="","",IF($U64="Disposed",0,$K64-$T64)) | T64: =IF($K64="","",INDEX($AA64:$BF64,1,MATCH(ReportingFYEnd,$AA$3:$BF$3,0)+1)) | U64: =IF($K64="","",IF(AND($I64<>"",$I64<=ReportingFYEnd),"Disposed",IF(OR($H64="",$H64>ReportingFYEnd),"Not Yet in Use","Active"))) | W64: =IF($V64="Double",1.5,IF($V64="Triple",2,1)) | Y64: =IF($K64="","",IF(OR(ISNUMBER(SEARCH("Build",$C64)),ISNUMBER(SEARCH("Lease",$C64))),"Yes","NA")) | AA64: =IF(OR($K64="",$H64=""),"",MIN(MAX(0,IF($O64="WDV",$K64*$P64*MAX(0,(IF($I64="",AA$3,MIN($I64,AA$3)))-(MAX($H64,(EDATE(AA$3,-12)+1)))+1)/(AA$3-(EDATE(AA$3,-12)+1)+1),IF($N64=0,0,$Q64/$N64*MAX(0,(IF($I64="",AA$3,MIN($I64,AA$3)))-(MAX($H64,(EDATE(AA$3,-12)+1)))+1)/(AA$3-(EDATE(AA$3,-12)+1)+1)))*$W64),MAX(0,$K64-$M64))) | AB64: =IF($K64="","",IF(AND($I64<>"",$I64<=AA$3),0,$K64-AA64)) | AC64: =IF(OR($K64="",$H64=""),"",MIN(MAX(0,IF($O64="WDV",AB64*$P64*MAX(0,(IF($I64="",AC$3,MIN($I64,AC$3)))-(MAX($H64,(EDATE(AC$3,-12)+1)))+1)/(AC$3-(EDATE(AC$3,-12)+1)+1),IF($N64=0,0,$Q64/$N64*MAX(0,(IF($I64="",AC$3,MIN($I64,AC$3)))-(MAX($H64,(EDATE(AC$3,-12)+1)))+1)/(AC$3-(EDATE(AC$3,-12)+1)+1)))*$W64),MAX(0,AB64-$M64))) | AD64: =IF($K64="","",IF(AND($I64<>"",$I64<=AC$3),0,AB64-AC64)) | AE64: =IF(OR($K64="",$H64=""),"",MIN(MAX(0,IF($O64="WDV",AD64*$P64*MAX(0,(IF($I64="",AE$3,MIN($I64,AE$3)))-(MAX($H64,(EDATE(AE$3,-12)+1)))+1)/(AE$3-(EDATE(AE$3,-12)+1)+1),IF($N64=0,0,$Q64/$N64*MAX(0,(IF($I64="",AE$3,MIN($I64,AE$3)))-(MAX($H64,(EDATE(AE$3,-12)+1)))+1)/(AE$3-(EDATE(AE$3,-12)+1)+1)))*$W64),MAX(0,AD64-$M64))) | AF64: =IF($K64="","",IF(AND($I64<>"",$I64<=AE$3),0,AD64-AE64)) | AG64: =IF(OR($K64="",$H64=""),"",MIN(MAX(0,IF($O64="WDV",AF64*$P64*MAX(0,(IF($I64="",AG$3,MIN($I64,AG$3)))-(MAX($H64,(EDATE(AG$3,-12)+1)))+1)/(AG$3-(EDATE(AG$3,-12)+1)+1),IF($N64=0,0,$Q64/$N64*MAX(0,(IF($I64="",AG$3,MIN($I64,AG$3)))-(MAX($H64,(EDATE(AG$3,-12)+1)))+1)/(AG$3-(EDATE(AG$3,-12)+1)+1)))*$W64),MAX(0,AF64-$M64))) | AH64: =IF($K64="","",IF(AND($I64<>"",$I64<=AG$3),0,AF64-AG64)) | AI64: =IF(OR($K64="",$H64=""),"",MIN(MAX(0,IF($O64="WDV",AH64*$P64*MAX(0,(IF($I64="",AI$3,MIN($I64,AI$3)))-(MAX($H64,(EDATE(AI$3,-12)+1)))+1)/(AI$3-(EDATE(AI$3,-12)+1)+1),IF($N64=0,0,$Q64/$N64*MAX(0,(IF($I64="",AI$3,MIN($I64,AI$3)))-(MAX($H64,(EDATE(AI$3,-12)+1)))+1)/(AI$3-(EDATE(AI$3,-12)+1)+1)))*$W64),MAX(0,AH64-$M64))) | AJ64: =IF($K64="","",IF(AND($I64<>"",$I64<=AI$3),0,AH64-AI64)) | AK64: =IF(OR($K64="",$H64=""),"",MIN(MAX(0,IF($O64="WDV",AJ64*$P64*MAX(0,(IF($I64="",AK$3,MIN($I64,AK$3)))-(MAX($H64,(EDATE(AK$3,-12)+1)))+1)/(AK$3-(EDATE(AK$3,-12)+1)+1),IF($N64=0,0,$Q64/$N64*MAX(0,(IF($I64="",AK$3,MIN($I64,AK$3)))-(MAX($H64,(EDATE(AK$3,-12)+1)))+1)/(AK$3-(EDATE(AK$3,-12)+1)+1)))*$W64),MAX(0,AJ64-$M64))) | AL64: =IF($K64="","",IF(AND($I64<>"",$I64<=AK$3),0,AJ64-AK64)) | AM64: =IF(OR($K64="",$H64=""),"",MIN(MAX(0,IF($O64="WDV",AL64*$P64*MAX(0,(IF($I64="",AM$3,MIN($I64,AM$3)))-(MAX($H64,(EDATE(AM$3,-12)+1)))+1)/(AM$3-(EDATE(AM$3,-12)+1)+1),IF($N64=0,0,$Q64/$N64*MAX(0,(IF($I64="",AM$3,MIN($I64,AM$3)))-(MAX($H64,(EDATE(AM$3,-12)+1)))+1)/(AM$3-(EDATE(AM$3,-12)+1)+1)))*$W64),MAX(0,AL64-$M64))) | AN64: =IF($K64="","",IF(AND($I64<>"",$I64<=AM$3),0,AL64-AM64)) | AO64: =IF(OR($K64="",$H64=""),"",MIN(MAX(0,IF($O64="WDV",AN64*$P64*MAX(0,(IF($I64="",AO$3,MIN($I64,AO$3)))-(MAX($H64,(EDATE(AO$3,-12)+1)))+1)/(AO$3-(EDATE(AO$3,-12)+1)+1),IF($N64=0,0,$Q64/$N64*MAX(0,(IF($I64="",AO$3,MIN($I64,AO$3)))-(MAX($H64,(EDATE(AO$3,-12)+1)))+1)/(AO$3-(EDATE(AO$3,-12)+1)+1)))*$W64),MAX(0,AN64-$M64))) | AP64: =IF($K64="","",IF(AND($I64<>"",$I64<=AO$3),0,AN64-AO64)) | AQ64: =IF(OR($K64="",$H64=""),"",MIN(MAX(0,IF($O64="WDV",AP64*$P64*MAX(0,(IF($I64="",AQ$3,MIN($I64,AQ$3)))-(MAX($H64,(EDATE(AQ$3,-12)+1)))+1)/(AQ$3-(EDATE(AQ$3,-12)+1)+1),IF($N64=0,0,$Q64/$N64*MAX(0,(IF($I64="",AQ$3,MIN($I64,AQ$3)))-(MAX($H64,(EDATE(AQ$3,-12)+1)))+1)/(AQ$3-(EDATE(AQ$3,-12)+1)+1)))*$W64),MAX(0,AP64-$M64))) | AR64: =IF($K64="","",IF(AND($I64<>"",$I64<=AQ$3),0,AP64-AQ64)) | AS64: =IF(OR($K64="",$H64=""),"",MIN(MAX(0,IF($O64="WDV",AR64*$P64*MAX(0,(IF($I64="",AS$3,MIN($I64,AS$3)))-(MAX($H64,(EDATE(AS$3,-12)+1)))+1)/(AS$3-(EDATE(AS$3,-12)+1)+1),IF($N64=0,0,$Q64/$N64*MAX(0,(IF($I64="",AS$3,MIN($I64,AS$3)))-(MAX($H64,(EDATE(AS$3,-12)+1)))+1)/(AS$3-(EDATE(AS$3,-12)+1)+1)))*$W64),MAX(0,AR64-$M64))) | AT64: =IF($K64="","",IF(AND($I64<>"",$I64<=AS$3),0,AR64-AS64)) | AU64: =IF(OR($K64="",$H64=""),"",MIN(MAX(0,IF($O64="WDV",AT64*$P64*MAX(0,(IF($I64="",AU$3,MIN($I64,AU$3)))-(MAX($H64,(EDATE(AU$3,-12)+1)))+1)/(AU$3-(EDATE(AU$3,-12)+1)+1),IF($N64=0,0,$Q64/$N64*MAX(0,(IF($I64="",AU$3,MIN($I64,AU$3)))-(MAX($H64,(EDATE(AU$3,-12)+1)))+1)/(AU$3-(EDATE(AU$3,-12)+1)+1)))*$W64),MAX(0,AT64-$M64))) | AV64: =IF($K64="","",IF(AND($I64<>"",$I64<=AU$3),0,AT64-AU64)) | AW64: =IF(OR($K64="",$H64=""),"",MIN(MAX(0,IF($O64="WDV",AV64*$P64*MAX(0,(IF($I64="",AW$3,MIN($I64,AW$3)))-(MAX($H64,(EDATE(AW$3,-12)+1)))+1)/(AW$3-(EDATE(AW$3,-12)+1)+1),IF($N64=0,0,$Q64/$N64*MAX(0,(IF($I64="",AW$3,MIN($I64,AW$3)))-(MAX($H64,(EDATE(AW$3,-12)+1)))+1)/(AW$3-(EDATE(AW$3,-12)+1)+1)))*$W64),MAX(0,AV64-$M64))) | AX64: =IF($K64="","",IF(AND($I64<>"",$I64<=AW$3),0,AV64-AW64)) | AY64: =IF(OR($K64="",$H64=""),"",MIN(MAX(0,IF($O64="WDV",AX64*$P64*MAX(0,(IF($I64="",AY$3,MIN($I64,AY$3)))-(MAX($H64,(EDATE(AY$3,-12)+1)))+1)/(AY$3-(EDATE(AY$3,-12)+1)+1),IF($N64=0,0,$Q64/$N64*MAX(0,(IF($I64="",AY$3,MIN($I64,AY$3)))-(MAX($H64,(EDATE(AY$3,-12)+1)))+1)/(AY$3-(EDATE(AY$3,-12)+1)+1)))*$W64),MAX(0,AX64-$M64))) | AZ64: =IF($K64="","",IF(AND($I64<>"",$I64<=AY$3),0,AX64-AY64)) | BA64: =IF(OR($K64="",$H64=""),"",MIN(MAX(0,IF($O64="WDV",AZ64*$P64*MAX(0,(IF($I64="",BA$3,MIN($I64,BA$3)))-(MAX($H64,(EDATE(BA$3,-12)+1)))+1)/(BA$3-(EDATE(BA$3,-12)+1)+1),IF($N64=0,0,$Q64/$N64*MAX(0,(IF($I64="",BA$3,MIN($I64,BA$3)))-(MAX($H64,(EDATE(BA$3,-12)+1)))+1)/(BA$3-(EDATE(BA$3,-12)+1)+1)))*$W64),MAX(0,AZ64-$M64))) | BB64: =IF($K64="","",IF(AND($I64<>"",$I64<=BA$3),0,AZ64-BA64)) | BC64: =IF(OR($K64="",$H64=""),"",MIN(MAX(0,IF($O64="WDV",BB64*$P64*MAX(0,(IF($I64="",BC$3,MIN($I64,BC$3)))-(MAX($H64,(EDATE(BC$3,-12)+1)))+1)/(BC$3-(EDATE(BC$3,-12)+1)+1),IF($N64=0,0,$Q64/$N64*MAX(0,(IF($I64="",BC$3,MIN($I64,BC$3)))-(MAX($H64,(EDATE(BC$3,-12)+1)))+1)/(BC$3-(EDATE(BC$3,-12)+1)+1)))*$W64),MAX(0,BB64-$M64))) | BD64: =IF($K64="","",IF(AND($I64<>"",$I64<=BC$3),0,BB64-BC64)) | BE64: =IF(OR($K64="",$H64=""),"",MIN(MAX(0,IF($O64="WDV",BD64*$P64*MAX(0,(IF($I64="",BE$3,MIN($I64,BE$3)))-(MAX($H64,(EDATE(BE$3,-12)+1)))+1)/(BE$3-(EDATE(BE$3,-12)+1)+1),IF($N64=0,0,$Q64/$N64*MAX(0,(IF($I64="",BE$3,MIN($I64,BE$3)))-(MAX($H64,(EDATE(BE$3,-12)+1)))+1)/(BE$3-(EDATE(BE$3,-12)+1)+1)))*$W64),MAX(0,BD64-$M64))) | BF64: =IF($K64="","",IF(AND($I64<>"",$I64<=BE$3),0,BD64-BE64))
A65: TOTAL | J65: =SUM(J5:J64) | K65: =SUM(K5:K64) | M65: =SUM(M5:M64) | Q65: =SUM(Q5:Q64) | R65: =SUM(R5:R64) | S65: =SUM(S5:S64) | T65: =SUM(T5:T64) | AA65: =SUM(AA5:AA64) | AB65: =SUM(AB5:AB64) | AC65: =SUM(AC5:AC64) | AD65: =SUM(AD5:AD64) | AE65: =SUM(AE5:AE64) | AF65: =SUM(AF5:AF64) | AG65: =SUM(AG5:AG64) | AH65: =SUM(AH5:AH64) | ... BF65: =SUM(BF5:BF64)

Sheet Reports
B2: DEPRECIATION REPORTS – YEAR-WISE SCHEDULE
B3: ="Method: "&GlobalMethod&" | All figures auto-link to the FAR sheet"
B5: A. YEAR-WISE DEPRECIATION & NET BLOCK MOVEMENT
B6: Financial Year | C6: Dep for the Year (Rs.) | D6: Cumulative Dep (Rs.) | E6: Closing Net Block / WDV (Rs.)
B7: ="FY "&TEXT(FAR!AA$3,"yyyy") | C7: =FAR!AA65 | D7: =C7 | E7: =FAR!AB65
B8: ="FY "&TEXT(FAR!AC$3,"yyyy") | C8: =FAR!AC65 | D8: =D7+C8 | E8: =FAR!AD65
B9: ="FY "&TEXT(FAR!AE$3,"yyyy") | C9: =FAR!AE65 | D9: =D8+C9 | E9: =FAR!AF65
B10: ="FY "&TEXT(FAR!AG$3,"yyyy") | C10: =FAR!AG65 | D10: =D9+C10 | E10: =FAR!AH65
B11: ="FY "&TEXT(FAR!AI$3,"yyyy") | C11: =FAR!AI65 | D11: =D10+C11 | E11: =FAR!AJ65
B12: ="FY "&TEXT(FAR!AK$3,"yyyy") | C12: =FAR!AK65 | D12: =D11+C12 | E12: =FAR!AL65
B13: ="FY "&TEXT(FAR!AM$3,"yyyy") | C13: =FAR!AM65 | D13: =D12+C13 | E13: =FAR!AN65
B14: ="FY "&TEXT(FAR!AO$3,"yyyy") | C14: =FAR!AO65 | D14: =D13+C14 | E14: =FAR!AP65
B15: ="FY "&TEXT(FAR!AQ$3,"yyyy") | C15: =FAR!AQ65 | D15: =D14+C15 | E15: =FAR!AR65
B16: ="FY "&TEXT(FAR!AS$3,"yyyy") | C16: =FAR!AS65 | D16: =D15+C16 | E16: =FAR!AT65
B17: ="FY "&TEXT(FAR!AU$3,"yyyy") | C17: =FAR!AU65 | D17: =D16+C17 | E17: =FAR!AV65
B18: ="FY "&TEXT(FAR!AW$3,"yyyy") | C18: =FAR!AW65 | D18: =D17+C18 | E18: =FAR!AX65
B19: ="FY "&TEXT(FAR!AY$3,"yyyy") | C19: =FAR!AY65 | D19: =D18+C19 | E19: =FAR!AZ65
B20: ="FY "&TEXT(FAR!BA$3,"yyyy") | C20: =FAR!BA65 | D20: =D19+C20 | E20: =FAR!BB65
B21: ="FY "&TEXT(FAR!BC$3,"yyyy") | C21: =FAR!BC65 | D21: =D20+C21 | E21: =FAR!BD65
B22: ="FY "&TEXT(FAR!BE$3,"yyyy") | C22: =FAR!BE65 | D22: =D21+C22 | E22: =FAR!BF65
B24: B. CATEGORY × YEAR DEPRECIATION MATRIX (Rs.)
B25: Asset Category | C25: =TEXT(FAR!AA$3,"yyyy") | D25: =TEXT(FAR!AC$3,"yyyy") | E25: =TEXT(FAR!AE$3,"yyyy") | F25: =TEXT(FAR!AG$3,"yyyy") | G25: =TEXT(FAR!AI$3,"yyyy") | H25: =TEXT(FAR!AK$3,"yyyy") | I25: =TEXT(FAR!AM$3,"yyyy") | J25: =TEXT(FAR!AO$3,"yyyy") | K25: =TEXT(FAR!AQ$3,"yyyy") | L25: =TEXT(FAR!AS$3,"yyyy") | M25: =TEXT(FAR!AU$3,"yyyy") | N25: =TEXT(FAR!AW$3,"yyyy") | O25: =TEXT(FAR!AY$3,"yyyy") | P25: =TEXT(FAR!BA$3,"yyyy") | Q25: =TEXT(FAR!BC$3,"yyyy") | R25: =TEXT(FAR!BE$3,"yyyy")
B26: =Input!C15 | C26: =SUMIF(FAR!$C$5:$C$64,$B26,FAR!AA$5:AA$64) | D26: =SUMIF(FAR!$C$5:$C$64,$B26,FAR!AC$5:AC$64) | E26: =SUMIF(FAR!$C$5:$C$64,$B26,FAR!AE$5:AE$64) | F26: =SUMIF(FAR!$C$5:$C$64,$B26,FAR!AG$5:AG$64) | G26: =SUMIF(FAR!$C$5:$C$64,$B26,FAR!AI$5:AI$64) | H26: =SUMIF(FAR!$C$5:$C$64,$B26,FAR!AK$5:AK$64) | I26: =SUMIF(FAR!$C$5:$C$64,$B26,FAR!AM$5:AM$64) | J26: =SUMIF(FAR!$C$5:$C$64,$B26,FAR!AO$5:AO$64) | K26: =SUMIF(FAR!$C$5:$C$64,$B26,FAR!AQ$5:AQ$64) | L26: =SUMIF(FAR!$C$5:$C$64,$B26,FAR!AS$5:AS$64) | M26: =SUMIF(FAR!$C$5:$C$64,$B26,FAR!AU$5:AU$64) | N26: =SUMIF(FAR!$C$5:$C$64,$B26,FAR!AW$5:AW$64) | O26: =SUMIF(FAR!$C$5:$C$64,$B26,FAR!AY$5:AY$64) | P26: =SUMIF(FAR!$C$5:$C$64,$B26,FAR!BA$5:BA$64) | Q26: =SUMIF(FAR!$C$5:$C$64,$B26,FAR!BC$5:BC$64) | R26: =SUMIF(FAR!$C$5:$C$64,$B26,FAR!BE$5:BE$64)
B27: =Input!C16 | C27: =SUMIF(FAR!$C$5:$C$64,$B27,FAR!AA$5:AA$64) | D27: =SUMIF(FAR!$C$5:$C$64,$B27,FAR!AC$5:AC$64) | E27: =SUMIF(FAR!$C$5:$C$64,$B27,FAR!AE$5:AE$64) | F27: =SUMIF(FAR!$C$5:$C$64,$B27,FAR!AG$5:AG$64) | G27: =SUMIF(FAR!$C$5:$C$64,$B27,FAR!AI$5:AI$64) | H27: =SUMIF(FAR!$C$5:$C$64,$B27,FAR!AK$5:AK$64) | I27: =SUMIF(FAR!$C$5:$C$64,$B27,FAR!AM$5:AM$64) | J27: =SUMIF(FAR!$C$5:$C$64,$B27,FAR!AO$5:AO$64) | K27: =SUMIF(FAR!$C$5:$C$64,$B27,FAR!AQ$5:AQ$64) | L27: =SUMIF(FAR!$C$5:$C$64,$B27,FAR!AS$5:AS$64) | M27: =SUMIF(FAR!$C$5:$C$64,$B27,FAR!AU$5:AU$64) | N27: =SUMIF(FAR!$C$5:$C$64,$B27,FAR!AW$5:AW$64) | O27: =SUMIF(FAR!$C$5:$C$64,$B27,FAR!AY$5:AY$64) | P27: =SUMIF(FAR!$C$5:$C$64,$B27,FAR!BA$5:BA$64) | Q27: =SUMIF(FAR!$C$5:$C$64,$B27,FAR!BC$5:BC$64) | R27: =SUMIF(FAR!$C$5:$C$64,$B27,FAR!BE$5:BE$64)
B28: =Input!C17 | C28: =SUMIF(FAR!$C$5:$C$64,$B28,FAR!AA$5:AA$64) | D28: =SUMIF(FAR!$C$5:$C$64,$B28,FAR!AC$5:AC$64) | E28: =SUMIF(FAR!$C$5:$C$64,$B28,FAR!AE$5:AE$64) | F28: =SUMIF(FAR!$C$5:$C$64,$B28,FAR!AG$5:AG$64) | G28: =SUMIF(FAR!$C$5:$C$64,$B28,FAR!AI$5:AI$64) | H28: =SUMIF(FAR!$C$5:$C$64,$B28,FAR!AK$5:AK$64) | I28: =SUMIF(FAR!$C$5:$C$64,$B28,FAR!AM$5:AM$64) | J28: =SUMIF(FAR!$C$5:$C$64,$B28,FAR!AO$5:AO$64) | K28: =SUMIF(FAR!$C$5:$C$64,$B28,FAR!AQ$5:AQ$64) | L28: =SUMIF(FAR!$C$5:$C$64,$B28,FAR!AS$5:AS$64) | M28: =SUMIF(FAR!$C$5:$C$64,$B28,FAR!AU$5:AU$64) | N28: =SUMIF(FAR!$C$5:$C$64,$B28,FAR!AW$5:AW$64) | O28: =SUMIF(FAR!$C$5:$C$64,$B28,FAR!AY$5:AY$64) | P28: =SUMIF(FAR!$C$5:$C$64,$B28,FAR!BA$5:BA$64) | Q28: =SUMIF(FAR!$C$5:$C$64,$B28,FAR!BC$5:BC$64) | R28: =SUMIF(FAR!$C$5:$C$64,$B28,FAR!BE$5:BE$64)
B29: =Input!C18 | C29: =SUMIF(FAR!$C$5:$C$64,$B29,FAR!AA$5:AA$64) | D29: =SUMIF(FAR!$C$5:$C$64,$B29,FAR!AC$5:AC$64) | E29: =SUMIF(FAR!$C$5:$C$64,$B29,FAR!AE$5:AE$64) | F29: =SUMIF(FAR!$C$5:$C$64,$B29,FAR!AG$5:AG$64) | G29: =SUMIF(FAR!$C$5:$C$64,$B29,FAR!AI$5:AI$64) | H29: =SUMIF(FAR!$C$5:$C$64,$B29,FAR!AK$5:AK$64) | I29: =SUMIF(FAR!$C$5:$C$64,$B29,FAR!AM$5:AM$64) | J29: =SUMIF(FAR!$C$5:$C$64,$B29,FAR!AO$5:AO$64) | K29: =SUMIF(FAR!$C$5:$C$64,$B29,FAR!AQ$5:AQ$64) | L29: =SUMIF(FAR!$C$5:$C$64,$B29,FAR!AS$5:AS$64) | M29: =SUMIF(FAR!$C$5:$C$64,$B29,FAR!AU$5:AU$64) | N29: =SUMIF(FAR!$C$5:$C$64,$B29,FAR!AW$5:AW$64) | O29: =SUMIF(FAR!$C$5:$C$64,$B29,FAR!AY$5:AY$64) | P29: =SUMIF(FAR!$C$5:$C$64,$B29,FAR!BA$5:BA$64) | Q29: =SUMIF(FAR!$C$5:$C$64,$B29,FAR!BC$5:BC$64) | R29: =SUMIF(FAR!$C$5:$C$64,$B29,FAR!BE$5:BE$64)
B30: =Input!C19 | C30: =SUMIF(FAR!$C$5:$C$64,$B30,FAR!AA$5:AA$64) | D30: =SUMIF(FAR!$C$5:$C$64,$B30,FAR!AC$5:AC$64) | E30: =SUMIF(FAR!$C$5:$C$64,$B30,FAR!AE$5:AE$64) | F30: =SUMIF(FAR!$C$5:$C$64,$B30,FAR!AG$5:AG$64) | G30: =SUMIF(FAR!$C$5:$C$64,$B30,FAR!AI$5:AI$64) | H30: =SUMIF(FAR!$C$5:$C$64,$B30,FAR!AK$5:AK$64) | I30: =SUMIF(FAR!$C$5:$C$64,$B30,FAR!AM$5:AM$64) | J30: =SUMIF(FAR!$C$5:$C$64,$B30,FAR!AO$5:AO$64) | K30: =SUMIF(FAR!$C$5:$C$64,$B30,FAR!AQ$5:AQ$64) | L30: =SUMIF(FAR!$C$5:$C$64,$B30,FAR!AS$5:AS$64) | M30: =SUMIF(FAR!$C$5:$C$64,$B30,FAR!AU$5:AU$64) | N30: =SUMIF(FAR!$C$5:$C$64,$B30,FAR!AW$5:AW$64) | O30: =SUMIF(FAR!$C$5:$C$64,$B30,FAR!AY$5:AY$64) | P30: =SUMIF(FAR!$C$5:$C$64,$B30,FAR!BA$5:BA$64) | Q30: =SUMIF(FAR!$C$5:$C$64,$B30,FAR!BC$5:BC$64) | R30: =SUMIF(FAR!$C$5:$C$64,$B30,FAR!BE$5:BE$64)
B31: =Input!C20 | C31: =SUMIF(FAR!$C$5:$C$64,$B31,FAR!AA$5:AA$64) | D31: =SUMIF(FAR!$C$5:$C$64,$B31,FAR!AC$5:AC$64) | E31: =SUMIF(FAR!$C$5:$C$64,$B31,FAR!AE$5:AE$64) | F31: =SUMIF(FAR!$C$5:$C$64,$B31,FAR!AG$5:AG$64) | G31: =SUMIF(FAR!$C$5:$C$64,$B31,FAR!AI$5:AI$64) | H31: =SUMIF(FAR!$C$5:$C$64,$B31,FAR!AK$5:AK$64) | I31: =SUMIF(FAR!$C$5:$C$64,$B31,FAR!AM$5:AM$64) | J31: =SUMIF(FAR!$C$5:$C$64,$B31,FAR!AO$5:AO$64) | K31: =SUMIF(FAR!$C$5:$C$64,$B31,FAR!AQ$5:AQ$64) | L31: =SUMIF(FAR!$C$5:$C$64,$B31,FAR!AS$5:AS$64) | M31: =SUMIF(FAR!$C$5:$C$64,$B31,FAR!AU$5:AU$64) | N31: =SUMIF(FAR!$C$5:$C$64,$B31,FAR!AW$5:AW$64) | O31: =SUMIF(FAR!$C$5:$C$64,$B31,FAR!AY$5:AY$64) | P31: =SUMIF(FAR!$C$5:$C$64,$B31,FAR!BA$5:BA$64) | Q31: =SUMIF(FAR!$C$5:$C$64,$B31,FAR!BC$5:BC$64) | R31: =SUMIF(FAR!$C$5:$C$64,$B31,FAR!BE$5:BE$64)
B32: =Input!C21 | C32: =SUMIF(FAR!$C$5:$C$64,$B32,FAR!AA$5:AA$64) | D32: =SUMIF(FAR!$C$5:$C$64,$B32,FAR!AC$5:AC$64) | E32: =SUMIF(FAR!$C$5:$C$64,$B32,FAR!AE$5:AE$64) | F32: =SUMIF(FAR!$C$5:$C$64,$B32,FAR!AG$5:AG$64) | G32: =SUMIF(FAR!$C$5:$C$64,$B32,FAR!AI$5:AI$64) | H32: =SUMIF(FAR!$C$5:$C$64,$B32,FAR!AK$5:AK$64) | I32: =SUMIF(FAR!$C$5:$C$64,$B32,FAR!AM$5:AM$64) | J32: =SUMIF(FAR!$C$5:$C$64,$B32,FAR!AO$5:AO$64) | K32: =SUMIF(FAR!$C$5:$C$64,$B32,FAR!AQ$5:AQ$64) | L32: =SUMIF(FAR!$C$5:$C$64,$B32,FAR!AS$5:AS$64) | M32: =SUMIF(FAR!$C$5:$C$64,$B32,FAR!AU$5:AU$64) | N32: =SUMIF(FAR!$C$5:$C$64,$B32,FAR!AW$5:AW$64) | O32: =SUMIF(FAR!$C$5:$C$64,$B32,FAR!AY$5:AY$64) | P32: =SUMIF(FAR!$C$5:$C$64,$B32,FAR!BA$5:BA$64) | Q32: =SUMIF(FAR!$C$5:$C$64,$B32,FAR!BC$5:BC$64) | R32: =SUMIF(FAR!$C$5:$C$64,$B32,FAR!BE$5:BE$64)
B33: =Input!C22 | C33: =SUMIF(FAR!$C$5:$C$64,$B33,FAR!AA$5:AA$64) | D33: =SUMIF(FAR!$C$5:$C$64,$B33,FAR!AC$5:AC$64) | E33: =SUMIF(FAR!$C$5:$C$64,$B33,FAR!AE$5:AE$64) | F33: =SUMIF(FAR!$C$5:$C$64,$B33,FAR!AG$5:AG$64) | G33: =SUMIF(FAR!$C$5:$C$64,$B33,FAR!AI$5:AI$64) | H33: =SUMIF(FAR!$C$5:$C$64,$B33,FAR!AK$5:AK$64) | I33: =SUMIF(FAR!$C$5:$C$64,$B33,FAR!AM$5:AM$64) | J33: =SUMIF(FAR!$C$5:$C$64,$B33,FAR!AO$5:AO$64) | K33: =SUMIF(FAR!$C$5:$C$64,$B33,FAR!AQ$5:AQ$64) | L33: =SUMIF(FAR!$C$5:$C$64,$B33,FAR!AS$5:AS$64) | M33: =SUMIF(FAR!$C$5:$C$64,$B33,FAR!AU$5:AU$64) | N33: =SUMIF(FAR!$C$5:$C$64,$B33,FAR!AW$5:AW$64) | O33: =SUMIF(FAR!$C$5:$C$64,$B33,FAR!AY$5:AY$64) | P33: =SUMIF(FAR!$C$5:$C$64,$B33,FAR!BA$5:BA$64) | Q33: =SUMIF(FAR!$C$5:$C$64,$B33,FAR!BC$5:BC$64) | R33: =SUMIF(FAR!$C$5:$C$64,$B33,FAR!BE$5:BE$64)
B34: =Input!C23 | C34: =SUMIF(FAR!$C$5:$C$64,$B34,FAR!AA$5:AA$64) | D34: =SUMIF(FAR!$C$5:$C$64,$B34,FAR!AC$5:AC$64) | E34: =SUMIF(FAR!$C$5:$C$64,$B34,FAR!AE$5:AE$64) | F34: =SUMIF(FAR!$C$5:$C$64,$B34,FAR!AG$5:AG$64) | G34: =SUMIF(FAR!$C$5:$C$64,$B34,FAR!AI$5:AI$64) | H34: =SUMIF(FAR!$C$5:$C$64,$B34,FAR!AK$5:AK$64) | I34: =SUMIF(FAR!$C$5:$C$64,$B34,FAR!AM$5:AM$64) | J34: =SUMIF(FAR!$C$5:$C$64,$B34,FAR!AO$5:AO$64) | K34: =SUMIF(FAR!$C$5:$C$64,$B34,FAR!AQ$5:AQ$64) | L34: =SUMIF(FAR!$C$5:$C$64,$B34,FAR!AS$5:AS$64) | M34: =SUMIF(FAR!$C$5:$C$64,$B34,FAR!AU$5:AU$64) | N34: =SUMIF(FAR!$C$5:$C$64,$B34,FAR!AW$5:AW$64) | O34: =SUMIF(FAR!$C$5:$C$64,$B34,FAR!AY$5:AY$64) | P34: =SUMIF(FAR!$C$5:$C$64,$B34,FAR!BA$5:BA$64) | Q34: =SUMIF(FAR!$C$5:$C$64,$B34,FAR!BC$5:BC$64) | R34: =SUMIF(FAR!$C$5:$C$64,$B34,FAR!BE$5:BE$64)
B35: =Input!C24 | C35: =SUMIF(FAR!$C$5:$C$64,$B35,FAR!AA$5:AA$64) | D35: =SUMIF(FAR!$C$5:$C$64,$B35,FAR!AC$5:AC$64) | E35: =SUMIF(FAR!$C$5:$C$64,$B35,FAR!AE$5:AE$64) | F35: =SUMIF(FAR!$C$5:$C$64,$B35,FAR!AG$5:AG$64) | G35: =SUMIF(FAR!$C$5:$C$64,$B35,FAR!AI$5:AI$64) | H35: =SUMIF(FAR!$C$5:$C$64,$B35,FAR!AK$5:AK$64) | I35: =SUMIF(FAR!$C$5:$C$64,$B35,FAR!AM$5:AM$64) | J35: =SUMIF(FAR!$C$5:$C$64,$B35,FAR!AO$5:AO$64) | K35: =SUMIF(FAR!$C$5:$C$64,$B35,FAR!AQ$5:AQ$64) | L35: =SUMIF(FAR!$C$5:$C$64,$B35,FAR!AS$5:AS$64) | M35: =SUMIF(FAR!$C$5:$C$64,$B35,FAR!AU$5:AU$64) | N35: =SUMIF(FAR!$C$5:$C$64,$B35,FAR!AW$5:AW$64) | O35: =SUMIF(FAR!$C$5:$C$64,$B35,FAR!AY$5:AY$64) | P35: =SUMIF(FAR!$C$5:$C$64,$B35,FAR!BA$5:BA$64) | Q35: =SUMIF(FAR!$C$5:$C$64,$B35,FAR!BC$5:BC$64) | R35: =SUMIF(FAR!$C$5:$C$64,$B35,FAR!BE$5:BE$64)
B36: =Input!C25 | C36: =SUMIF(FAR!$C$5:$C$64,$B36,FAR!AA$5:AA$64) | D36: =SUMIF(FAR!$C$5:$C$64,$B36,FAR!AC$5:AC$64) | E36: =SUMIF(FAR!$C$5:$C$64,$B36,FAR!AE$5:AE$64) | F36: =SUMIF(FAR!$C$5:$C$64,$B36,FAR!AG$5:AG$64) | G36: =SUMIF(FAR!$C$5:$C$64,$B36,FAR!AI$5:AI$64) | H36: =SUMIF(FAR!$C$5:$C$64,$B36,FAR!AK$5:AK$64) | I36: =SUMIF(FAR!$C$5:$C$64,$B36,FAR!AM$5:AM$64) | J36: =SUMIF(FAR!$C$5:$C$64,$B36,FAR!AO$5:AO$64) | K36: =SUMIF(FAR!$C$5:$C$64,$B36,FAR!AQ$5:AQ$64) | L36: =SUMIF(FAR!$C$5:$C$64,$B36,FAR!AS$5:AS$64) | M36: =SUMIF(FAR!$C$5:$C$64,$B36,FAR!AU$5:AU$64) | N36: =SUMIF(FAR!$C$5:$C$64,$B36,FAR!AW$5:AW$64) | O36: =SUMIF(FAR!$C$5:$C$64,$B36,FAR!AY$5:AY$64) | P36: =SUMIF(FAR!$C$5:$C$64,$B36,FAR!BA$5:BA$64) | Q36: =SUMIF(FAR!$C$5:$C$64,$B36,FAR!BC$5:BC$64) | R36: =SUMIF(FAR!$C$5:$C$64,$B36,FAR!BE$5:BE$64)
B37: =Input!C26 | C37: =SUMIF(FAR!$C$5:$C$64,$B37,FAR!AA$5:AA$64) | D37: =SUMIF(FAR!$C$5:$C$64,$B37,FAR!AC$5:AC$64) | E37: =SUMIF(FAR!$C$5:$C$64,$B37,FAR!AE$5:AE$64) | F37: =SUMIF(FAR!$C$5:$C$64,$B37,FAR!AG$5:AG$64) | G37: =SUMIF(FAR!$C$5:$C$64,$B37,FAR!AI$5:AI$64) | H37: =SUMIF(FAR!$C$5:$C$64,$B37,FAR!AK$5:AK$64) | I37: =SUMIF(FAR!$C$5:$C$64,$B37,FAR!AM$5:AM$64) | J37: =SUMIF(FAR!$C$5:$C$64,$B37,FAR!AO$5:AO$64) | K37: =SUMIF(FAR!$C$5:$C$64,$B37,FAR!AQ$5:AQ$64) | L37: =SUMIF(FAR!$C$5:$C$64,$B37,FAR!AS$5:AS$64) | M37: =SUMIF(FAR!$C$5:$C$64,$B37,FAR!AU$5:AU$64) | N37: =SUMIF(FAR!$C$5:$C$64,$B37,FAR!AW$5:AW$64) | O37: =SUMIF(FAR!$C$5:$C$64,$B37,FAR!AY$5:AY$64) | P37: =SUMIF(FAR!$C$5:$C$64,$B37,FAR!BA$5:BA$64) | Q37: =SUMIF(FAR!$C$5:$C$64,$B37,FAR!BC$5:BC$64) | R37: =SUMIF(FAR!$C$5:$C$64,$B37,FAR!BE$5:BE$64)
... B43: =Input!C32 | C43: =SUMIF(FAR!$C$5:$C$64,$B43,FAR!AA$5:AA$64) | D43: =SUMIF(FAR!$C$5:$C$64,$B43,FAR!AC$5:AC$64) | E43: =SUMIF(FAR!$C$5:$C$64,$B43,FAR!AE$5:AE$64) | F43: =SUMIF(FAR!$C$5:$C$64,$B43,FAR!AG$5:AG$64) | G43: =SUMIF(FAR!$C$5:$C$64,$B43,FAR!AI$5:AI$64) | H43: =SUMIF(FAR!$C$5:$C$64,$B43,FAR!AK$5:AK$64) | I43: =SUMIF(FAR!$C$5:$C$64,$B43,FAR!AM$5:AM$64) | J43: =SUMIF(FAR!$C$5:$C$64,$B43,FAR!AO$5:AO$64) | K43: =SUMIF(FAR!$C$5:$C$64,$B43,FAR!AQ$5:AQ$64) | L43: =SUMIF(FAR!$C$5:$C$64,$B43,FAR!AS$5:AS$64) | M43: =SUMIF(FAR!$C$5:$C$64,$B43,FAR!AU$5:AU$64) | N43: =SUMIF(FAR!$C$5:$C$64,$B43,FAR!AW$5:AW$64) | O43: =SUMIF(FAR!$C$5:$C$64,$B43,FAR!AY$5:AY$64) | P43: =SUMIF(FAR!$C$5:$C$64,$B43,FAR!BA$5:BA$64) | Q43: =SUMIF(FAR!$C$5:$C$64,$B43,FAR!BC$5:BC$64) | R43: =SUMIF(FAR!$C$5:$C$64,$B43,FAR!BE$5:BE$64)
B44: TOTAL | C44: =SUM(C26:C43) | D44: =SUM(D26:D43) | E44: =SUM(E26:E43) | F44: =SUM(F26:F43) | G44: =SUM(G26:G43) | H44: =SUM(H26:H43) | I44: =SUM(I26:I43) | J44: =SUM(J26:J43) | ... R44: =SUM(R26:R43)

Sheet Summary
B2: FIXED ASSETS – SUMMARY / SCHEDULE TO ACCOUNTS
B3: ="As on "&TEXT(ReportingFYEnd,"dd-mmm-yyyy")&" | Method: "&GlobalMethod&" | "&Input!C6
B5: Asset Category | C5: Gross Block (Rs.) | D5: Dep for the Year (Rs.) | E5: Accumulated Dep (Rs.) | F5: Net Block / WDV (Rs.)
B6: =Input!C15 | C6: =SUMIFS(FAR!$K$5:$K$64,FAR!$C$5:$C$64,$B6,FAR!$U$5:$U$64,"<>Disposed") | D6: =SUMIFS(FAR!$R$5:$R$64,FAR!$C$5:$C$64,$B6,FAR!$U$5:$U$64,"<>Disposed") | E6: =SUMIFS(FAR!$S$5:$S$64,FAR!$C$5:$C$64,$B6,FAR!$U$5:$U$64,"<>Disposed") | F6: =SUMIFS(FAR!$T$5:$T$64,FAR!$C$5:$C$64,$B6,FAR!$U$5:$U$64,"<>Disposed")
B7: =Input!C16 | C7: =SUMIFS(FAR!$K$5:$K$64,FAR!$C$5:$C$64,$B7,FAR!$U$5:$U$64,"<>Disposed") | D7: =SUMIFS(FAR!$R$5:$R$64,FAR!$C$5:$C$64,$B7,FAR!$U$5:$U$64,"<>Disposed") | E7: =SUMIFS(FAR!$S$5:$S$64,FAR!$C$5:$C$64,$B7,FAR!$U$5:$U$64,"<>Disposed") | F7: =SUMIFS(FAR!$T$5:$T$64,FAR!$C$5:$C$64,$B7,FAR!$U$5:$U$64,"<>Disposed")
B8: =Input!C17 | C8: =SUMIFS(FAR!$K$5:$K$64,FAR!$C$5:$C$64,$B8,FAR!$U$5:$U$64,"<>Disposed") | D8: =SUMIFS(FAR!$R$5:$R$64,FAR!$C$5:$C$64,$B8,FAR!$U$5:$U$64,"<>Disposed") | E8: =SUMIFS(FAR!$S$5:$S$64,FAR!$C$5:$C$64,$B8,FAR!$U$5:$U$64,"<>Disposed") | F8: =SUMIFS(FAR!$T$5:$T$64,FAR!$C$5:$C$64,$B8,FAR!$U$5:$U$64,"<>Disposed")
B9: =Input!C18 | C9: =SUMIFS(FAR!$K$5:$K$64,FAR!$C$5:$C$64,$B9,FAR!$U$5:$U$64,"<>Disposed") | D9: =SUMIFS(FAR!$R$5:$R$64,FAR!$C$5:$C$64,$B9,FAR!$U$5:$U$64,"<>Disposed") | E9: =SUMIFS(FAR!$S$5:$S$64,FAR!$C$5:$C$64,$B9,FAR!$U$5:$U$64,"<>Disposed") | F9: =SUMIFS(FAR!$T$5:$T$64,FAR!$C$5:$C$64,$B9,FAR!$U$5:$U$64,"<>Disposed")
B10: =Input!C19 | C10: =SUMIFS(FAR!$K$5:$K$64,FAR!$C$5:$C$64,$B10,FAR!$U$5:$U$64,"<>Disposed") | D10: =SUMIFS(FAR!$R$5:$R$64,FAR!$C$5:$C$64,$B10,FAR!$U$5:$U$64,"<>Disposed") | E10: =SUMIFS(FAR!$S$5:$S$64,FAR!$C$5:$C$64,$B10,FAR!$U$5:$U$64,"<>Disposed") | F10: =SUMIFS(FAR!$T$5:$T$64,FAR!$C$5:$C$64,$B10,FAR!$U$5:$U$64,"<>Disposed")
B11: =Input!C20 | C11: =SUMIFS(FAR!$K$5:$K$64,FAR!$C$5:$C$64,$B11,FAR!$U$5:$U$64,"<>Disposed") | D11: =SUMIFS(FAR!$R$5:$R$64,FAR!$C$5:$C$64,$B11,FAR!$U$5:$U$64,"<>Disposed") | E11: =SUMIFS(FAR!$S$5:$S$64,FAR!$C$5:$C$64,$B11,FAR!$U$5:$U$64,"<>Disposed") | F11: =SUMIFS(FAR!$T$5:$T$64,FAR!$C$5:$C$64,$B11,FAR!$U$5:$U$64,"<>Disposed")
B12: =Input!C21 | C12: =SUMIFS(FAR!$K$5:$K$64,FAR!$C$5:$C$64,$B12,FAR!$U$5:$U$64,"<>Disposed") | D12: =SUMIFS(FAR!$R$5:$R$64,FAR!$C$5:$C$64,$B12,FAR!$U$5:$U$64,"<>Disposed") | E12: =SUMIFS(FAR!$S$5:$S$64,FAR!$C$5:$C$64,$B12,FAR!$U$5:$U$64,"<>Disposed") | F12: =SUMIFS(FAR!$T$5:$T$64,FAR!$C$5:$C$64,$B12,FAR!$U$5:$U$64,"<>Disposed")
B13: =Input!C22 | C13: =SUMIFS(FAR!$K$5:$K$64,FAR!$C$5:$C$64,$B13,FAR!$U$5:$U$64,"<>Disposed") | D13: =SUMIFS(FAR!$R$5:$R$64,FAR!$C$5:$C$64,$B13,FAR!$U$5:$U$64,"<>Disposed") | E13: =SUMIFS(FAR!$S$5:$S$64,FAR!$C$5:$C$64,$B13,FAR!$U$5:$U$64,"<>Disposed") | F13: =SUMIFS(FAR!$T$5:$T$64,FAR!$C$5:$C$64,$B13,FAR!$U$5:$U$64,"<>Disposed")
B14: =Input!C23 | C14: =SUMIFS(FAR!$K$5:$K$64,FAR!$C$5:$C$64,$B14,FAR!$U$5:$U$64,"<>Disposed") | D14: =SUMIFS(FAR!$R$5:$R$64,FAR!$C$5:$C$64,$B14,FAR!$U$5:$U$64,"<>Disposed") | E14: =SUMIFS(FAR!$S$5:$S$64,FAR!$C$5:$C$64,$B14,FAR!$U$5:$U$64,"<>Disposed") | F14: =SUMIFS(FAR!$T$5:$T$64,FAR!$C$5:$C$64,$B14,FAR!$U$5:$U$64,"<>Disposed")
B15: =Input!C24 | C15: =SUMIFS(FAR!$K$5:$K$64,FAR!$C$5:$C$64,$B15,FAR!$U$5:$U$64,"<>Disposed") | D15: =SUMIFS(FAR!$R$5:$R$64,FAR!$C$5:$C$64,$B15,FAR!$U$5:$U$64,"<>Disposed") | E15: =SUMIFS(FAR!$S$5:$S$64,FAR!$C$5:$C$64,$B15,FAR!$U$5:$U$64,"<>Disposed") | F15: =SUMIFS(FAR!$T$5:$T$64,FAR!$C$5:$C$64,$B15,FAR!$U$5:$U$64,"<>Disposed")
B16: =Input!C25 | C16: =SUMIFS(FAR!$K$5:$K$64,FAR!$C$5:$C$64,$B16,FAR!$U$5:$U$64,"<>Disposed") | D16: =SUMIFS(FAR!$R$5:$R$64,FAR!$C$5:$C$64,$B16,FAR!$U$5:$U$64,"<>Disposed") | E16: =SUMIFS(FAR!$S$5:$S$64,FAR!$C$5:$C$64,$B16,FAR!$U$5:$U$64,"<>Disposed") | F16: =SUMIFS(FAR!$T$5:$T$64,FAR!$C$5:$C$64,$B16,FAR!$U$5:$U$64,"<>Disposed")
B17: =Input!C26 | C17: =SUMIFS(FAR!$K$5:$K$64,FAR!$C$5:$C$64,$B17,FAR!$U$5:$U$64,"<>Disposed") | D17: =SUMIFS(FAR!$R$5:$R$64,FAR!$C$5:$C$64,$B17,FAR!$U$5:$U$64,"<>Disposed") | E17: =SUMIFS(FAR!$S$5:$S$64,FAR!$C$5:$C$64,$B17,FAR!$U$5:$U$64,"<>Disposed") | F17: =SUMIFS(FAR!$T$5:$T$64,FAR!$C$5:$C$64,$B17,FAR!$U$5:$U$64,"<>Disposed")
... B23: =Input!C32 | C23: =SUMIFS(FAR!$K$5:$K$64,FAR!$C$5:$C$64,$B23,FAR!$U$5:$U$64,"<>Disposed") | D23: =SUMIFS(FAR!$R$5:$R$64,FAR!$C$5:$C$64,$B23,FAR!$U$5:$U$64,"<>Disposed") | E23: =SUMIFS(FAR!$S$5:$S$64,FAR!$C$5:$C$64,$B23,FAR!$U$5:$U$64,"<>Disposed") | F23: =SUMIFS(FAR!$T$5:$T$64,FAR!$C$5:$C$64,$B23,FAR!$U$5:$U$64,"<>Disposed")
B24: TOTAL | C24: =SUM(C6:C23) | D24: =SUM(D6:D23) | E24: =SUM(E6:E23) | F24: =SUM(F6:F23)
B26: Check: Gross − Acc. Dep = Net Block | E26: =C24-E24 | F26: =IF(ROUND(E26-F24,0)=0,"OK ✓","CHECK")
B28: DISPOSALS DURING / UP TO REPORTING FY
B29: Asset | C29: Category | D29: Disposal Date | E29: Gross Cost (Rs.) | F29: Sale Proceeds (Rs.)
B30: =FAR!B14 | C30: =FAR!C14 | D30: =FAR!I14 | E30: =FAR!K14 | F30: =FAR!J14

Sheet Income-Tax Dep Chart
B2: INCOME-TAX DEPRECIATION CHART – BLOCK OF ASSETS
B3: Section 32, Income-Tax Act • WDV method on block of assets (Appendix I rates) • 180-day half-rate rule applied automatically from 'Date Put to Use' on FAR
B5: Income-Tax Computation FY (year ending): | E5: 44286 | F5: ↳ Additions of THIS year auto-flow from FAR (≥180 / <180 days). Enter Opening WDV (closing WDV of prior year) and any Additional Depreciation u/s 32(1)(iia) in the yellow cells.
B6: A. BLOCK-OF-ASSETS DEPRECIATION CHART (yellow = your input)
B7: Block of Assets | C7: Rate | D7: Opening WDV | E7: Additions ≥180 days | F7: Additions <180 days | G7: Deletions (Sale) | H7: Normal Dep (full rate) | I7: Dep on <180 (½ rate) | J7: Additional Dep | K7: Total Depreciation | L7: Closing WDV | M7: Remarks
B8: =Input!B36 | C8: =VLOOKUP($B8,ITBlockTable,5,FALSE) | D8: 0 | E8: =SUMIF($C$25:$C$84,$B8,$G$25:$G$84) | F8: =SUMIF($C$25:$C$84,$B8,$H$25:$H$84) | G8: =SUMIF($C$25:$C$84,$B8,$J$25:$J$84) | H8: =MAX(0,($D8+$E8-$G8))*$C8 | I8: =MAX(0,$F8+MIN(0,($D8+$E8-$G8)))*$C8*0.5 | J8: 0 | K8: =IF(($D8+$E8+$F8-$G8)<=0,0,MIN($H8+$I8+$J8,($D8+$E8+$F8-$G8))) | L8: =IF(($D8+$E8+$F8-$G8)<=0,0,($D8+$E8+$F8-$G8)-$K8) | M8: =IF(($D8+$E8-$G8)<0,"Block negative – examine STCG (Sec.50)",IF(AND(($D8+$E8+$F8)=0,$G8>0),"Block ceased",""))
B9: =Input!B37 | C9: =VLOOKUP($B9,ITBlockTable,5,FALSE) | D9: 0 | E9: =SUMIF($C$25:$C$84,$B9,$G$25:$G$84) | F9: =SUMIF($C$25:$C$84,$B9,$H$25:$H$84) | G9: =SUMIF($C$25:$C$84,$B9,$J$25:$J$84) | H9: =MAX(0,($D9+$E9-$G9))*$C9 | I9: =MAX(0,$F9+MIN(0,($D9+$E9-$G9)))*$C9*0.5 | J9: 0 | K9: =IF(($D9+$E9+$F9-$G9)<=0,0,MIN($H9+$I9+$J9,($D9+$E9+$F9-$G9))) | L9: =IF(($D9+$E9+$F9-$G9)<=0,0,($D9+$E9+$F9-$G9)-$K9) | M9: =IF(($D9+$E9-$G9)<0,"Block negative – examine STCG (Sec.50)",IF(AND(($D9+$E9+$F9)=0,$G9>0),"Block ceased",""))
B10: =Input!B38 | C10: =VLOOKUP($B10,ITBlockTable,5,FALSE) | D10: 0 | E10: =SUMIF($C$25:$C$84,$B10,$G$25:$G$84) | F10: =SUMIF($C$25:$C$84,$B10,$H$25:$H$84) | G10: =SUMIF($C$25:$C$84,$B10,$J$25:$J$84) | H10: =MAX(0,($D10+$E10-$G10))*$C10 | I10: =MAX(0,$F10+MIN(0,($D10+$E10-$G10)))*$C10*0.5 | J10: 0 | K10: =IF(($D10+$E10+$F10-$G10)<=0,0,MIN($H10+$I10+$J10,($D10+$E10+$F10-$G10))) | L10: =IF(($D10+$E10+$F10-$G10)<=0,0,($D10+$E10+$F10-$G10)-$K10) | M10: =IF(($D10+$E10-$G10)<0,"Block negative – examine STCG (Sec.50)",IF(AND(($D10+$E10+$F10)=0,$G10>0),"Block ceased",""))
B11: =Input!B39 | C11: =VLOOKUP($B11,ITBlockTable,5,FALSE) | D11: 0 | E11: =SUMIF($C$25:$C$84,$B11,$G$25:$G$84) | F11: =SUMIF($C$25:$C$84,$B11,$H$25:$H$84) | G11: =SUMIF($C$25:$C$84,$B11,$J$25:$J$84) | H11: =MAX(0,($D11+$E11-$G11))*$C11 | I11: =MAX(0,$F11+MIN(0,($D11+$E11-$G11)))*$C11*0.5 | J11: 0 | K11: =IF(($D11+$E11+$F11-$G11)<=0,0,MIN($H11+$I11+$J11,($D11+$E11+$F11-$G11))) | L11: =IF(($D11+$E11+$F11-$G11)<=0,0,($D11+$E11+$F11-$G11)-$K11) | M11: =IF(($D11+$E11-$G11)<0,"Block negative – examine STCG (Sec.50)",IF(AND(($D11+$E11+$F11)=0,$G11>0),"Block ceased",""))
B12: =Input!B40 | C12: =VLOOKUP($B12,ITBlockTable,5,FALSE) | D12: 0 | E12: =SUMIF($C$25:$C$84,$B12,$G$25:$G$84) | F12: =SUMIF($C$25:$C$84,$B12,$H$25:$H$84) | G12: =SUMIF($C$25:$C$84,$B12,$J$25:$J$84) | H12: =MAX(0,($D12+$E12-$G12))*$C12 | I12: =MAX(0,$F12+MIN(0,($D12+$E12-$G12)))*$C12*0.5 | J12: 0 | K12: =IF(($D12+$E12+$F12-$G12)<=0,0,MIN($H12+$I12+$J12,($D12+$E12+$F12-$G12))) | L12: =IF(($D12+$E12+$F12-$G12)<=0,0,($D12+$E12+$F12-$G12)-$K12) | M12: =IF(($D12+$E12-$G12)<0,"Block negative – examine STCG (Sec.50)",IF(AND(($D12+$E12+$F12)=0,$G12>0),"Block ceased",""))
B13: =Input!B41 | C13: =VLOOKUP($B13,ITBlockTable,5,FALSE) | D13: 0 | E13: =SUMIF($C$25:$C$84,$B13,$G$25:$G$84) | F13: =SUMIF($C$25:$C$84,$B13,$H$25:$H$84) | G13: =SUMIF($C$25:$C$84,$B13,$J$25:$J$84) | H13: =MAX(0,($D13+$E13-$G13))*$C13 | I13: =MAX(0,$F13+MIN(0,($D13+$E13-$G13)))*$C13*0.5 | J13: 0 | K13: =IF(($D13+$E13+$F13-$G13)<=0,0,MIN($H13+$I13+$J13,($D13+$E13+$F13-$G13))) | L13: =IF(($D13+$E13+$F13-$G13)<=0,0,($D13+$E13+$F13-$G13)-$K13) | M13: =IF(($D13+$E13-$G13)<0,"Block negative – examine STCG (Sec.50)",IF(AND(($D13+$E13+$F13)=0,$G13>0),"Block ceased",""))
B14: =Input!B42 | C14: =VLOOKUP($B14,ITBlockTable,5,FALSE) | D14: 0 | E14: =SUMIF($C$25:$C$84,$B14,$G$25:$G$84) | F14: =SUMIF($C$25:$C$84,$B14,$H$25:$H$84) | G14: =SUMIF($C$25:$C$84,$B14,$J$25:$J$84) | H14: =MAX(0,($D14+$E14-$G14))*$C14 | I14: =MAX(0,$F14+MIN(0,($D14+$E14-$G14)))*$C14*0.5 | J14: 0 | K14: =IF(($D14+$E14+$F14-$G14)<=0,0,MIN($H14+$I14+$J14,($D14+$E14+$F14-$G14))) | L14: =IF(($D14+$E14+$F14-$G14)<=0,0,($D14+$E14+$F14-$G14)-$K14) | M14: =IF(($D14+$E14-$G14)<0,"Block negative – examine STCG (Sec.50)",IF(AND(($D14+$E14+$F14)=0,$G14>0),"Block ceased",""))
B15: =Input!B43 | C15: =VLOOKUP($B15,ITBlockTable,5,FALSE) | D15: 0 | E15: =SUMIF($C$25:$C$84,$B15,$G$25:$G$84) | F15: =SUMIF($C$25:$C$84,$B15,$H$25:$H$84) | G15: =SUMIF($C$25:$C$84,$B15,$J$25:$J$84) | H15: =MAX(0,($D15+$E15-$G15))*$C15 | I15: =MAX(0,$F15+MIN(0,($D15+$E15-$G15)))*$C15*0.5 | J15: 0 | K15: =IF(($D15+$E15+$F15-$G15)<=0,0,MIN($H15+$I15+$J15,($D15+$E15+$F15-$G15))) | L15: =IF(($D15+$E15+$F15-$G15)<=0,0,($D15+$E15+$F15-$G15)-$K15) | M15: =IF(($D15+$E15-$G15)<0,"Block negative – examine STCG (Sec.50)",IF(AND(($D15+$E15+$F15)=0,$G15>0),"Block ceased",""))
B16: =Input!B44 | C16: =VLOOKUP($B16,ITBlockTable,5,FALSE) | D16: 0 | E16: =SUMIF($C$25:$C$84,$B16,$G$25:$G$84) | F16: =SUMIF($C$25:$C$84,$B16,$H$25:$H$84) | G16: =SUMIF($C$25:$C$84,$B16,$J$25:$J$84) | H16: =MAX(0,($D16+$E16-$G16))*$C16 | I16: =MAX(0,$F16+MIN(0,($D16+$E16-$G16)))*$C16*0.5 | J16: 0 | K16: =IF(($D16+$E16+$F16-$G16)<=0,0,MIN($H16+$I16+$J16,($D16+$E16+$F16-$G16))) | L16: =IF(($D16+$E16+$F16-$G16)<=0,0,($D16+$E16+$F16-$G16)-$K16) | M16: =IF(($D16+$E16-$G16)<0,"Block negative – examine STCG (Sec.50)",IF(AND(($D16+$E16+$F16)=0,$G16>0),"Block ceased",""))
B17: =Input!B45 | C17: =VLOOKUP($B17,ITBlockTable,5,FALSE) | D17: 0 | E17: =SUMIF($C$25:$C$84,$B17,$G$25:$G$84) | F17: =SUMIF($C$25:$C$84,$B17,$H$25:$H$84) | G17: =SUMIF($C$25:$C$84,$B17,$J$25:$J$84) | H17: =MAX(0,($D17+$E17-$G17))*$C17 | I17: =MAX(0,$F17+MIN(0,($D17+$E17-$G17)))*$C17*0.5 | J17: 0 | K17: =IF(($D17+$E17+$F17-$G17)<=0,0,MIN($H17+$I17+$J17,($D17+$E17+$F17-$G17))) | L17: =IF(($D17+$E17+$F17-$G17)<=0,0,($D17+$E17+$F17-$G17)-$K17) | M17: =IF(($D17+$E17-$G17)<0,"Block negative – examine STCG (Sec.50)",IF(AND(($D17+$E17+$F17)=0,$G17>0),"Block ceased",""))
B18: =Input!B46 | C18: =VLOOKUP($B18,ITBlockTable,5,FALSE) | D18: 0 | E18: =SUMIF($C$25:$C$84,$B18,$G$25:$G$84) | F18: =SUMIF($C$25:$C$84,$B18,$H$25:$H$84) | G18: =SUMIF($C$25:$C$84,$B18,$J$25:$J$84) | H18: =MAX(0,($D18+$E18-$G18))*$C18 | I18: =MAX(0,$F18+MIN(0,($D18+$E18-$G18)))*$C18*0.5 | J18: 0 | K18: =IF(($D18+$E18+$F18-$G18)<=0,0,MIN($H18+$I18+$J18,($D18+$E18+$F18-$G18))) | L18: =IF(($D18+$E18+$F18-$G18)<=0,0,($D18+$E18+$F18-$G18)-$K18) | M18: =IF(($D18+$E18-$G18)<0,"Block negative – examine STCG (Sec.50)",IF(AND(($D18+$E18+$F18)=0,$G18>0),"Block ceased",""))
B19: =Input!B47 | C19: =VLOOKUP($B19,ITBlockTable,5,FALSE) | D19: 0 | E19: =SUMIF($C$25:$C$84,$B19,$G$25:$G$84) | F19: =SUMIF($C$25:$C$84,$B19,$H$25:$H$84) | G19: =SUMIF($C$25:$C$84,$B19,$J$25:$J$84) | H19: =MAX(0,($D19+$E19-$G19))*$C19 | I19: =MAX(0,$F19+MIN(0,($D19+$E19-$G19)))*$C19*0.5 | J19: 0 | K19: =IF(($D19+$E19+$F19-$G19)<=0,0,MIN($H19+$I19+$J19,($D19+$E19+$F19-$G19))) | L19: =IF(($D19+$E19+$F19-$G19)<=0,0,($D19+$E19+$F19-$G19)-$K19) | M19: =IF(($D19+$E19-$G19)<0,"Block negative – examine STCG (Sec.50)",IF(AND(($D19+$E19+$F19)=0,$G19>0),"Block ceased",""))
B20: TOTAL | D20: =SUM(D8:D19) | E20: =SUM(E8:E19) | F20: =SUM(F8:F19) | G20: =SUM(G8:G19) | H20: =SUM(H8:H19) | I20: =SUM(I8:I19) | J20: =SUM(J8:J19) | K20: =SUM(K8:K19) | L20: =SUM(L8:L19)
B23: B. ASSET-WISE WORKING (auto-linked to FAR; classifies each addition by the 180-day rule)
B24: Asset | C24: IT Block | D24: Gross Cost | E24: Date Put to Use | F24: Days Used in FY | G24: Addition ≥180 | H24: Addition <180 | I24: Disposal Date | J24: Sale Proceeds (FY)
B25: =IF(FAR!K5="","",FAR!B5) | C25: =IF(FAR!C5="","",IFERROR(VLOOKUP(FAR!C5,ScheduleIITable,5,FALSE),"")) | D25: =IF(FAR!K5="","",FAR!K5) | E25: =IF(FAR!H5="","",FAR!H5) | F25: =IF(AND(FAR!H5<>"",FAR!H5>=(EDATE(ITFYEnd,-12)+1),FAR!H5<=ITFYEnd),ITFYEnd-FAR!H5+1,"") | G25: =IF(AND(FAR!K5<>"",AND(FAR!H5<>"",FAR!H5>=(EDATE(ITFYEnd,-12)+1),FAR!H5<=ITFYEnd),(ITFYEnd-FAR!H5+1)>=180),FAR!K5,0) | H25: =IF(AND(FAR!K5<>"",AND(FAR!H5<>"",FAR!H5>=(EDATE(ITFYEnd,-12)+1),FAR!H5<=ITFYEnd),(ITFYEnd-FAR!H5+1)<180),FAR!K5,0) | I25: =IF(FAR!I5="","",FAR!I5) | J25: =IF(AND(FAR!I5<>"",FAR!I5>=(EDATE(ITFYEnd,-12)+1),FAR!I5<=ITFYEnd),FAR!J5,0)
B26: =IF(FAR!K6="","",FAR!B6) | C26: =IF(FAR!C6="","",IFERROR(VLOOKUP(FAR!C6,ScheduleIITable,5,FALSE),"")) | D26: =IF(FAR!K6="","",FAR!K6) | E26: =IF(FAR!H6="","",FAR!H6) | F26: =IF(AND(FAR!H6<>"",FAR!H6>=(EDATE(ITFYEnd,-12)+1),FAR!H6<=ITFYEnd),ITFYEnd-FAR!H6+1,"") | G26: =IF(AND(FAR!K6<>"",AND(FAR!H6<>"",FAR!H6>=(EDATE(ITFYEnd,-12)+1),FAR!H6<=ITFYEnd),(ITFYEnd-FAR!H6+1)>=180),FAR!K6,0) | H26: =IF(AND(FAR!K6<>"",AND(FAR!H6<>"",FAR!H6>=(EDATE(ITFYEnd,-12)+1),FAR!H6<=ITFYEnd),(ITFYEnd-FAR!H6+1)<180),FAR!K6,0) | I26: =IF(FAR!I6="","",FAR!I6) | J26: =IF(AND(FAR!I6<>"",FAR!I6>=(EDATE(ITFYEnd,-12)+1),FAR!I6<=ITFYEnd),FAR!J6,0)
B27: =IF(FAR!K7="","",FAR!B7) | C27: =IF(FAR!C7="","",IFERROR(VLOOKUP(FAR!C7,ScheduleIITable,5,FALSE),"")) | D27: =IF(FAR!K7="","",FAR!K7) | E27: =IF(FAR!H7="","",FAR!H7) | F27: =IF(AND(FAR!H7<>"",FAR!H7>=(EDATE(ITFYEnd,-12)+1),FAR!H7<=ITFYEnd),ITFYEnd-FAR!H7+1,"") | G27: =IF(AND(FAR!K7<>"",AND(FAR!H7<>"",FAR!H7>=(EDATE(ITFYEnd,-12)+1),FAR!H7<=ITFYEnd),(ITFYEnd-FAR!H7+1)>=180),FAR!K7,0) | H27: =IF(AND(FAR!K7<>"",AND(FAR!H7<>"",FAR!H7>=(EDATE(ITFYEnd,-12)+1),FAR!H7<=ITFYEnd),(ITFYEnd-FAR!H7+1)<180),FAR!K7,0) | I27: =IF(FAR!I7="","",FAR!I7) | J27: =IF(AND(FAR!I7<>"",FAR!I7>=(EDATE(ITFYEnd,-12)+1),FAR!I7<=ITFYEnd),FAR!J7,0)
B28: =IF(FAR!K8="","",FAR!B8) | C28: =IF(FAR!C8="","",IFERROR(VLOOKUP(FAR!C8,ScheduleIITable,5,FALSE),"")) | D28: =IF(FAR!K8="","",FAR!K8) | E28: =IF(FAR!H8="","",FAR!H8) | F28: =IF(AND(FAR!H8<>"",FAR!H8>=(EDATE(ITFYEnd,-12)+1),FAR!H8<=ITFYEnd),ITFYEnd-FAR!H8+1,"") | G28: =IF(AND(FAR!K8<>"",AND(FAR!H8<>"",FAR!H8>=(EDATE(ITFYEnd,-12)+1),FAR!H8<=ITFYEnd),(ITFYEnd-FAR!H8+1)>=180),FAR!K8,0) | H28: =IF(AND(FAR!K8<>"",AND(FAR!H8<>"",FAR!H8>=(EDATE(ITFYEnd,-12)+1),FAR!H8<=ITFYEnd),(ITFYEnd-FAR!H8+1)<180),FAR!K8,0) | I28: =IF(FAR!I8="","",FAR!I8) | J28: =IF(AND(FAR!I8<>"",FAR!I8>=(EDATE(ITFYEnd,-12)+1),FAR!I8<=ITFYEnd),FAR!J8,0)
B29: =IF(FAR!K9="","",FAR!B9) | C29: =IF(FAR!C9="","",IFERROR(VLOOKUP(FAR!C9,ScheduleIITable,5,FALSE),"")) | D29: =IF(FAR!K9="","",FAR!K9) | E29: =IF(FAR!H9="","",FAR!H9) | F29: =IF(AND(FAR!H9<>"",FAR!H9>=(EDATE(ITFYEnd,-12)+1),FAR!H9<=ITFYEnd),ITFYEnd-FAR!H9+1,"") | G29: =IF(AND(FAR!K9<>"",AND(FAR!H9<>"",FAR!H9>=(EDATE(ITFYEnd,-12)+1),FAR!H9<=ITFYEnd),(ITFYEnd-FAR!H9+1)>=180),FAR!K9,0) | H29: =IF(AND(FAR!K9<>"",AND(FAR!H9<>"",FAR!H9>=(EDATE(ITFYEnd,-12)+1),FAR!H9<=ITFYEnd),(ITFYEnd-FAR!H9+1)<180),FAR!K9,0) | I29: =IF(FAR!I9="","",FAR!I9) | J29: =IF(AND(FAR!I9<>"",FAR!I9>=(EDATE(ITFYEnd,-12)+1),FAR!I9<=ITFYEnd),FAR!J9,0)
B30: =IF(FAR!K10="","",FAR!B10) | C30: =IF(FAR!C10="","",IFERROR(VLOOKUP(FAR!C10,ScheduleIITable,5,FALSE),"")) | D30: =IF(FAR!K10="","",FAR!K10) | E30: =IF(FAR!H10="","",FAR!H10) | F30: =IF(AND(FAR!H10<>"",FAR!H10>=(EDATE(ITFYEnd,-12)+1),FAR!H10<=ITFYEnd),ITFYEnd-FAR!H10+1,"") | G30: =IF(AND(FAR!K10<>"",AND(FAR!H10<>"",FAR!H10>=(EDATE(ITFYEnd,-12)+1),FAR!H10<=ITFYEnd),(ITFYEnd-FAR!H10+1)>=180),FAR!K10,0) | H30: =IF(AND(FAR!K10<>"",AND(FAR!H10<>"",FAR!H10>=(EDATE(ITFYEnd,-12)+1),FAR!H10<=ITFYEnd),(ITFYEnd-FAR!H10+1)<180),FAR!K10,0) | I30: =IF(FAR!I10="","",FAR!I10) | J30: =IF(AND(FAR!I10<>"",FAR!I10>=(EDATE(ITFYEnd,-12)+1),FAR!I10<=ITFYEnd),FAR!J10,0)
